Workbook

Sheet Assumptions
A1: Assumptions
A4: Block 1: Per-vehicle activity and energy intensity
A5: Vehicle category | B5: Annual VKT (km/yr) | C5: Energy intensity (kWh/km) | D5: Home-charge share | E5: Use battery swap? | F5: Source / Notes
A6: Motorcycle | B6: =D6*B88+(1-D6)*B89 -> 16296 | C6: 0.03 | D6: 0.5 | E6: YES: Class VKT = home (private-duty) share x private VKT + commercial share x commercial VKT (Block 14). | F6: VKT: SSA boda-boda/okada studies; kWh/km: Average valude from Indonesia Electric Motorcycle Roadmap [https://www.adb.org/sites/default/files/publication/830831/electric-motorcycle-charging-infrastructure-indonesia.pdf]
A7: Private car | B7: 32500 | C7: 0.17 | D7: 0.4 | E7: No | F7: VKT: Cervigni 2013 Ch.21 [https://documents1.worldbank.org/curated/en/333931468332952975/pdf/Assessing-low-carbon-development-in-Nigeria-an-analysis-of-four-sectors.pdf]; kWh/km: Hypercharge [https://hypercharge.com/blog/how-fuel-efficient-are-evs-cost-per-distance-to-drive-electric/]
A8: Light commercial | B8: 20600 | C8: 0.22 | D8: 0.3 | E8: No | F8: VKT: light freight benchmarks [https://www.sciencedirect.com/science/article/abs/pii/S2352550923000635; https://documents1.worldbank.org/curated/en/333931468332952975/pdf/Assessing-low-carbon-development-in-Nigeria-an-analysis-of-four-sectors.pdf]; kWh/km: Our assumption LCV energy intensity of 0.22 kWh/km is consistent with U.S. DOE/EPA EV efficiency benchmarks. The U.S. DOE reports that light-duty all-electric vehicles can consume roughly 25–40 kWh per 100 miles; 0.22 kWh/km converts to about 35.4 kWh/100 miles, which falls within this range [https://afdc.energy.gov/fuels/electricity-benefits]
A9: Heavy goods | B9: 33700 | C9: 1.3 | D9: 0 | E9: No | F9: Heavy-truck Nigeria avg [https://documents1.worldbank.org/curated/en/333931468332952975/pdf/Assessing-low-carbon-development-in-Nigeria-an-analysis-of-four-sectors.pdf]; kWh/km: Designwerk [https://www.designwerk.com/en/post/e-truck/from-real-operation-consumption-values-of-electric-trucks-in-special-applications/]
A10: Light bus | B10: 21400 | C10: 0.7 | D10: 0 | E10: No | F10: The IEA assumes electric minibuses consume 0.35–1.49 kWh/km and our assumption falls within [https://www.iea.org/data-and-statistics/charts/electricity-demand-from-the-electric-vehicle-fleet-by-country-and-region-2030]
A11: Coach | B11: 33200 | C11: 1.5 | D11: 0 | E11: No | F11: Intercity coach activity factors [https://documents1.worldbank.org/curated/en/333931468332952975/pdf/Assessing-low-carbon-development-in-Nigeria-an-analysis-of-four-sectors.pdf]; kWh/km: Alarrouqi et al [https://www.sciencedirect.com/science/article/pii/S235246772400081X]
A14: Block 2: EV adoption S-curve parameters
A15: Vehicle category | B15: t50 (year EV share = 50%) | C15: k (steepness) | F15: Rationale
A16: Motorcycle | B16: 2046.1 | C16: 0.279 | F16: Earliest electrification (Ampersand model already proven in East Africa)
A17: Private car | B17: 2048.4 | C17: 0.254 | F17: Tracks Nigeria ETP middle-of-road
A18: Light commercial | B18: 2049.1 | C18: 0.224 | F18: Commercial fleets follow private LDV with slight lag
A19: Heavy goods | B19: 2053.1 | C19: 0.201 | F19: Most CAPEX-intensive segment; longest payback
A20: Light bus | B20: 2047.3 | C20: 0.233 | F20: Urban fleets electrify early under air-quality mandates
A21: Coach | B21: 2050 | C21: 0.22 | F21: Intercity routes require fast/depot charging; intermediate timing
A24: Block 3: Charger-to-EV ratios
A25: Charger type | B25: EVs per charger
A26: Home L2 | B26: 1.2
A27: Public AC | B27: 12
A28: Public DC fast | B28: 60
A29: Depot HD | B29: 2.5
A30: Swap station (motorcycles per station) | B30: 250
A33: Block 4: Charger CAPEX (USD per port, all-in incl. installation)
A34: Charger type | B34: CAPEX USD/port | C34: Rated power (kW) | D34: Diversity factor
A35: Home L2 | B35: 1500 | C35: 7.4 | D35: 0.2
A36: Public AC | B36: 5500 | C36: 22 | D36: 0.3
A37: Public DC fast | B37: 55000 | C37: 100 | D37: 0.4
A38: Depot HD | B38: 85000 | C38: 250 | D38: 0.6
A39: Swap station | B39: 350000 | C39: 200 | D39: 0.5
A42: Block 5: Grid upgrade unit cost
A43: Grid upgrade USD per kW of new EV peak load | B43: 450
A45: Block 6: Macro inputs (population and GDP_pc for context; not directly used in charging calcs)
A46: Nigeria 2024 GDP/capita (constant 2015 US$; WDI GDP / WPP 2024 population) | B46: ='GDP and Population'!B19 -> 2348.9093 | F46: World Bank [https://data.worldbank.org/indicator/NY.GDP.PCAP.PP.CD?locations=NG]
A47: Assumed real GDP/capita growth, 2024-2060 (CAGR) | B47: 0.025 | F47: Moderate convergence; sensitivity-tested
A48: Nigeria 2060 population (M; UN WPP 2024 medium, 1 January) | B48: ='GDP and Population'!D55 -> 397.91185 | F48: UN DESA WPP [https://population.un.org/wpp/]
A50: Block 7: Level 1 (Mode 2 socket) home charging
A51: Level 1 share of LDV home charging | B51: 0.7 | C51: Share of car/LCV home charging done on a standard 230 V socket (Level 1, Mode 2) rather than a dedicated 7 kW Level 2 unit. IEA GEVO 2024: socket charging is the most common home mode in 220-240 V grids.
A52: EVs per Level 1 socket | B52: 1 | C52: One socket per home-charging vehicle.
A53: Level 1 CAPEX (USD per socket incl. Mode 2 cable) | B53: 200 | C53: IEA GEVO 2024: dedicated home charger "several hundred USD"; Mode 2 cable + certified socket is the lower bound.
A54: Level 1 rated power (kW) | B54: 2.3
A55: Level 1 diversity factor | B55: 0.3 | C55: Share of sockets drawing full power at system peak (uncontrolled).
A56: Motorcycle home charging on Level 1 sockets (share of home-charged e-2W) | B56: 1 | C56: Private e-2W/3W batteries (<8 kWh) fully charge overnight on a standard socket
A58: Block 8: Generation-side factors
A59: Generation-side gross-up for network losses and delivery risk | B59: 1.2 | C59: Applied to at-wall demand when converting to dispatched generation (Eq. 4). Conservative relative to physical T&D losses; see Section 3.4.
A60: Smart-charging load factor LF (average / peak) | B60: ='Load profile'!B32 -> 0.60814349 | C60: Derived on the "Load profile" sheet from an explicit hourly charging profile under managed charging.
A61: Uniform charging-loss uplift (at-wall / battery-side traction energy) | B61: 1.09 | C61: A uniform 9% uplift is applied to battery-side traction energy for every vehicle class. The model does not apply charger-route-specific loss factors.
A62: Intercategory coincidence factor applied after charger diversity factors | B62: 0.9 | C62: Diversity factors describe simultaneous use within each charger category. This factor allows category-specific peaks not to align perfectly. Set to 1.00 to remove the adjustment; the 0.90-to-1.00 range is sensitivity-tested.
A63: Block 9: Vehicle-to-grid (V2G) capacity calculation
A64: Share of private-car and LCV EV stock enrolled in V2G | B64: 0.1 | C64: Conservative enrolment assumption; Dioha et al. (2022) show benefits do not require full participation.
A65: Availability factor (plugged-in and dispatchable at system peak) | B65: 0.3 | C65: Dioha et al. (2022, iScience) vary the share of parked grid-connected vehicles between 10% and 70%; 30% is a conservative mid-low value.
A66: Bidirectional charger power (kW) | B66: 7 | C66: Typical residential bidirectional AC charger
A68: Block 10: Battery-swap station operating parameters (energy-delivery check)
A69: Energy per swap (kWh) | B69: 3.24 | C69: Ampersand LFP pack 3.24 kWh (2025, operator-reported).
A70: Operator-reported swap frequency (context only; not used in model) | B70: n.a. | C70: Reported swaps per motorcycle vary by operator and are not used as an energy input. Annual motorcycle energy is determined from VKT multiplied by kWh/km; the delivery check converts assigned energy into full-battery-equivalent swaps.
A71: Station operating days per year | B71: 365
A72: Maximum feasible full-battery-equivalent swaps per station per day | B72: 900 | C72: Capacity benchmark used only in the aggregate annual energy-throughput check. One equivalent swap is 3.24 kWh; actual transactions may replenish partial batteries.
A74: Block 11: Charger utilisation caps for energy-delivery check
A75: Home L1 max annual utilisation (share of hours at rated kW) | B75: 0.35 | C75: About 8 h/day overnight.
A76: Home L2 max annual utilisation | B76: 0.3
A77: Public AC max annual utilisation | B77: 0.25
A78: Public DC fast max annual utilisation | B78: 0.3 | C78: ICCT: well-utilised DC fast sites reach 20-35% time utilisation.
A79: Depot HD max annual utilisation | B79: 0.4 | C79: Overnight depot charging ~10 h/day.
A81: Block 12: Fleet-composition sensitivity (buses gain share from private cars)
A82: Share of 2060 private-car stock displaced by mass transit | B82: 0.1 | C82: Alternative-composition case: 10% of private-car stock is displaced by light buses on a passenger-capacity-neutral basis (Assumptions B83 car-equivalents per bus). Applied on the "Composition sensitivity" sheet.
A83: Private-car equivalents replaced per additional light bus (passenger-capacity basis) | B83: =(B10*40*0.6)/(B7*1.5) -> 10.535385 | C83: A 40-seat urban bus at a 60% load factor carries 24 passengers. At 1.5 occupants per private car, the passenger-capacity-neutral ratio is 24 / 1.5 = 16 cars per bus.
A84: Block 13: Scenario growth-rate construction (see Fleet projections)
A85: Income elasticity of vehicle ownership at 2060 (Scenario C terminal rate) | B85: 0.9 | C85: Terminal CAGR (Scenario C) = population growth + elasticity x GDP/cap growth. Dargay, Gately & Sommer (2007) report elasticities near 1 at low-middle income, declining toward saturation.
A87: Block 14: Motorcycle/tricycle class VKT derivation (WB Table 21.5 duty cycles)
A88: Private-duty motorcycle VKT (km/yr), WB Table 21.5 | B88: 7659 | C88: Cervigni et al. (2013) Table 21.5, private motorcycle.
A89: Commercial-duty (okada/keke) VKT (km/yr), WB Table 21.5 tricycle | B89: 24933 | C89: Cervigni et al. (2013) Table 21.5, tricycle (commercial passenger duty cycle). Spiro operator data (150-200 km/day, East Africa) imply higher values for full-time riders; 24,933 km/yr (~80 km/day) is retained as a conservative Nigerian commercial duty cycle.
A91: Block 15: Complete-electrification variant
A92: Force 100% EV stock share in 2060 (1 = yes, 0 = central case) | B92: 0 | C92: When 1, each class logistic is divided by its own 2060 value so the stock share reaches exactly 100% in 2060 (shape, t50 and k unchanged; intermediate years rise by up to 25% for HGV).

Sheet GDP and Population
A1: GDP per capita (constant 2015 US$) and population, Nigeria 2010 to 2060
A2: GDP per capita (constant 2015 US$) = World Bank WDI GDP divided by UN WPP 2024 population; population to 2060 = UN WPP 2024 medium variant
A4: Year | B4: GDP/cap (constant 2015 US$) | C4: GDP (constant 2015 US$) | D4: Population (M) | E4: GDP/cap growth (yoy) | F4: Pop growth (yoy)
A5: 2010 | B5: =C5/(D5*1000000) -> 2348.4232 | C5: 3.8585606e+11 | D5: 164.30431
A6: 2011 | B6: =C6/(D6*1000000) -> 2404.6249 | C6: 4.0633701e+11 | D6: 168.98146 | E6: =B6/B5-1 -> 0.023931652 | F6: =D6/D5-1 -> 0.028466343
A7: 2012 | B7: =C7/(D7*1000000) -> 2437.1667 | C7: 4.2352532e+11 | D7: 173.77774 | E7: =B7/B6-1 -> 0.013533022 | F7: =D7/D6-1 -> 0.028383475
A8: 2013 | B8: =C8/(D8*1000000) -> 2529.2309 | C8: 4.5178011e+11 | D8: 178.62351 | E8: =B8/B7-1 -> 0.03777511 | F8: =D8/D7-1 -> 0.027884889
A9: 2014 | B9: =C9/(D9*1000000) -> 2617.7146 | C9: 4.8028616e+11 | D9: 183.47538 | E9: =B9/B8-1 -> 0.034984406 | F9: =D9/D8-1 -> 0.027162516
A10: 2015 | B10: =C10/(D10*1000000) -> 2618.0476 | C10: 4.9302668e+11 | D10: 188.31846 | E10: =B10/B9-1 -> 0.00012722583 | F10: =D10/D9-1 -> 0.026396349
A11: 2016 | B11: =C11/(D11*1000000) -> 2512.9094 | C11: 4.8505509e+11 | D11: 193.0253 | E11: =B11/B10-1 -> -0.040159029 | F11: =D11/D10-1 -> 0.024994077
A12: 2017 | B12: =C12/(D12*1000000) -> 2471.2367 | C12: 4.8896408e+11 | D12: 197.8621 | E12: =B12/B11-1 -> -0.016583433 | F12: =D12/D11-1 -> 0.025057845
A13: 2018 | B13: =C13/(D13*1000000) -> 2459.2791 | C13: 4.9836567e+11 | D13: 202.64706 | E13: =B13/B12-1 -> -0.0048387131 | F13: =D13/D12-1 -> 0.024183303
A14: 2019 | B14: =C14/(D14*1000000) -> 2457.9965 | C14: 5.0937173e+11 | D14: 207.23045 | E14: =B14/B13-1 -> -0.00052152586 | F14: =D14/D13-1 -> 0.022617614
A15: 2020 | B15: =C15/(D15*1000000) -> 2252.4251 | C15: 4.7693036e+11 | D15: 211.74083 | E15: =B15/B14-1 -> -0.083633737 | F15: =D15/D14-1 -> 0.021765045
A16: 2021 | B16: =C16/(D16*1000000) -> 2229.9066 | C16: 4.8222072e+11 | D16: 216.25153 | E16: =B16/B15-1 -> -0.0099974296 | F16: =D16/D15-1 -> 0.02130293
A17: 2022 | B17: =C17/(D17*1000000) -> 2278.22 | C17: 5.0304701e+11 | D17: 220.80704 | E17: =B17/B16-1 -> 0.021666084 | F17: =D17/D16-1 -> 0.021065798
... A19: 2024 | B19: =C19/(D19*1000000) -> 2348.9093 | C19: 5.4088602e+11 | D19: 230.27114 | E19: =B19/B18-1 -> 0.019123756 | F19: =D19/D18-1 -> 0.021181832
A20: 2025 | B20: =B19*(1+Assumptions!$B$47) -> 2407.632 | D20: 235.08781 | E20: =B20/B19-1 -> 0.025 | F20: =D20/D19-1 -> 0.020917398
A21: 2026 | B21: =B20*(1+Assumptions!$B$47) -> 2467.8228 | D21: 239.96775 | E21: =B21/B20-1 -> 0.025 | F21: =D21/D20-1 -> 0.020757924
A22: 2027 | B22: =B21*(1+Assumptions!$B$47) -> 2529.5184 | D22: 244.89592 | E22: =B22/B21-1 -> 0.025 | F22: =D22/D21-1 -> 0.020536785
A23: 2028 | B23: =B22*(1+Assumptions!$B$47) -> 2592.7564 | D23: 249.85261 | E23: =B23/B22-1 -> 0.025 | F23: =D23/D22-1 -> 0.020240007
A24: 2029 | B24: =B23*(1+Assumptions!$B$47) -> 2657.5753 | D24: 254.83964 | E24: =B24/B23-1 -> 0.025 | F24: =D24/D23-1 -> 0.019959908
A25: 2030 | B25: =B24*(1+Assumptions!$B$47) -> 2724.0146 | D25: 259.86563 | E25: =B25/B24-1 -> 0.025 | F25: =D25/D24-1 -> 0.019722151
A26: 2031 | B26: =B25*(1+Assumptions!$B$47) -> 2792.115 | D26: 264.89631 | E26: =B26/B25-1 -> 0.025 | F26: =D26/D25-1 -> 0.019358762
A27: 2032 | B27: =B26*(1+Assumptions!$B$47) -> 2861.9179 | D27: 269.94584 | E27: =B27/B26-1 -> 0.025 | F27: =D27/D26-1 -> 0.0190623
A28: 2033 | B28: =B27*(1+Assumptions!$B$47) -> 2933.4658 | D28: 275.02144 | E28: =B28/B27-1 -> 0.025 | F28: =D28/D27-1 -> 0.018802297
A29: 2034 | B29: =B28*(1+Assumptions!$B$47) -> 3006.8025 | D29: 280.08879 | E29: =B29/B28-1 -> 0.025 | F29: =D29/D28-1 -> 0.018425269
A30: 2035 | B30: =B29*(1+Assumptions!$B$47) -> 3081.9725 | D30: 285.15601 | E30: =B30/B29-1 -> 0.025 | F30: =D30/D29-1 -> 0.018091478
A31: 2036 | B31: =B30*(1+Assumptions!$B$47) -> 3159.0219 | D31: 290.21552 | E31: =B31/B30-1 -> 0.025 | F31: =D31/D30-1 -> 0.017742958
... A55: 2060 | B55: =B54*(1+Assumptions!$B$47) -> 5713.8048 | D55: 397.91185 | E55: =B55/B54-1 -> 0.025 | F55: =D55/D54-1 -> 0.0096546472

Sheet Gompertz fit
A1: Gompertz fit of Nigerian vehicle ownership vs GDP per capita (one estimated 2010 anchor and two observed NBS counts)
A3: Inputs
A12: gamma (saturation ceiling, vehicles per 1,000 persons): | B12: 300 | C12: Dargay, Gately & Sommer (2007) high-income asymptote 850 (652 cars); South Africa ~176, Morocco ~112 today. 300 is an intermediate ceiling; sensitivity 225-375 (+/-25%).
A14: Anchor data (2010: World Bank base-year estimate; 2017 and 2018: observed NBS counts)
A15: Year | B15: Vehicle stock (M) | C15: Population (M) | D15: GDP/cap (const. 2015 US$) | E15: V/P (per 1000) | F15: V/(P*gamma) | G15: LN(V/(P*gamma)) | H15: y_lin = LN(-LN(V/(P*gamma)))
A16: 2010 | B16: 8.671474 | C16: ='GDP and Population'!D5 -> 164.30431 | D16: ='GDP and Population'!B5 -> 2348.4232 | E16: =B16*1000/C16 -> 52.77691 | F16: =E16/$B$12 -> 0.17592303 | G16: =LN(F16) -> -1.7377087 | H16: =LN(-G16) -> 0.5525674 | I16: World Bank Cervigni et al. (2013) Table 22.4 base year (SLA 2005 uplifted)
A17: 2017 | B17: 11.45837 | C17: ='GDP and Population'!D12 -> 197.8621 | D17: ='GDP and Population'!B12 -> 2471.2367 | E17: =B17*1000/C17 -> 57.910889 | F17: =E17/$B$12 -> 0.1930363 | G17: =LN(F17) -> -1.644877 | H17: =LN(-G17) -> 0.49766564 | I17: NBS Road Transport Data Q1 2017 (vehicle population)
A18: 2018 | B18: 11.826033 | C18: ='GDP and Population'!D13 -> 202.64706 | D18: ='GDP and Population'!B13 -> 2459.2791 | E18: =B18*1000/C18 -> 58.357783 | F18: =E18/$B$12 -> 0.19452594 | G18: =LN(F18) -> -1.6371897 | H18: =LN(-G18) -> 0.4929812 | I18: NBS Road Transport Data Q4 2018 (vehicle population; last official total)
A20: Linearised regression (LINEST with statistics)
A21: Slope (= beta): | B21: =INDEX(LINEST(H16:H18,D16:D18,TRUE(),TRUE()),1,1) -> -0.00048308424
A22: Intercept (= LN(-alpha)): | B22: =INDEX(LINEST(H16:H18,D16:D18,TRUE(),TRUE()),1,2) -> 1.6865183
A23: SE of slope: | B23: =STEYX(H16:H18,D16:D18)/SQRT(DEVSQ(D16:D18)) -> 7.754087e-05
A24: Fitted alpha (= -EXP(intercept)): | B24: =-EXP(B22) -> -5.4006446
A25: Fitted beta (= slope): | B25: =B21 -> -0.00048308424
A26: R^2 (linearised): | B26: =INDEX(LINEST(H16:H18,D16:D18,TRUE(),TRUE()),3,1) -> 0.97488298
A27: SE of intercept: | B27: =INDEX(LINEST(H16:H18,D16:D18,TRUE(),TRUE()),2,2) -> 0.18818727
A28: Degrees of freedom: | B28: =INDEX(LINEST(H16:H18,D16:D18,TRUE(),TRUE()),4,2) -> 1
A29: t-statistic (beta): | B29: =B21/B23 -> -6.2300596
A30: 95% CI beta (lower, upper): | B30: =B21-TINV(0.05,B28)*B23 -> -0.0014683344 | C30: =B21+TINV(0.05,B28)*B23 -> 0.00050216593
A32: With three anchors (one estimated, two observed) and two parameters there is one degree of freedom; the parameters are weakly identified and confidence intervals are wide. We therefore treat the saturation ceiling gamma as the primary uncertainty (225-375 sensitivity) rather than relying on the statistical precision of alpha and beta.
A34: Fit quality at anchor years
A35: Year | B35: Actual V/1000 | C35: Predicted V/1000 | D35: Residual | E35: % error
A36: =A16 -> 2010 | B36: =E16 -> 52.77691 | C36: =$B$12*EXP($B$24*EXP($B$25*D16)) -> 52.826015 | D36: =B36-C36 -> -0.049104456 | E36: =D36/B36 -> -0.00093041553
A37: =A17 -> 2017 | B37: =E17 -> 57.910889 | C37: =$B$12*EXP($B$24*EXP($B$25*D17)) -> 58.384383 | D37: =B37-C37 -> -0.47349424 | E37: =D37/B37 -> -0.0081762559
A38: =A18 -> 2018 | B38: =E18 -> 58.357783 | C38: =$B$12*EXP($B$24*EXP($B$25*D18)) -> 57.833398 | D38: =B38-C38 -> 0.52438448 | E38: =D38/B38 -> 0.008985682

Sheet Fleet projections
A1: Annual fleet projections 2010 to 2060, anchored on the 2010 base-year estimate and observed NBS counts
A2: Phase 1 (2010-2018): geometric interpolation between the anchors (WB base-year 2010 estimate; observed NBS counts 2017, 2018). Bridge (2019-2024): anchor-derived 2010-2018 CAGR (NBS discontinued the vehicle-population series after Q4 2018). Phase 2 (2025-2060): Scenario A = constant CAGR at the World Bank 2013-implied 2010-2035 rate (upper bound); Scenario B = Gompertz (gamma = 300) fitted to observed anchors and driven by GDP/cap and population (central); Scenario C = CAGR declining linearly from the observed rate to a terminal rate equal to population growth plus income-elasticity x GDP/cap growth (lower bound). The World Bank 2013 projection is shown for comparison only.
A4: Vehicle-stock anchors (2010 estimate; 2017 and 2018 observed NBS counts)
A5: Year | B5: Total fleet (M) | C5: Source
A6: 2010 | B6: 8.671474 | C6: World Bank Cervigni et al. (2013) Table 22.4 base year
A7: 2017 | B7: 11.45837 | C7: NBS Road Transport Data Q1 2017 (vehicle population)
A8: 2018 | B8: 11.826033 | C8: NBS Road Transport Data Q4 2018 (vehicle population; last official total)
A10: Growth-rate parameters
A11: Anchor-derived CAGR 2010-2018: | B11: =(B8/B6)^(1/8)-1 -> 0.039544943
A12: Scenario A CAGR (WB 2013-implied 2010-2035): | B12: =(44.79147/8.671474)^(1/25)-1 -> 0.067884039 | C12: Cervigni et al. (2013) Table 22.4: 8.671M (2010) to 44.791M (2035). Editable.
A13: Scenario C starting CAGR (2025): | B13: =B11 -> 0.039544943
A14: Scenario C terminal CAGR (2060): | B14: =('GDP and Population'!D55/'GDP and Population'!D54-1)+Assumptions!$B$85*Assumptions!$B$47 -> 0.032154647 | C14: Population growth 2059-60 (UN WPP 2024) + income elasticity (Assumptions B85) x real GDP/cap growth (Assumptions B47).
A15: Scenario B anchor scaling factor (bridged 2024 fleet / Gompertz fit at 2024): | B15: =D32/(H32*G32/1000) -> 1.226406
A16: Annual projections (vehicles, millions)
A17: Year | B17: Anchored (2010-2018) / bridged (2019-2024) (M) | C17: Scenario A (upper) | D17: Scenario B (central, Gompertz) | E17: Scenario C (lower) | F17: B: GDP/cap | G17: B: Population (M) | H17: B: V/1000 | I17: C: CAGR this year | J17: WB 2013 projection (M)
A18: 2010 | B18: =$B$6 -> 8.671474 | C18: =B18 -> 8.671474 | D18: =B18 -> 8.671474 | E18: =B18 -> 8.671474 | F18: ='GDP and Population'!B5 -> 2348.4232 | G18: ='GDP and Population'!D5 -> 164.30431 | H18: ='Gompertz fit'!$B$12*EXP('Gompertz fit'!$B$24*EXP('Gompertz fit'!$B$25*F18)) -> 52.826015 | J18: 8.671474
A19: 2011 | B19: =$B$6*($B$7/$B$6)^(0.142857) -> 9.0236636 | C19: =B19 -> 9.0236636 | D19: =B19 -> 9.0236636 | E19: =B19 -> 9.0236636 | F19: ='GDP and Population'!B6 -> 2404.6249 | G19: ='GDP and Population'!D6 -> 168.98146 | H19: ='Gompertz fit'!$B$12*EXP('Gompertz fit'!$B$24*EXP('Gompertz fit'!$B$25*F19)) -> 55.341505 | J19: 9.3101
A20: 2012 | B20: =$B$6*($B$7/$B$6)^(0.285714) -> 9.3901573 | C20: =B20 -> 9.3901573 | D20: =B20 -> 9.3901573 | E20: =B20 -> 9.3901573 | F20: ='GDP and Population'!B7 -> 2437.1667 | G20: ='GDP and Population'!D7 -> 173.77774 | H20: ='Gompertz fit'!$B$12*EXP('Gompertz fit'!$B$24*EXP('Gompertz fit'!$B$25*F20)) -> 56.819924 | J20: 9.9957
A21: 2013 | B21: =$B$6*($B$7/$B$6)^(0.428571) -> 9.771536 | C21: =B21 -> 9.771536 | D21: =B21 -> 9.771536 | E21: =B21 -> 9.771536 | F21: ='GDP and Population'!B8 -> 2529.2309 | G21: ='GDP and Population'!D8 -> 178.62351 | H21: ='Gompertz fit'!$B$12*EXP('Gompertz fit'!$B$24*EXP('Gompertz fit'!$B$25*F21)) -> 61.085038 | J21: 10.7318
A22: 2014 | B22: =$B$6*($B$7/$B$6)^(0.571429) -> 10.168407 | C22: =B22 -> 10.168407 | D22: =B22 -> 10.168407 | E22: =B22 -> 10.168407 | F22: ='GDP and Population'!B9 -> 2617.7146 | G22: ='GDP and Population'!D9 -> 183.47538 | H22: ='Gompertz fit'!$B$12*EXP('Gompertz fit'!$B$24*EXP('Gompertz fit'!$B$25*F22)) -> 65.291569 | J22: 11.5221
A23: 2015 | B23: =$B$6*($B$7/$B$6)^(0.714286) -> 10.581394 | C23: =B23 -> 10.581394 | D23: =B23 -> 10.581394 | E23: =B23 -> 10.581394 | F23: ='GDP and Population'!B10 -> 2618.0476 | G23: ='GDP and Population'!D10 -> 188.31846 | H23: ='Gompertz fit'!$B$12*EXP('Gompertz fit'!$B$24*EXP('Gompertz fit'!$B$25*F23)) -> 65.307588 | J23: 12.3706
A24: 2016 | B24: =$B$6*($B$7/$B$6)^(0.857143) -> 11.011155 | C24: =B24 -> 11.011155 | D24: =B24 -> 11.011155 | E24: =B24 -> 11.011155 | F24: ='GDP and Population'!B11 -> 2512.9094 | G24: ='GDP and Population'!D11 -> 193.0253 | H24: ='Gompertz fit'!$B$12*EXP('Gompertz fit'!$B$24*EXP('Gompertz fit'!$B$25*F24)) -> 60.320303 | J24: 13.2816
A25: 2017 | B25: =$B$7 -> 11.45837 | C25: =B25 -> 11.45837 | D25: =B25 -> 11.45837 | E25: =B25 -> 11.45837 | F25: ='GDP and Population'!B12 -> 2471.2367 | G25: ='GDP and Population'!D12 -> 197.8621 | H25: ='Gompertz fit'!$B$12*EXP('Gompertz fit'!$B$24*EXP('Gompertz fit'!$B$25*F25)) -> 58.384383 | J25: 14.2596
A26: 2018 | B26: =$B$8 -> 11.826033 | C26: =B26 -> 11.826033 | D26: =B26 -> 11.826033 | E26: =B26 -> 11.826033 | F26: ='GDP and Population'!B13 -> 2459.2791 | G26: ='GDP and Population'!D13 -> 202.64706 | H26: ='Gompertz fit'!$B$12*EXP('Gompertz fit'!$B$24*EXP('Gompertz fit'!$B$25*F26)) -> 57.833398 | J26: 15.3098
A27: 2019 | B27: =B26*(1+$B$11) -> 12.293693 | C27: =B27 -> 12.293693 | D27: =B27 -> 12.293693 | E27: =B27 -> 12.293693 | F27: ='GDP and Population'!B14 -> 2457.9965 | G27: ='GDP and Population'!D14 -> 207.23045 | H27: ='Gompertz fit'!$B$12*EXP('Gompertz fit'!$B$24*EXP('Gompertz fit'!$B$25*F27)) -> 57.774421 | J27: 16.4372
A28: 2020 | B28: =B27*(1+$B$11) -> 12.779846 | C28: =B28 -> 12.779846 | D28: =B28 -> 12.779846 | E28: =B28 -> 12.779846 | F28: ='GDP and Population'!B15 -> 2252.4251 | G28: ='GDP and Population'!D15 -> 211.74083 | H28: ='Gompertz fit'!$B$12*EXP('Gompertz fit'!$B$24*EXP('Gompertz fit'!$B$25*F28)) -> 48.645705 | J28: 17.647653
A29: 2021 | B29: =B28*(1+$B$11) -> 13.285224 | C29: =B29 -> 13.285224 | D29: =B29 -> 13.285224 | E29: =B29 -> 13.285224 | F29: ='GDP and Population'!B16 -> 2229.9066 | G29: ='GDP and Population'!D16 -> 216.25153 | H29: ='Gompertz fit'!$B$12*EXP('Gompertz fit'!$B$24*EXP('Gompertz fit'!$B$25*F29)) -> 47.687317 | J29: 18.8382
A30: 2022 | B30: =B29*(1+$B$11) -> 13.810588 | C30: =B30 -> 13.810588 | D30: =B30 -> 13.810588 | E30: =B30 -> 13.810588 | F30: ='GDP and Population'!B17 -> 2278.22 | G30: ='GDP and Population'!D17 -> 220.80704 | H30: ='Gompertz fit'!$B$12*EXP('Gompertz fit'!$B$24*EXP('Gompertz fit'!$B$25*F30)) -> 49.754074 | J30: 20.109
A31: 2023 | B31: =B30*(1+$B$11) -> 14.356727 | C31: =B31 -> 14.356727 | D31: =B31 -> 14.356727 | E31: =B31 -> 14.356727 | F31: ='GDP and Population'!B18 -> 2304.8322 | G31: ='GDP and Population'!D18 -> 225.49475 | H31: ='Gompertz fit'!$B$12*EXP('Gompertz fit'!$B$24*EXP('Gompertz fit'!$B$25*F31)) -> 50.909151 | J31: 21.4656
A32: 2024 | B32: =B31*(1+$B$11) -> 14.924463 | C32: =B32 -> 14.924463 | D32: =B32 -> 14.924463 | E32: =B32 -> 14.924463 | F32: ='GDP and Population'!B19 -> 2348.9093 | G32: ='GDP and Population'!D19 -> 230.27114 | H32: ='Gompertz fit'!$B$12*EXP('Gompertz fit'!$B$24*EXP('Gompertz fit'!$B$25*F32)) -> 52.84756 | J32: 22.9137
A33: 2025 | C33: =C32*(1+$B$12) -> 15.937596 | D33: =$D$32*(H33*G33)/($H$32*$G$32) -> 15.994879 | E33: =E32*(1+I33) -> 15.511586 | F33: ='GDP and Population'!B20 -> 2407.632 | G33: ='GDP and Population'!D20 -> 235.08781 | H33: ='Gompertz fit'!$B$12*EXP('Gompertz fit'!$B$24*EXP('Gompertz fit'!$B$25*F33)) -> 55.477462 | I33: =$B$13+(0.027778)*($B$14-$B$13) -> 0.039339655 | J33: 24.4595
A34: 2026 | C34: =C33*(1+$B$12) -> 17.019504 | D34: =$D$32*(H34*G34)/($H$32*$G$32) -> 17.136044 | E34: =E33*(1+I34) -> 16.118622 | F34: ='GDP and Population'!B21 -> 2467.8228 | G34: ='GDP and Population'!D21 -> 239.96775 | H34: ='Gompertz fit'!$B$12*EXP('Gompertz fit'!$B$24*EXP('Gompertz fit'!$B$25*F34)) -> 58.226869 | I34: =$B$13+(0.055556)*($B$14-$B$13) -> 0.039134368 | J34: 26.1096
A35: 2027 | C35: =C34*(1+$B$12) -> 18.174857 | D35: =$D$32*(H35*G35)/($H$32*$G$32) -> 18.350446 | E35: =E34*(1+I35) -> 16.746105 | F35: ='GDP and Population'!B22 -> 2529.5184 | G35: ='GDP and Population'!D22 -> 244.89592 | H35: ='Gompertz fit'!$B$12*EXP('Gompertz fit'!$B$24*EXP('Gompertz fit'!$B$25*F35)) -> 61.098539 | I35: =$B$13+(0.083333)*($B$14-$B$13) -> 0.038929087 | J35: 27.871
A36: 2028 | C36: =C35*(1+$B$12) -> 19.408639 | D36: =$D$32*(H36*G36)/($H$32*$G$32) -> 19.640025 | E36: =E35*(1+I36) -> 17.394578 | F36: ='GDP and Population'!B23 -> 2592.7564 | G36: ='GDP and Population'!D23 -> 249.85261 | H36: ='Gompertz fit'!$B$12*EXP('Gompertz fit'!$B$24*EXP('Gompertz fit'!$B$25*F36)) -> 64.094963 | I36: =$B$13+(0.111111)*($B$14-$B$13) -> 0.0387238 | J36: 29.7512
A37: 2029 | C37: =C36*(1+$B$12) -> 20.726176 | D37: =$D$32*(H37*G37)/($H$32*$G$32) -> 21.008205 | E37: =E36*(1+I37) -> 18.064591 | F37: ='GDP and Population'!B24 -> 2657.5753 | G37: ='GDP and Population'!D24 -> 254.83964 | H37: ='Gompertz fit'!$B$12*EXP('Gompertz fit'!$B$24*EXP('Gompertz fit'!$B$25*F37)) -> 67.218329 | I37: =$B$13+(0.138889)*($B$14-$B$13) -> 0.038518512 | J37: 31.7583
A38: 2030 | C38: =C37*(1+$B$12) -> 22.133153 | D38: =$D$32*(H38*G38)/($H$32*$G$32) -> 22.458992 | E38: =E37*(1+I38) -> 18.756704 | F38: ='GDP and Population'!B25 -> 2724.0146 | G38: ='GDP and Population'!D25 -> 259.86563 | H38: ='Gompertz fit'!$B$12*EXP('Gompertz fit'!$B$24*EXP('Gompertz fit'!$B$25*F38)) -> 70.470471 | I38: =$B$13+(0.166667)*($B$14-$B$13) -> 0.038313224 | J38: 33.90072
A39: 2031 | C39: =C38*(1+$B$12) -> 23.635641 | D39: =$D$32*(H39*G39)/($H$32*$G$32) -> 23.9926 | E39: =E38*(1+I39) -> 19.471484 | F39: ='GDP and Population'!B26 -> 2792.115 | G39: ='GDP and Population'!D26 -> 264.89631 | H39: ='Gompertz fit'!$B$12*EXP('Gompertz fit'!$B$24*EXP('Gompertz fit'!$B$25*F39)) -> 73.852834 | I39: =$B$13+(0.194444)*($B$14-$B$13) -> 0.038107944 | J39: 35.8432
A40: 2032 | C40: =C39*(1+$B$12) -> 25.240123 | D40: =$D$32*(H40*G40)/($H$32*$G$32) -> 25.613174 | E40: =E39*(1+I40) -> 20.209505 | F40: ='GDP and Population'!B27 -> 2861.9179 | G40: ='GDP and Population'!D27 -> 269.94584 | H40: ='Gompertz fit'!$B$12*EXP('Gompertz fit'!$B$24*EXP('Gompertz fit'!$B$25*F40)) -> 77.366422 | I40: =$B$13+(0.222222)*($B$14-$B$13) -> 0.037902657 | J40: 37.8969
A41: 2033 | C41: =C40*(1+$B$12) -> 26.953525 | D41: =$D$32*(H41*G41)/($H$32*$G$32) -> 27.324289 | E41: =E40*(1+I41) -> 20.97135 | F41: ='GDP and Population'!B28 -> 2933.4658 | G41: ='GDP and Population'!D28 -> 275.02144 | H41: ='Gompertz fit'!$B$12*EXP('Gompertz fit'!$B$24*EXP('Gompertz fit'!$B$25*F41)) -> 81.01176 | I41: =$B$13+(0.25)*($B$14-$B$13) -> 0.037697369 | J41: 40.0683
A42: 2034 | C42: =C41*(1+$B$12) -> 28.783239 | D42: =$D$32*(H42*G42)/($H$32*$G$32) -> 29.125185 | E42: =E41*(1+I42) -> 21.757609 | F42: ='GDP and Population'!B29 -> 3006.8025 | G42: ='GDP and Population'!D29 -> 280.08879 | H42: ='Gompertz fit'!$B$12*EXP('Gompertz fit'!$B$24*EXP('Gompertz fit'!$B$25*F42)) -> 84.788844 | I42: =$B$13+(0.277778)*($B$14-$B$13) -> 0.037492081 | J42: 42.3641
A43: 2035 | C43: =C42*(1+$B$12) -> 30.737161 | D43: =$D$32*(H43*G43)/($H$32*$G$32) -> 31.018886 | E43: =E42*(1+I43) -> 22.568881 | F43: ='GDP and Population'!B30 -> 3081.9725 | G43: ='GDP and Population'!D30 -> 285.15601 | H43: ='Gompertz fit'!$B$12*EXP('Gompertz fit'!$B$24*EXP('Gompertz fit'!$B$25*F43)) -> 88.6971 | I43: =$B$13+(0.305556)*($B$14-$B$13) -> 0.037286794 | J43: 44.79147
A44: 2036 | C44: =C43*(1+$B$12) -> 32.823724 | D44: =$D$32*(H44*G44)/($H$32*$G$32) -> 33.006553 | E44: =E43*(1+I44) -> 23.405769 | F44: ='GDP and Population'!B31 -> 3159.0219 | G44: ='GDP and Population'!D31 -> 290.21552 | H44: ='Gompertz fit'!$B$12*EXP('Gompertz fit'!$B$24*EXP('Gompertz fit'!$B$25*F44)) -> 92.735345 | I44: =$B$13+(0.333333)*($B$14-$B$13) -> 0.037081513
A45: 2037 | C45: =C44*(1+$B$12) -> 35.051931 | D45: =$D$32*(H45*G45)/($H$32*$G$32) -> 35.089346 | E45: =E44*(1+I45) -> 24.268885 | F45: ='GDP and Population'!B32 -> 3237.9974 | G45: ='GDP and Population'!D32 -> 295.26327 | H45: ='Gompertz fit'!$B$12*EXP('Gompertz fit'!$B$24*EXP('Gompertz fit'!$B$25*F45)) -> 96.901745 | I45: =$B$13+(0.361111)*($B$14-$B$13) -> 0.036876226
A46: 2038 | C46: =C45*(1+$B$12) -> 37.431398 | D46: =$D$32*(H46*G46)/($H$32*$G$32) -> 37.266544 | E46: =E45*(1+I46) -> 25.158848 | F46: ='GDP and Population'!B33 -> 3318.9473 | G46: ='GDP and Population'!D33 -> 300.28321 | H46: ='Gompertz fit'!$B$12*EXP('Gompertz fit'!$B$24*EXP('Gompertz fit'!$B$25*F46)) -> 101.19378 | I46: =$B$13+(0.388889)*($B$14-$B$13) -> 0.036670938
A47: 2039 | C47: =C46*(1+$B$12) -> 39.972392 | D47: =$D$32*(H47*G47)/($H$32*$G$32) -> 39.539614 | E47: =E46*(1+I47) -> 26.076282 | F47: ='GDP and Population'!B34 -> 3401.921 | G47: ='GDP and Population'!D34 -> 305.2815 | H47: ='Gompertz fit'!$B$12*EXP('Gompertz fit'!$B$24*EXP('Gompertz fit'!$B$25*F47)) -> 105.60821 | I47: =$B$13+(0.416667)*($B$14-$B$13) -> 0.036465651
A48: 2040 | C48: =C47*(1+$B$12) -> 42.68588 | D48: =$D$32*(H48*G48)/($H$32*$G$32) -> 41.907573 | E48: =E47*(1+I48) -> 27.021818 | F48: ='GDP and Population'!B35 -> 3486.969 | G48: ='GDP and Population'!D35 -> 310.24801 | H48: ='Gompertz fit'!$B$12*EXP('Gompertz fit'!$B$24*EXP('Gompertz fit'!$B$25*F48)) -> 110.14106 | I48: =$B$13+(0.444444)*($B$14-$B$13) -> 0.03626037
A49: 2041 | C49: =C48*(1+$B$12) -> 45.58357 | D49: =$D$32*(H49*G49)/($H$32*$G$32) -> 44.368824 | E49: =E48*(1+I49) -> 27.996092 | F49: ='GDP and Population'!B36 -> 3574.1433 | G49: ='GDP and Population'!D36 -> 315.17282 | H49: ='Gompertz fit'!$B$12*EXP('Gompertz fit'!$B$24*EXP('Gompertz fit'!$B$25*F49)) -> 114.78758 | I49: =$B$13+(0.472222)*($B$14-$B$13) -> 0.036055083
A50: 2042 | C50: =C49*(1+$B$12) -> 48.677966 | D50: =$D$32*(H50*G50)/($H$32*$G$32) -> 46.920456 | E50: =E49*(1+I50) -> 28.999746 | F50: ='GDP and Population'!B37 -> 3663.4968 | G50: ='GDP and Population'!D37 -> 320.04167 | H50: ='Gompertz fit'!$B$12*EXP('Gompertz fit'!$B$24*EXP('Gompertz fit'!$B$25*F50)) -> 119.54226 | I50: =$B$13+(0.5)*($B$14-$B$13) -> 0.035849795
A51: 2043 | C51: =C50*(1+$B$12) -> 51.982423 | D51: =$D$32*(H51*G51)/($H$32*$G$32) -> 49.561586 | E51: =E50*(1+I51) -> 30.033427 | F51: ='GDP and Population'!B38 -> 3755.0843 | G51: ='GDP and Population'!D38 -> 324.85895 | H51: ='Gompertz fit'!$B$12*EXP('Gompertz fit'!$B$24*EXP('Gompertz fit'!$B$25*F51)) -> 124.39877 | I51: =$B$13+(0.527778)*($B$14-$B$13) -> 0.035644507
A52: 2044 | C52: =C51*(1+$B$12) -> 55.5112 | D52: =$D$32*(H52*G52)/($H$32*$G$32) -> 52.290905 | E52: =E51*(1+I52) -> 31.097789 | F52: ='GDP and Population'!B39 -> 3848.9614 | G52: ='GDP and Population'!D39 -> 329.62893 | H52: ='Gompertz fit'!$B$12*EXP('Gompertz fit'!$B$24*EXP('Gompertz fit'!$B$25*F52)) -> 129.35005 | I52: =$B$13+(0.555556)*($B$14-$B$13) -> 0.03543922
A53: 2045 | C53: =C52*(1+$B$12) -> 59.279525 | D53: =$D$32*(H53*G53)/($H$32*$G$32) -> 55.103716 | E53: =E52*(1+I53) -> 32.193486 | F53: ='GDP and Population'!B40 -> 3945.1854 | G53: ='GDP and Population'!D40 -> 334.33779 | H53: ='Gompertz fit'!$B$12*EXP('Gompertz fit'!$B$24*EXP('Gompertz fit'!$B$25*F53)) -> 134.38821 | I53: =$B$13+(0.583333)*($B$14-$B$13) -> 0.03523394
A54: 2046 | C54: =C53*(1+$B$12) -> 63.303658 | D54: =$D$32*(H54*G54)/($H$32*$G$32) -> 57.997096 | E54: =E53*(1+I54) -> 33.321181 | F54: ='GDP and Population'!B41 -> 4043.815 | G54: ='GDP and Population'!D41 -> 338.98721 | H54: ='Gompertz fit'!$B$12*EXP('Gompertz fit'!$B$24*EXP('Gompertz fit'!$B$25*F54)) -> 139.50465 | I54: =$B$13+(0.611111)*($B$14-$B$13) -> 0.035028652
A55: 2047 | C55: =C54*(1+$B$12) -> 67.600966 | D55: =$D$32*(H55*G55)/($H$32*$G$32) -> 60.967171 | E55: =E54*(1+I55) -> 34.481536 | F55: ='GDP and Population'!B42 -> 4144.9104 | G55: ='GDP and Population'!D42 -> 343.57631 | H55: ='Gompertz fit'!$B$12*EXP('Gompertz fit'!$B$24*EXP('Gompertz fit'!$B$25*F55)) -> 144.69002 | I55: =$B$13+(0.638889)*($B$14-$B$13) -> 0.034823364
A56: 2048 | C56: =C55*(1+$B$12) -> 72.189993 | D56: =$D$32*(H56*G56)/($H$32*$G$32) -> 64.010892 | E56: =E55*(1+I56) -> 35.675221 | F56: ='GDP and Population'!B43 -> 4248.5332 | G56: ='GDP and Population'!D43 -> 348.1117 | H56: ='Gompertz fit'!$B$12*EXP('Gompertz fit'!$B$24*EXP('Gompertz fit'!$B$25*F56)) -> 149.9343 | I56: =$B$13+(0.666667)*($B$14-$B$13) -> 0.034618077
A57: 2049 | C57: =C56*(1+$B$12) -> 77.090541 | D57: =$D$32*(H57*G57)/($H$32*$G$32) -> 67.121776 | E57: =E56*(1+I57) -> 36.902905 | F57: ='GDP and Population'!B44 -> 4354.7465 | G57: ='GDP and Population'!D44 -> 352.58383 | H57: ='Gompertz fit'!$B$12*EXP('Gompertz fit'!$B$24*EXP('Gompertz fit'!$B$25*F57)) -> 155.22683 | I57: =$B$13+(0.694444)*($B$14-$B$13) -> 0.034412796
A58: 2050 | C58: =C57*(1+$B$12) -> 82.323759 | D58: =$D$32*(H58*G58)/($H$32*$G$32) -> 70.296101 | E58: =E57*(1+I58) -> 38.165261 | F58: ='GDP and Population'!B45 -> 4463.6152 | G58: ='GDP and Population'!D45 -> 357.00102 | H58: ='Gompertz fit'!$B$12*EXP('Gompertz fit'!$B$24*EXP('Gompertz fit'!$B$25*F58)) -> 160.55637 | I58: =$B$13+(0.722222)*($B$14-$B$13) -> 0.034207509
A59: 2051 | C59: =C58*(1+$B$12) -> 87.912228 | D59: =$D$32*(H59*G59)/($H$32*$G$32) -> 73.529577 | E59: =E58*(1+I59) -> 39.462965 | F59: ='GDP and Population'!B46 -> 4575.2056 | G59: ='GDP and Population'!D46 -> 361.37009 | H59: ='Gompertz fit'!$B$12*EXP('Gompertz fit'!$B$24*EXP('Gompertz fit'!$B$25*F59)) -> 165.91116 | I59: =$B$13+(0.75)*($B$14-$B$13) -> 0.034002221
A60: 2052 | C60: =C59*(1+$B$12) -> 93.880065 | D60: =$D$32*(H60*G60)/($H$32*$G$32) -> 76.813271 | E60: =E59*(1+I60) -> 40.796692 | F60: ='GDP and Population'!B47 -> 4689.5857 | G60: ='GDP and Population'!D47 -> 365.67713 | H60: ='Gompertz fit'!$B$12*EXP('Gompertz fit'!$B$24*EXP('Gompertz fit'!$B$25*F60)) -> 171.27904 | I60: =$B$13+(0.777778)*($B$14-$B$13) -> 0.033796934
A61: 2053 | C61: =C60*(1+$B$12) -> 100.25302 | D61: =$D$32*(H61*G61)/($H$32*$G$32) -> 80.14225 | E61: =E60*(1+I61) -> 42.16712 | F61: ='GDP and Population'!B48 -> 4806.8253 | G61: ='GDP and Population'!D48 -> 369.93029 | H61: ='Gompertz fit'!$B$12*EXP('Gompertz fit'!$B$24*EXP('Gompertz fit'!$B$25*F61)) -> 176.64746 | I61: =$B$13+(0.805556)*($B$14-$B$13) -> 0.033591646
A62: 2054 | C62: =C61*(1+$B$12) -> 107.0586 | D62: =$D$32*(H62*G62)/($H$32*$G$32) -> 83.506913 | E62: =E61*(1+I62) -> 43.574927 | F62: ='GDP and Population'!B49 -> 4926.996 | G62: ='GDP and Population'!D49 -> 374.11756 | H62: ='Gompertz fit'!$B$12*EXP('Gompertz fit'!$B$24*EXP('Gompertz fit'!$B$25*F62)) -> 182.00365 | I62: =$B$13+(0.833333)*($B$14-$B$13) -> 0.033386366
A63: 2055 | C63: =C62*(1+$B$12) -> 114.32617 | D63: =$D$32*(H63*G63)/($H$32*$G$32) -> 86.89939 | E63: =E62*(1+I63) -> 45.02079 | F63: ='GDP and Population'!B50 -> 5050.1709 | G63: ='GDP and Population'!D50 -> 378.23728 | H63: ='Gompertz fit'!$B$12*EXP('Gompertz fit'!$B$24*EXP('Gompertz fit'!$B$25*F63)) -> 187.33466 | I63: =$B$13+(0.861111)*($B$14-$B$13) -> 0.033181078
A64: 2056 | C64: =C63*(1+$B$12) -> 122.0871 | D64: =$D$32*(H64*G64)/($H$32*$G$32) -> 90.314305 | E64: =E63*(1+I64) -> 46.505386 | F64: ='GDP and Population'!B51 -> 5176.4251 | G64: ='GDP and Population'!D51 -> 382.29971 | H64: ='Gompertz fit'!$B$12*EXP('Gompertz fit'!$B$24*EXP('Gompertz fit'!$B$25*F64)) -> 192.62752 | I64: =$B$13+(0.888889)*($B$14-$B$13) -> 0.03297579
A65: 2057 | C65: =C64*(1+$B$12) -> 130.37486 | D65: =$D$32*(H65*G65)/($H$32*$G$32) -> 93.743073 | E65: =E64*(1+I65) -> 48.029391 | F65: ='GDP and Population'!B52 -> 5305.8358 | G65: ='GDP and Population'!D52 -> 386.30165 | H65: ='Gompertz fit'!$B$12*EXP('Gompertz fit'!$B$24*EXP('Gompertz fit'!$B$25*F65)) -> 197.86928 | I65: =$B$13+(0.916667)*($B$14-$B$13) -> 0.032770503
A66: 2058 | C66: =C65*(1+$B$12) -> 139.22523 | D66: =$D$32*(H66*G66)/($H$32*$G$32) -> 97.175525 | E66: =E65*(1+I66) -> 49.593479 | F66: ='GDP and Population'!B53 -> 5438.4817 | G66: ='GDP and Population'!D53 -> 390.23454 | H66: ='Gompertz fit'!$B$12*EXP('Gompertz fit'!$B$24*EXP('Gompertz fit'!$B$25*F66)) -> 203.04717 | I66: =$B$13+(0.944444)*($B$14-$B$13) -> 0.032565223
A67: 2059 | C67: =C66*(1+$B$12) -> 148.67641 | D67: =$D$32*(H67*G67)/($H$32*$G$32) -> 100.60556 | E67: =E66*(1+I67) -> 51.198321 | F67: ='GDP and Population'!B54 -> 5574.4437 | G67: ='GDP and Population'!D54 -> 394.10689 | H67: ='Gompertz fit'!$B$12*EXP('Gompertz fit'!$B$24*EXP('Gompertz fit'!$B$25*F67)) -> 208.1487 | I67: =$B$13+(0.972222)*($B$14-$B$13) -> 0.032359935
A68: 2060 | C68: =C67*(1+$B$12) -> 158.76916 | D68: =$D$32*(H68*G68)/($H$32*$G$32) -> 104.02324 | E68: =E67*(1+I68) -> 52.844585 | F68: ='GDP and Population'!B55 -> 5713.8048 | G68: ='GDP and Population'!D55 -> 397.91185 | H68: ='Gompertz fit'!$B$12*EXP('Gompertz fit'!$B$24*EXP('Gompertz fit'!$B$25*F68)) -> 213.16175 | I68: =$B$13+(1)*($B$14-$B$13) -> 0.032154647
A69: Scenario B follows the anchored/bridged stock through 2024. From 2025, the fitted Gompertz ownership-and-population trajectory is scaled to equal the common 2024 anchor, eliminating a curve-splicing discontinuity while preserving subsequent growth.
A70: Effective Scenario B asymptote after anchoring (gamma x scaling factor, vehicles per 1,000): | B70: ='Gompertz fit'!B12*B15 -> 367.92179
A71: Class-disaggregated totals (scenario total x class share; shares = WB Table 22.4, 2035)
A72: Class share (WB 2035): | C72: 0.39697541 | D72: 0.46536514 | E72: 0.081161675 | F72: 0.05494178 | G72: 0.00077799689 | H72: 0.00077799689
A74: Scenario A class-disaggregated (M)
A75: Year | B75: Total | C75: Motorcycle | D75: Private car | E75: Light commercial | F75: Heavy goods | G75: Light bus | H75: Coach
A76: 2010 | B76: =C18 -> 8.671474 | C76: =$B76*$C$72 -> 3.442362 | D76: =$B76*$D$72 -> 4.0354017 | E76: =$B76*$E$72 -> 0.70379136 | F76: =$B76*$F$72 -> 0.47642622 | G76: =$B76*$G$72 -> 0.0067463798 | H76: =$B76*$H$72 -> 0.0067463798
A77: 2011 | B77: =C19 -> 9.0236636 | C77: =$B77*$C$72 -> 3.5821726 | D77: =$B77*$D$72 -> 4.1992985 | E77: =$B77*$E$72 -> 0.73237566 | F77: =$B77*$F$72 -> 0.49577614 | G77: =$B77*$G$72 -> 0.0070203822 | H77: =$B77*$H$72 -> 0.0070203822
A78: 2012 | B78: =C20 -> 9.3901573 | C78: =$B78*$C$72 -> 3.7276616 | D78: =$B78*$D$72 -> 4.3698519 | E78: =$B78*$E$72 -> 0.7621209 | F78: =$B78*$F$72 -> 0.51591196 | G78: =$B78*$G$72 -> 0.0073055132 | H78: =$B78*$H$72 -> 0.0073055132
A79: 2013 | B79: =C21 -> 9.771536 | C79: =$B79*$C$72 -> 3.8790595 | D79: =$B79*$D$72 -> 4.5473322 | E79: =$B79*$E$72 -> 0.79307424 | F79: =$B79*$F$72 -> 0.53686559 | G79: =$B79*$G$72 -> 0.0076022246 | H79: =$B79*$H$72 -> 0.0076022246
A80: 2014 | B80: =C22 -> 10.168407 | C80: =$B80*$C$72 -> 4.0366076 | D80: =$B80*$D$72 -> 4.7320222 | E80: =$B80*$E$72 -> 0.82528496 | F80: =$B80*$F$72 -> 0.55867039 | G80: =$B80*$G$72 -> 0.0079109892 | H80: =$B80*$H$72 -> 0.0079109892
A81: 2015 | B81: =C23 -> 10.581394 | C81: =$B81*$C$72 -> 4.2005534 | D81: =$B81*$D$72 -> 4.9242121 | E81: =$B81*$E$72 -> 0.85880369 | F81: =$B81*$F$72 -> 0.58136064 | G81: =$B81*$G$72 -> 0.0082322919 | H81: =$B81*$H$72 -> 0.0082322919
A82: 2016 | B82: =C24 -> 11.011155 | C82: =$B82*$C$72 -> 4.3711577 | D82: =$B82*$D$72 -> 5.1242076 | E82: =$B82*$E$72 -> 0.89368378 | F82: =$B82*$F$72 -> 0.60497245 | G82: =$B82*$G$72 -> 0.0085666442 | H82: =$B82*$H$72 -> 0.0085666442
A83: 2017 | B83: =C25 -> 11.45837 | C83: =$B83*$C$72 -> 4.5486912 | D83: =$B83*$D$72 -> 5.3323259 | E83: =$B83*$E$72 -> 0.92998051 | F83: =$B83*$F$72 -> 0.62954325 | G83: =$B83*$G$72 -> 0.0089145762 | H83: =$B83*$H$72 -> 0.0089145762
A84: 2018 | B84: =C26 -> 11.826033 | C84: =$B84*$C$72 -> 4.6946443 | D84: =$B84*$D$72 -> 5.5034235 | E84: =$B84*$E$72 -> 0.95982065 | F84: =$B84*$F$72 -> 0.64974331 | G84: =$B84*$G$72 -> 0.0092006169 | H84: =$B84*$H$72 -> 0.0092006169
A85: 2019 | B85: =C27 -> 12.293693 | C85: =$B85*$C$72 -> 4.8802938 | D85: =$B85*$D$72 -> 5.7210561 | E85: =$B85*$E$72 -> 0.9977767 | F85: =$B85*$F$72 -> 0.67543737 | G85: =$B85*$G$72 -> 0.0095644547 | H85: =$B85*$H$72 -> 0.0095644547
A86: 2020 | B86: =C28 -> 12.779846 | C86: =$B86*$C$72 -> 5.0732847 | D86: =$B86*$D$72 -> 5.9472949 | E86: =$B86*$E$72 -> 1.0372337 | F86: =$B86*$F$72 -> 0.7021475 | G86: =$B86*$G$72 -> 0.0099426806 | H86: =$B86*$H$72 -> 0.0099426806
A87: 2021 | B87: =C29 -> 13.285224 | C87: =$B87*$C$72 -> 5.2739075 | D87: =$B87*$D$72 -> 6.1824803 | E87: =$B87*$E$72 -> 1.0782511 | F87: =$B87*$F$72 -> 0.72991388 | G87: =$B87*$G$72 -> 0.010335863 | H87: =$B87*$H$72 -> 0.010335863
... A126: 2060 | B126: =C68 -> 158.76916 | C126: =$B126*$C$72 -> 63.027453 | D126: =$B126*$D$72 -> 73.885632 | E126: =$B126*$E$72 -> 12.885971 | F126: =$B126*$F$72 -> 8.7230603 | G126: =$B126*$G$72 -> 0.12352191 | H126: =$B126*$H$72 -> 0.12352191
A129: Scenario B class-disaggregated (M)
A130: Year | B130: Total | C130: Motorcycle | D130: Private car | E130: Light commercial | F130: Heavy goods | G130: Light bus | H130: Coach
A131: 2010 | B131: =D18 -> 8.671474 | C131: =$B131*$C$72 -> 3.442362 | D131: =$B131*$D$72 -> 4.0354017 | E131: =$B131*$E$72 -> 0.70379136 | F131: =$B131*$F$72 -> 0.47642622 | G131: =$B131*$G$72 -> 0.0067463798 | H131: =$B131*$H$72 -> 0.0067463798
A132: 2011 | B132: =D19 -> 9.0236636 | C132: =$B132*$C$72 -> 3.5821726 | D132: =$B132*$D$72 -> 4.1992985 | E132: =$B132*$E$72 -> 0.73237566 | F132: =$B132*$F$72 -> 0.49577614 | G132: =$B132*$G$72 -> 0.0070203822 | H132: =$B132*$H$72 -> 0.0070203822
A133: 2012 | B133: =D20 -> 9.3901573 | C133: =$B133*$C$72 -> 3.7276616 | D133: =$B133*$D$72 -> 4.3698519 | E133: =$B133*$E$72 -> 0.7621209 | F133: =$B133*$F$72 -> 0.51591196 | G133: =$B133*$G$72 -> 0.0073055132 | H133: =$B133*$H$72 -> 0.0073055132
A134: 2013 | B134: =D21 -> 9.771536 | C134: =$B134*$C$72 -> 3.8790595 | D134: =$B134*$D$72 -> 4.5473322 | E134: =$B134*$E$72 -> 0.79307424 | F134: =$B134*$F$72 -> 0.53686559 | G134: =$B134*$G$72 -> 0.0076022246 | H134: =$B134*$H$72 -> 0.0076022246
A135: 2014 | B135: =D22 -> 10.168407 | C135: =$B135*$C$72 -> 4.0366076 | D135: =$B135*$D$72 -> 4.7320222 | E135: =$B135*$E$72 -> 0.82528496 | F135: =$B135*$F$72 -> 0.55867039 | G135: =$B135*$G$72 -> 0.0079109892 | H135: =$B135*$H$72 -> 0.0079109892
A136: 2015 | B136: =D23 -> 10.581394 | C136: =$B136*$C$72 -> 4.2005534 | D136: =$B136*$D$72 -> 4.9242121 | E136: =$B136*$E$72 -> 0.85880369 | F136: =$B136*$F$72 -> 0.58136064 | G136: =$B136*$G$72 -> 0.0082322919 | H136: =$B136*$H$72 -> 0.0082322919
A137: 2016 | B137: =D24 -> 11.011155 | C137: =$B137*$C$72 -> 4.3711577 | D137: =$B137*$D$72 -> 5.1242076 | E137: =$B137*$E$72 -> 0.89368378 | F137: =$B137*$F$72 -> 0.60497245 | G137: =$B137*$G$72 -> 0.0085666442 | H137: =$B137*$H$72 -> 0.0085666442
A138: 2017 | B138: =D25 -> 11.45837 | C138: =$B138*$C$72 -> 4.5486912 | D138: =$B138*$D$72 -> 5.3323259 | E138: =$B138*$E$72 -> 0.92998051 | F138: =$B138*$F$72 -> 0.62954325 | G138: =$B138*$G$72 -> 0.0089145762 | H138: =$B138*$H$72 -> 0.0089145762
A139: 2018 | B139: =D26 -> 11.826033 | C139: =$B139*$C$72 -> 4.6946443 | D139: =$B139*$D$72 -> 5.5034235 | E139: =$B139*$E$72 -> 0.95982065 | F139: =$B139*$F$72 -> 0.64974331 | G139: =$B139*$G$72 -> 0.0092006169 | H139: =$B139*$H$72 -> 0.0092006169
A140: 2019 | B140: =D27 -> 12.293693 | C140: =$B140*$C$72 -> 4.8802938 | D140: =$B140*$D$72 -> 5.7210561 | E140: =$B140*$E$72 -> 0.9977767 | F140: =$B140*$F$72 -> 0.67543737 | G140: =$B140*$G$72 -> 0.0095644547 | H140: =$B140*$H$72 -> 0.0095644547
A141: 2020 | B141: =D28 -> 12.779846 | C141: =$B141*$C$72 -> 5.0732847 | D141: =$B141*$D$72 -> 5.9472949 | E141: =$B141*$E$72 -> 1.0372337 | F141: =$B141*$F$72 -> 0.7021475 | G141: =$B141*$G$72 -> 0.0099426806 | H141: =$B141*$H$72 -> 0.0099426806
A142: 2021 | B142: =D29 -> 13.285224 | C142: =$B142*$C$72 -> 5.2739075 | D142: =$B142*$D$72 -> 6.1824803 | E142: =$B142*$E$72 -> 1.0782511 | F142: =$B142*$F$72 -> 0.72991388 | G142: =$B142*$G$72 -> 0.010335863 | H142: =$B142*$H$72 -> 0.010335863
... A181: 2060 | B181: =D68 -> 104.02324 | C181: =$B181*$C$72 -> 41.29467 | D181: =$B181*$D$72 -> 48.408792 | E181: =$B181*$E$72 -> 8.4427008 | F181: =$B181*$F$72 -> 5.7152222 | G181: =$B181*$G$72 -> 0.080929761 | H181: =$B181*$H$72 -> 0.080929761
...

Sheet Validation
A1: Validation of the World Bank (2013) vehicle-stock projection against the anchor data
A2: Observed NBS vehicle-population counts show that the 2013 projection overshoots: the WB path implies ~15.4 M vehicles in 2018 against 11.83 M observed (+30%). This model therefore anchors on observed data and retains the WB growth rate only as the upper-bound Scenario A.
A4: Year | B4: Anchor / estimate (M) | C4: Source | D4: WB 2013 projection (M) | E4: WB / anchor | F4: Model, Scenario B (M)
A5: 2010 | B5: 8.671474 | C5: WB Table 22.4 base year | D5: ='Fleet projections'!J18 -> 8.671474 | E5: =IF(D5="","",D5/B5) -> 1 | F5: ='Fleet projections'!D18 -> 8.671474
A6: 2017 | B6: 11.45837 | C6: NBS Q1 2017 | D6: ='Fleet projections'!J25 -> 14.2596 | E6: =IF(D6="","",D6/B6) -> 1.2444702 | F6: ='Fleet projections'!D25 -> 11.45837
A7: 2017.75 | B7: 11.547236 | C7: NBS Q3 2017 | D7: ='Fleet projections'!J26 -> 15.3098 | E7: =IF(D7="","",D7/B7) -> 1.3258411 | F7: ='Fleet projections'!D26 -> 11.826033
A8: 2018.25 | B8: 11.653871 | C8: NBS Q1 2018 | D8: ='Fleet projections'!J26 -> 15.3098 | E8: =IF(D8="","",D8/B8) -> 1.3137094 | F8: ='Fleet projections'!D26 -> 11.826033
A9: 2018 | B9: 11.826033 | C9: NBS Q4 2018 | D9: ='Fleet projections'!J26 -> 15.3098 | E9: =IF(D9="","",D9/B9) -> 1.2945846 | F9: ='Fleet projections'!D26 -> 11.826033
A10: 2020 | B10: 11.605207 | C10: CEIC/OICA (modelled; different methodology) | D10: ='Fleet projections'!J28 -> 17.647653 | E10: =IF(D10="","",D10/B10) -> 1.5206668 | F10: ='Fleet projections'!D28 -> 12.779846
A11: 2023 | B11: 12 | C11: FRSC / NIA round estimate (low confidence) | D11: ='Fleet projections'!J31 -> 21.4656 | E11: =IF(D11="","",D11/B11) -> 1.7888 | F11: ='Fleet projections'!D31 -> 14.356727
A13: Implied CAGR 2010-2018, anchor-derived: | B13: ='Fleet projections'!B11 -> 0.039544943
A14: Implied CAGR 2010-2035, WB 2013 projection: | B14: ='Fleet projections'!B12 -> 0.067884039
A16: Scenario endpoints 2060 (M):
A17: Scenario A (upper, WB growth rate) | B17: ='Fleet projections'!C68 -> 158.76916 | C17: =B17*1000/'GDP and Population'!D55 -> 399.00586 | D17: vehicles per 1,000 persons in 2060 (col C); South Africa ~176, Morocco ~112, Libya ~490 today (OICA).
A18: Scenario B (central, Gompertz gamma=300) | B18: ='Fleet projections'!D68 -> 104.02324 | C18: =B18*1000/'GDP and Population'!D55 -> 261.42283 | D18: vehicles per 1,000 persons in 2060 (col C); South Africa ~176, Morocco ~112, Libya ~490 today (OICA).
A19: Scenario C (lower, declining CAGR) | B19: ='Fleet projections'!E68 -> 52.844585 | C19: =B19*1000/'GDP and Population'!D55 -> 132.80475 | D19: vehicles per 1,000 persons in 2060 (col C); South Africa ~176, Morocco ~112, Libya ~490 today (OICA).

Sheet EV adoption
A1: EV adoption share by class and year (logistic S-curves)
A3: Year | B3: Motorcycle | C3: Private car | D3: Light commercial | E3: Heavy goods | F3: Light bus | G3: Coach
A4: 2010 | B4: =IF(A4<2025,0,(1/(1+EXP(-Assumptions!$C$16*(A4-Assumptions!$B$16))))/IF(Assumptions!$B$92=1,1/(1+EXP(-Assumptions!$C$16*(2060-Assumptions!$B$16))),1)) -> 0 | C4: =IF(A4<2025,0,(1/(1+EXP(-Assumptions!$C$17*(A4-Assumptions!$B$17))))/IF(Assumptions!$B$92=1,1/(1+EXP(-Assumptions!$C$17*(2060-Assumptions!$B$17))),1)) -> 0 | D4: =IF(A4<2025,0,(1/(1+EXP(-Assumptions!$C$18*(A4-Assumptions!$B$18))))/IF(Assumptions!$B$92=1,1/(1+EXP(-Assumptions!$C$18*(2060-Assumptions!$B$18))),1)) -> 0 | E4: =IF(A4<2025,0,(1/(1+EXP(-Assumptions!$C$19*(A4-Assumptions!$B$19))))/IF(Assumptions!$B$92=1,1/(1+EXP(-Assumptions!$C$19*(2060-Assumptions!$B$19))),1)) -> 0 | F4: =IF(A4<2025,0,(1/(1+EXP(-Assumptions!$C$20*(A4-Assumptions!$B$20))))/IF(Assumptions!$B$92=1,1/(1+EXP(-Assumptions!$C$20*(2060-Assumptions!$B$20))),1)) -> 0 | G4: =IF(A4<2025,0,(1/(1+EXP(-Assumptions!$C$21*(A4-Assumptions!$B$21))))/IF(Assumptions!$B$92=1,1/(1+EXP(-Assumptions!$C$21*(2060-Assumptions!$B$21))),1)) -> 0
A5: 2011 | B5: =IF(A5<2025,0,(1/(1+EXP(-Assumptions!$C$16*(A5-Assumptions!$B$16))))/IF(Assumptions!$B$92=1,1/(1+EXP(-Assumptions!$C$16*(2060-Assumptions!$B$16))),1)) -> 0 | C5: =IF(A5<2025,0,(1/(1+EXP(-Assumptions!$C$17*(A5-Assumptions!$B$17))))/IF(Assumptions!$B$92=1,1/(1+EXP(-Assumptions!$C$17*(2060-Assumptions!$B$17))),1)) -> 0 | D5: =IF(A5<2025,0,(1/(1+EXP(-Assumptions!$C$18*(A5-Assumptions!$B$18))))/IF(Assumptions!$B$92=1,1/(1+EXP(-Assumptions!$C$18*(2060-Assumptions!$B$18))),1)) -> 0 | E5: =IF(A5<2025,0,(1/(1+EXP(-Assumptions!$C$19*(A5-Assumptions!$B$19))))/IF(Assumptions!$B$92=1,1/(1+EXP(-Assumptions!$C$19*(2060-Assumptions!$B$19))),1)) -> 0 | F5: =IF(A5<2025,0,(1/(1+EXP(-Assumptions!$C$20*(A5-Assumptions!$B$20))))/IF(Assumptions!$B$92=1,1/(1+EXP(-Assumptions!$C$20*(2060-Assumptions!$B$20))),1)) -> 0 | G5: =IF(A5<2025,0,(1/(1+EXP(-Assumptions!$C$21*(A5-Assumptions!$B$21))))/IF(Assumptions!$B$92=1,1/(1+EXP(-Assumptions!$C$21*(2060-Assumptions!$B$21))),1)) -> 0
A6: 2012 | B6: =IF(A6<2025,0,(1/(1+EXP(-Assumptions!$C$16*(A6-Assumptions!$B$16))))/IF(Assumptions!$B$92=1,1/(1+EXP(-Assumptions!$C$16*(2060-Assumptions!$B$16))),1)) -> 0 | C6: =IF(A6<2025,0,(1/(1+EXP(-Assumptions!$C$17*(A6-Assumptions!$B$17))))/IF(Assumptions!$B$92=1,1/(1+EXP(-Assumptions!$C$17*(2060-Assumptions!$B$17))),1)) -> 0 | D6: =IF(A6<2025,0,(1/(1+EXP(-Assumptions!$C$18*(A6-Assumptions!$B$18))))/IF(Assumptions!$B$92=1,1/(1+EXP(-Assumptions!$C$18*(2060-Assumptions!$B$18))),1)) -> 0 | E6: =IF(A6<2025,0,(1/(1+EXP(-Assumptions!$C$19*(A6-Assumptions!$B$19))))/IF(Assumptions!$B$92=1,1/(1+EXP(-Assumptions!$C$19*(2060-Assumptions!$B$19))),1)) -> 0 | F6: =IF(A6<2025,0,(1/(1+EXP(-Assumptions!$C$20*(A6-Assumptions!$B$20))))/IF(Assumptions!$B$92=1,1/(1+EXP(-Assumptions!$C$20*(2060-Assumptions!$B$20))),1)) -> 0 | G6: =IF(A6<2025,0,(1/(1+EXP(-Assumptions!$C$21*(A6-Assumptions!$B$21))))/IF(Assumptions!$B$92=1,1/(1+EXP(-Assumptions!$C$21*(2060-Assumptions!$B$21))),1)) -> 0
A7: 2013 | B7: =IF(A7<2025,0,(1/(1+EXP(-Assumptions!$C$16*(A7-Assumptions!$B$16))))/IF(Assumptions!$B$92=1,1/(1+EXP(-Assumptions!$C$16*(2060-Assumptions!$B$16))),1)) -> 0 | C7: =IF(A7<2025,0,(1/(1+EXP(-Assumptions!$C$17*(A7-Assumptions!$B$17))))/IF(Assumptions!$B$92=1,1/(1+EXP(-Assumptions!$C$17*(2060-Assumptions!$B$17))),1)) -> 0 | D7: =IF(A7<2025,0,(1/(1+EXP(-Assumptions!$C$18*(A7-Assumptions!$B$18))))/IF(Assumptions!$B$92=1,1/(1+EXP(-Assumptions!$C$18*(2060-Assumptions!$B$18))),1)) -> 0 | E7: =IF(A7<2025,0,(1/(1+EXP(-Assumptions!$C$19*(A7-Assumptions!$B$19))))/IF(Assumptions!$B$92=1,1/(1+EXP(-Assumptions!$C$19*(2060-Assumptions!$B$19))),1)) -> 0 | F7: =IF(A7<2025,0,(1/(1+EXP(-Assumptions!$C$20*(A7-Assumptions!$B$20))))/IF(Assumptions!$B$92=1,1/(1+EXP(-Assumptions!$C$20*(2060-Assumptions!$B$20))),1)) -> 0 | G7: =IF(A7<2025,0,(1/(1+EXP(-Assumptions!$C$21*(A7-Assumptions!$B$21))))/IF(Assumptions!$B$92=1,1/(1+EXP(-Assumptions!$C$21*(2060-Assumptions!$B$21))),1)) -> 0
A8: 2014 | B8: =IF(A8<2025,0,(1/(1+EXP(-Assumptions!$C$16*(A8-Assumptions!$B$16))))/IF(Assumptions!$B$92=1,1/(1+EXP(-Assumptions!$C$16*(2060-Assumptions!$B$16))),1)) -> 0 | C8: =IF(A8<2025,0,(1/(1+EXP(-Assumptions!$C$17*(A8-Assumptions!$B$17))))/IF(Assumptions!$B$92=1,1/(1+EXP(-Assumptions!$C$17*(2060-Assumptions!$B$17))),1)) -> 0 | D8: =IF(A8<2025,0,(1/(1+EXP(-Assumptions!$C$18*(A8-Assumptions!$B$18))))/IF(Assumptions!$B$92=1,1/(1+EXP(-Assumptions!$C$18*(2060-Assumptions!$B$18))),1)) -> 0 | E8: =IF(A8<2025,0,(1/(1+EXP(-Assumptions!$C$19*(A8-Assumptions!$B$19))))/IF(Assumptions!$B$92=1,1/(1+EXP(-Assumptions!$C$19*(2060-Assumptions!$B$19))),1)) -> 0 | F8: =IF(A8<2025,0,(1/(1+EXP(-Assumptions!$C$20*(A8-Assumptions!$B$20))))/IF(Assumptions!$B$92=1,1/(1+EXP(-Assumptions!$C$20*(2060-Assumptions!$B$20))),1)) -> 0 | G8: =IF(A8<2025,0,(1/(1+EXP(-Assumptions!$C$21*(A8-Assumptions!$B$21))))/IF(Assumptions!$B$92=1,1/(1+EXP(-Assumptions!$C$21*(2060-Assumptions!$B$21))),1)) -> 0
A9: 2015 | B9: =IF(A9<2025,0,(1/(1+EXP(-Assumptions!$C$16*(A9-Assumptions!$B$16))))/IF(Assumptions!$B$92=1,1/(1+EXP(-Assumptions!$C$16*(2060-Assumptions!$B$16))),1)) -> 0 | C9: =IF(A9<2025,0,(1/(1+EXP(-Assumptions!$C$17*(A9-Assumptions!$B$17))))/IF(Assumptions!$B$92=1,1/(1+EXP(-Assumptions!$C$17*(2060-Assumptions!$B$17))),1)) -> 0 | D9: =IF(A9<2025,0,(1/(1+EXP(-Assumptions!$C$18*(A9-Assumptions!$B$18))))/IF(Assumptions!$B$92=1,1/(1+EXP(-Assumptions!$C$18*(2060-Assumptions!$B$18))),1)) -> 0 | E9: =IF(A9<2025,0,(1/(1+EXP(-Assumptions!$C$19*(A9-Assumptions!$B$19))))/IF(Assumptions!$B$92=1,1/(1+EXP(-Assumptions!$C$19*(2060-Assumptions!$B$19))),1)) -> 0 | F9: =IF(A9<2025,0,(1/(1+EXP(-Assumptions!$C$20*(A9-Assumptions!$B$20))))/IF(Assumptions!$B$92=1,1/(1+EXP(-Assumptions!$C$20*(2060-Assumptions!$B$20))),1)) -> 0 | G9: =IF(A9<2025,0,(1/(1+EXP(-Assumptions!$C$21*(A9-Assumptions!$B$21))))/IF(Assumptions!$B$92=1,1/(1+EXP(-Assumptions!$C$21*(2060-Assumptions!$B$21))),1)) -> 0
A10: 2016 | B10: =IF(A10<2025,0,(1/(1+EXP(-Assumptions!$C$16*(A10-Assumptions!$B$16))))/IF(Assumptions!$B$92=1,1/(1+EXP(-Assumptions!$C$16*(2060-Assumptions!$B$16))),1)) -> 0 | C10: =IF(A10<2025,0,(1/(1+EXP(-Assumptions!$C$17*(A10-Assumptions!$B$17))))/IF(Assumptions!$B$92=1,1/(1+EXP(-Assumptions!$C$17*(2060-Assumptions!$B$17))),1)) -> 0 | D10: =IF(A10<2025,0,(1/(1+EXP(-Assumptions!$C$18*(A10-Assumptions!$B$18))))/IF(Assumptions!$B$92=1,1/(1+EXP(-Assumptions!$C$18*(2060-Assumptions!$B$18))),1)) -> 0 | E10: =IF(A10<2025,0,(1/(1+EXP(-Assumptions!$C$19*(A10-Assumptions!$B$19))))/IF(Assumptions!$B$92=1,1/(1+EXP(-Assumptions!$C$19*(2060-Assumptions!$B$19))),1)) -> 0 | F10: =IF(A10<2025,0,(1/(1+EXP(-Assumptions!$C$20*(A10-Assumptions!$B$20))))/IF(Assumptions!$B$92=1,1/(1+EXP(-Assumptions!$C$20*(2060-Assumptions!$B$20))),1)) -> 0 | G10: =IF(A10<2025,0,(1/(1+EXP(-Assumptions!$C$21*(A10-Assumptions!$B$21))))/IF(Assumptions!$B$92=1,1/(1+EXP(-Assumptions!$C$21*(2060-Assumptions!$B$21))),1)) -> 0
A11: 2017 | B11: =IF(A11<2025,0,(1/(1+EXP(-Assumptions!$C$16*(A11-Assumptions!$B$16))))/IF(Assumptions!$B$92=1,1/(1+EXP(-Assumptions!$C$16*(2060-Assumptions!$B$16))),1)) -> 0 | C11: =IF(A11<2025,0,(1/(1+EXP(-Assumptions!$C$17*(A11-Assumptions!$B$17))))/IF(Assumptions!$B$92=1,1/(1+EXP(-Assumptions!$C$17*(2060-Assumptions!$B$17))),1)) -> 0 | D11: =IF(A11<2025,0,(1/(1+EXP(-Assumptions!$C$18*(A11-Assumptions!$B$18))))/IF(Assumptions!$B$92=1,1/(1+EXP(-Assumptions!$C$18*(2060-Assumptions!$B$18))),1)) -> 0 | E11: =IF(A11<2025,0,(1/(1+EXP(-Assumptions!$C$19*(A11-Assumptions!$B$19))))/IF(Assumptions!$B$92=1,1/(1+EXP(-Assumptions!$C$19*(2060-Assumptions!$B$19))),1)) -> 0 | F11: =IF(A11<2025,0,(1/(1+EXP(-Assumptions!$C$20*(A11-Assumptions!$B$20))))/IF(Assumptions!$B$92=1,1/(1+EXP(-Assumptions!$C$20*(2060-Assumptions!$B$20))),1)) -> 0 | G11: =IF(A11<2025,0,(1/(1+EXP(-Assumptions!$C$21*(A11-Assumptions!$B$21))))/IF(Assumptions!$B$92=1,1/(1+EXP(-Assumptions!$C$21*(2060-Assumptions!$B$21))),1)) -> 0
A12: 2018 | B12: =IF(A12<2025,0,(1/(1+EXP(-Assumptions!$C$16*(A12-Assumptions!$B$16))))/IF(Assumptions!$B$92=1,1/(1+EXP(-Assumptions!$C$16*(2060-Assumptions!$B$16))),1)) -> 0 | C12: =IF(A12<2025,0,(1/(1+EXP(-Assumptions!$C$17*(A12-Assumptions!$B$17))))/IF(Assumptions!$B$92=1,1/(1+EXP(-Assumptions!$C$17*(2060-Assumptions!$B$17))),1)) -> 0 | D12: =IF(A12<2025,0,(1/(1+EXP(-Assumptions!$C$18*(A12-Assumptions!$B$18))))/IF(Assumptions!$B$92=1,1/(1+EXP(-Assumptions!$C$18*(2060-Assumptions!$B$18))),1)) -> 0 | E12: =IF(A12<2025,0,(1/(1+EXP(-Assumptions!$C$19*(A12-Assumptions!$B$19))))/IF(Assumptions!$B$92=1,1/(1+EXP(-Assumptions!$C$19*(2060-Assumptions!$B$19))),1)) -> 0 | F12: =IF(A12<2025,0,(1/(1+EXP(-Assumptions!$C$20*(A12-Assumptions!$B$20))))/IF(Assumptions!$B$92=1,1/(1+EXP(-Assumptions!$C$20*(2060-Assumptions!$B$20))),1)) -> 0 | G12: =IF(A12<2025,0,(1/(1+EXP(-Assumptions!$C$21*(A12-Assumptions!$B$21))))/IF(Assumptions!$B$92=1,1/(1+EXP(-Assumptions!$C$21*(2060-Assumptions!$B$21))),1)) -> 0
A13: 2019 | B13: =IF(A13<2025,0,(1/(1+EXP(-Assumptions!$C$16*(A13-Assumptions!$B$16))))/IF(Assumptions!$B$92=1,1/(1+EXP(-Assumptions!$C$16*(2060-Assumptions!$B$16))),1)) -> 0 | C13: =IF(A13<2025,0,(1/(1+EXP(-Assumptions!$C$17*(A13-Assumptions!$B$17))))/IF(Assumptions!$B$92=1,1/(1+EXP(-Assumptions!$C$17*(2060-Assumptions!$B$17))),1)) -> 0 | D13: =IF(A13<2025,0,(1/(1+EXP(-Assumptions!$C$18*(A13-Assumptions!$B$18))))/IF(Assumptions!$B$92=1,1/(1+EXP(-Assumptions!$C$18*(2060-Assumptions!$B$18))),1)) -> 0 | E13: =IF(A13<2025,0,(1/(1+EXP(-Assumptions!$C$19*(A13-Assumptions!$B$19))))/IF(Assumptions!$B$92=1,1/(1+EXP(-Assumptions!$C$19*(2060-Assumptions!$B$19))),1)) -> 0 | F13: =IF(A13<2025,0,(1/(1+EXP(-Assumptions!$C$20*(A13-Assumptions!$B$20))))/IF(Assumptions!$B$92=1,1/(1+EXP(-Assumptions!$C$20*(2060-Assumptions!$B$20))),1)) -> 0 | G13: =IF(A13<2025,0,(1/(1+EXP(-Assumptions!$C$21*(A13-Assumptions!$B$21))))/IF(Assumptions!$B$92=1,1/(1+EXP(-Assumptions!$C$21*(2060-Assumptions!$B$21))),1)) -> 0
A14: 2020 | B14: =IF(A14<2025,0,(1/(1+EXP(-Assumptions!$C$16*(A14-Assumptions!$B$16))))/IF(Assumptions!$B$92=1,1/(1+EXP(-Assumptions!$C$16*(2060-Assumptions!$B$16))),1)) -> 0 | C14: =IF(A14<2025,0,(1/(1+EXP(-Assumptions!$C$17*(A14-Assumptions!$B$17))))/IF(Assumptions!$B$92=1,1/(1+EXP(-Assumptions!$C$17*(2060-Assumptions!$B$17))),1)) -> 0 | D14: =IF(A14<2025,0,(1/(1+EXP(-Assumptions!$C$18*(A14-Assumptions!$B$18))))/IF(Assumptions!$B$92=1,1/(1+EXP(-Assumptions!$C$18*(2060-Assumptions!$B$18))),1)) -> 0 | E14: =IF(A14<2025,0,(1/(1+EXP(-Assumptions!$C$19*(A14-Assumptions!$B$19))))/IF(Assumptions!$B$92=1,1/(1+EXP(-Assumptions!$C$19*(2060-Assumptions!$B$19))),1)) -> 0 | F14: =IF(A14<2025,0,(1/(1+EXP(-Assumptions!$C$20*(A14-Assumptions!$B$20))))/IF(Assumptions!$B$92=1,1/(1+EXP(-Assumptions!$C$20*(2060-Assumptions!$B$20))),1)) -> 0 | G14: =IF(A14<2025,0,(1/(1+EXP(-Assumptions!$C$21*(A14-Assumptions!$B$21))))/IF(Assumptions!$B$92=1,1/(1+EXP(-Assumptions!$C$21*(2060-Assumptions!$B$21))),1)) -> 0
A15: 2021 | B15: =IF(A15<2025,0,(1/(1+EXP(-Assumptions!$C$16*(A15-Assumptions!$B$16))))/IF(Assumptions!$B$92=1,1/(1+EXP(-Assumptions!$C$16*(2060-Assumptions!$B$16))),1)) -> 0 | C15: =IF(A15<2025,0,(1/(1+EXP(-Assumptions!$C$17*(A15-Assumptions!$B$17))))/IF(Assumptions!$B$92=1,1/(1+EXP(-Assumptions!$C$17*(2060-Assumptions!$B$17))),1)) -> 0 | D15: =IF(A15<2025,0,(1/(1+EXP(-Assumptions!$C$18*(A15-Assumptions!$B$18))))/IF(Assumptions!$B$92=1,1/(1+EXP(-Assumptions!$C$18*(2060-Assumptions!$B$18))),1)) -> 0 | E15: =IF(A15<2025,0,(1/(1+EXP(-Assumptions!$C$19*(A15-Assumptions!$B$19))))/IF(Assumptions!$B$92=1,1/(1+EXP(-Assumptions!$C$19*(2060-Assumptions!$B$19))),1)) -> 0 | F15: =IF(A15<2025,0,(1/(1+EXP(-Assumptions!$C$20*(A15-Assumptions!$B$20))))/IF(Assumptions!$B$92=1,1/(1+EXP(-Assumptions!$C$20*(2060-Assumptions!$B$20))),1)) -> 0 | G15: =IF(A15<2025,0,(1/(1+EXP(-Assumptions!$C$21*(A15-Assumptions!$B$21))))/IF(Assumptions!$B$92=1,1/(1+EXP(-Assumptions!$C$21*(2060-Assumptions!$B$21))),1)) -> 0
... A54: 2060 | B54: =IF(A54<2025,0,(1/(1+EXP(-Assumptions!$C$16*(A54-Assumptions!$B$16))))/IF(Assumptions!$B$92=1,1/(1+EXP(-Assumptions!$C$16*(2060-Assumptions!$B$16))),1)) -> 0.9797293 | C54: =IF(A54<2025,0,(1/(1+EXP(-Assumptions!$C$17*(A54-Assumptions!$B$17))))/IF(Assumptions!$B$92=1,1/(1+EXP(-Assumptions!$C$17*(2060-Assumptions!$B$17))),1)) -> 0.95009307 | D54: =IF(A54<2025,0,(1/(1+EXP(-Assumptions!$C$18*(A54-Assumptions!$B$18))))/IF(Assumptions!$B$92=1,1/(1+EXP(-Assumptions!$C$18*(2060-Assumptions!$B$18))),1)) -> 0.919945 | E54: =IF(A54<2025,0,(1/(1+EXP(-Assumptions!$C$19*(A54-Assumptions!$B$19))))/IF(Assumptions!$B$92=1,1/(1+EXP(-Assumptions!$C$19*(2060-Assumptions!$B$19))),1)) -> 0.80009688 | F54: =IF(A54<2025,0,(1/(1+EXP(-Assumptions!$C$20*(A54-Assumptions!$B$20))))/IF(Assumptions!$B$92=1,1/(1+EXP(-Assumptions!$C$20*(2060-Assumptions!$B$20))),1)) -> 0.95069182 | G54: =IF(A54<2025,0,(1/(1+EXP(-Assumptions!$C$21*(A54-Assumptions!$B$21))))/IF(Assumptions!$B$92=1,1/(1+EXP(-Assumptions!$C$21*(2060-Assumptions!$B$21))),1)) -> 0.90024951

Sheet Load profile
A1: Hourly charging profile under managed (smart) charging and derived load factor
A2: Each column gives the share of that charger segment's daily energy delivered in each hour (sums to 100%). Segment weights (row 30) are the segment's share of 2060 central-case at-wall energy. The aggregate hourly profile is the weighted sum; LF = mean / max. Managed charging shifts home and depot charging into the 22:00-06:00 window and workplace charging into 09:00-15:00 (solar hours). Profiles are stylised, informed by Lukuyu et al. (2024, Sci. Rep.) for African cities and NREL/ICCT load-profile conventions.
A4: Hour | B4: Home (L1+L2, managed overnight) | C4: Workplace/public AC (daytime) | D4: Public DC fast | E4: Depot HD (managed overnight) | F4: Battery swap (distributed) | G4: Aggregate share
A5: 0 | B5: 0.1 | C5: 0 | D5: 0.0097 | E5: 0.11 | F5: 0.0196 | G5: =SUMPRODUCT(B5:F5,$B$30:$F$30) -> 0.068516558
A6: 1 | B6: 0.1 | C6: 0 | D6: 0.0097 | E6: 0.11 | F6: 0.0196 | G6: =SUMPRODUCT(B6:F6,$B$30:$F$30) -> 0.068516558
A7: 2 | B7: 0.1 | C7: 0 | D7: 0.0097 | E7: 0.11 | F7: 0.0196 | G7: =SUMPRODUCT(B7:F7,$B$30:$F$30) -> 0.068516558
A8: 3 | B8: 0.1 | C8: 0 | D8: 0.0097 | E8: 0.11 | F8: 0.0196 | G8: =SUMPRODUCT(B8:F8,$B$30:$F$30) -> 0.068516558
A9: 4 | B9: 0.1 | C9: 0 | D9: 0.0097 | E9: 0.11 | F9: 0.0196 | G9: =SUMPRODUCT(B9:F9,$B$30:$F$30) -> 0.068516558
A10: 5 | B10: 0.09 | C10: 0 | D10: 0.0194 | E10: 0.1 | F10: 0.0294 | G10: =SUMPRODUCT(B10:F10,$B$30:$F$30) -> 0.063879872
A11: 6 | B11: 0.05 | C11: 0 | D11: 0.0388 | E11: 0.04 | F11: 0.049 | G11: =SUMPRODUCT(B11:F11,$B$30:$F$30) -> 0.034105705
A12: 7 | B12: 0.01 | C12: 0.02 | D12: 0.0583 | E12: 0 | F12: 0.0588 | G12: =SUMPRODUCT(B12:F12,$B$30:$F$30) -> 0.016167991
A13: 8 | B13: 0 | C13: 0.06 | D13: 0.068 | E13: 0 | F13: 0.0588 | G13: =SUMPRODUCT(B13:F13,$B$30:$F$30) -> 0.02349818
A14: 9 | B14: 0 | C14: 0.12 | D14: 0.068 | E14: 0 | F14: 0.0588 | G14: =SUMPRODUCT(B14:F14,$B$30:$F$30) -> 0.03589763
A15: 10 | B15: 0 | C15: 0.14 | D15: 0.068 | E15: 0 | F15: 0.0588 | G15: =SUMPRODUCT(B15:F15,$B$30:$F$30) -> 0.040030781
A16: 11 | B16: 0 | C16: 0.14 | D16: 0.068 | E16: 0 | F16: 0.0588 | G16: =SUMPRODUCT(B16:F16,$B$30:$F$30) -> 0.040030781
... A28: 23 | B28: 0.1 | C28: 0 | D28: 0.0097 | E28: 0.08 | F28: 0.0196 | G28: =SUMPRODUCT(B28:F28,$B$30:$F$30) -> 0.056549706
A29: Column sums | B29: =SUM(B5:B28) -> 1 | C29: =SUM(C5:C28) -> 1 | D29: =SUM(D5:D28) -> 1.0003 | E29: =SUM(E5:E28) -> 1 | F29: =SUM(F5:F28) -> 0.9996
A30: Segment energy weight (2060, Scenario B) | B30: =(B37*Assumptions!$D$7+B38*Assumptions!$D$8+B36*Assumptions!$D$6*Assumptions!$B$88/Assumptions!$B$6)/$B$42 -> 0.22724962 | C30: =((B37*(1-Assumptions!$D$7)+B38*(1-Assumptions!$D$8))*0.6)/$B$42 -> 0.20665751 | D30: =((B37*(1-Assumptions!$D$7)+B38*(1-Assumptions!$D$8))*0.4)/$B$42 -> 0.13777167 | E30: =(B39+B40+B41)/$B$42 -> 0.39889507 | F30: =B36*(1-Assumptions!$D$6)*Assumptions!$B$89/Assumptions!$B$6/$B$42 -> 0.029426126 | G30: Non-home LDV energy split 60% public AC / 40% DC fast (stylised).
A32: Load factor LF = mean hourly share / max hourly share: | B32: =AVERAGE(G5:G28)/MAX(G5:G28) -> 0.60814349
A33: Peak hour (0-23): | B33: =INDEX(A5:A28,MATCH(MAX(G5:G28),G5:G28,0)) -> 0
A35: Energy-by-segment weights (2060, Scenario B at-wall TWh)
A36: Motorcycle TWh | B36: ='Results Scenario B'!C39*Assumptions!$B$6*Assumptions!$C$6*Assumptions!$B$61/1000000000 -> 21.559013
A37: Private car TWh | B37: ='Results Scenario B'!D39*Assumptions!$B$7*Assumptions!$C$7*Assumptions!$B$61/1000000000 -> 276.98048
A38: LCV TWh | B38: ='Results Scenario B'!E39*Assumptions!$B$8*Assumptions!$C$8*Assumptions!$B$61/1000000000 -> 38.367161
A39: HGV TWh | B39: ='Results Scenario B'!F39*Assumptions!$B$9*Assumptions!$C$9*Assumptions!$B$61/1000000000 -> 218.36119
A40: Light bus TWh | B40: ='Results Scenario B'!G39*Assumptions!$B$10*Assumptions!$C$10*Assumptions!$B$61/1000000000 -> 1.2562796
A41: Coach TWh | B41: ='Results Scenario B'!H39*Assumptions!$B$11*Assumptions!$C$11*Assumptions!$B$61/1000000000 -> 3.9548224
A42: Total TWh | B42: =SUM(B36:B41) -> 560.47895
A44: Load factor by year (same hourly profiles, each year's charging mix; Scenario B energy by class) | I44: Year | J44: 2025 | K44: 2026 | L44: 2027 | M44: 2028 | N44: 2029 | O44: 2030 | P44: 2031 | Q44: 2032 | R44: 2033 | S44: 2034 | T44: 2035 | U44: 2036 | V44: 2037 | W44: 2038 | X44: 2039 | Y44: 2040 | Z44: 2041 | AA44: 2042 | AB44: 2043 | AC44: 2044 | AD44: 2045 | AE44: 2046 | AF44: 2047 | AG44: 2048 | AH44: 2049 | AI44: 2050 | AJ44: 2051 | AK44: 2052 | AL44: 2053 | AM44: 2054 | AN44: 2055 | AO44: 2056 | AP44: 2057 | AQ44: 2058 | AR44: 2059 | AS44: 2060
I45: Home weight | J45: =('Results Scenario B'!D4*Assumptions!$B$7*Assumptions!$C$7*Assumptions!$B$61*Assumptions!$D$7+'Results Scenario B'!E4*Assumptions!$B$8*Assumptions!$C$8*Assumptions!$B$61*Assumptions!$D$8+'Results Scenario B'!C4*Assumptions!$B$6*Assumptions!$C$6*Assumptions!$B$61*Assumptions!$D$6*Assumptions!$B$88/Assumptions!$B$6)/('Results Scenario B'!C4*Assumptions!$B$6*Assumptions!$C$6*Assumptions!$B$61+'Results Scenario B'!D4*Assumptions!$B$7*Assumptions!$C$7*Assumptions!$B$61+'Results Scenario B'!E4*Assumptions!$B$8*Assumptions!$C$8*Assumptions!$B$61+'Results Scenario B'!F4*Assumptions!$B$9*Assumptions!$C$9*Assumptions!$B$61+'Results Scenario B'!G4*Assumptions!$B$10*Assumptions!$C$10*Assumptions!$B$61+'Results Scenario B'!H4*Assumptions!$B$11*Assumptions!$C$11*Assumptions!$B$61) -> 0.18832245 | K45: =('Results Scenario B'!D5*Assumptions!$B$7*Assumptions!$C$7*Assumptions!$B$61*Assumptions!$D$7+'Results Scenario B'!E5*Assumptions!$B$8*Assumptions!$C$8*Assumptions!$B$61*Assumptions!$D$8+'Results Scenario B'!C5*Assumptions!$B$6*Assumptions!$C$6*Assumptions!$B$61*Assumptions!$D$6*Assumptions!$B$88/Assumptions!$B$6)/('Results Scenario B'!C5*Assumptions!$B$6*Assumptions!$C$6*Assumptions!$B$61+'Results Scenario B'!D5*Assumptions!$B$7*Assumptions!$C$7*Assumptions!$B$61+'Results Scenario B'!E5*Assumptions!$B$8*Assumptions!$C$8*Assumptions!$B$61+'Results Scenario B'!F5*Assumptions!$B$9*Assumptions!$C$9*Assumptions!$B$61+'Results Scenario B'!G5*Assumptions!$B$10*Assumptions!$C$10*Assumptions!$B$61+'Results Scenario B'!H5*Assumptions!$B$11*Assumptions!$C$11*Assumptions!$B$61) -> 0.19291311 | L45: =('Results Scenario B'!D6*Assumptions!$B$7*Assumptions!$C$7*Assumptions!$B$61*Assumptions!$D$7+'Results Scenario B'!E6*Assumptions!$B$8*Assumptions!$C$8*Assumptions!$B$61*Assumptions!$D$8+'Results Scenario B'!C6*Assumptions!$B$6*Assumptions!$C$6*Assumptions!$B$61*Assumptions!$D$6*Assumptions!$B$88/Assumptions!$B$6)/('Results Scenario B'!C6*Assumptions!$B$6*Assumptions!$C$6*Assumptions!$B$61+'Results Scenario B'!D6*Assumptions!$B$7*Assumptions!$C$7*Assumptions!$B$61+'Results Scenario B'!E6*Assumptions!$B$8*Assumptions!$C$8*Assumptions!$B$61+'Results Scenario B'!F6*Assumptions!$B$9*Assumptions!$C$9*Assumptions!$B$61+'Results Scenario B'!G6*Assumptions!$B$10*Assumptions!$C$10*Assumptions!$B$61+'Results Scenario B'!H6*Assumptions!$B$11*Assumptions!$C$11*Assumptions!$B$61) -> 0.19750348 | M45: =('Results Scenario B'!D7*Assumptions!$B$7*Assumptions!$C$7*Assumptions!$B$61*Assumptions!$D$7+'Results Scenario B'!E7*Assumptions!$B$8*Assumptions!$C$8*Assumptions!$B$61*Assumptions!$D$8+'Results Scenario B'!C7*Assumptions!$B$6*Assumptions!$C$6*Assumptions!$B$61*Assumptions!$D$6*Assumptions!$B$88/Assumptions!$B$6)/('Results Scenario B'!C7*Assumptions!$B$6*Assumptions!$C$6*Assumptions!$B$61+'Results Scenario B'!D7*Assumptions!$B$7*Assumptions!$C$7*Assumptions!$B$61+'Results Scenario B'!E7*Assumptions!$B$8*Assumptions!$C$8*Assumptions!$B$61+'Results Scenario B'!F7*Assumptions!$B$9*Assumptions!$C$9*Assumptions!$B$61+'Results Scenario B'!G7*Assumptions!$B$10*Assumptions!$C$10*Assumptions!$B$61+'Results Scenario B'!H7*Assumptions!$B$11*Assumptions!$C$11*Assumptions!$B$61) -> 0.20208528 | N45: =('Results Scenario B'!D8*Assumptions!$B$7*Assumptions!$C$7*Assumptions!$B$61*Assumptions!$D$7+'Results Scenario B'!E8*Assumptions!$B$8*Assumptions!$C$8*Assumptions!$B$61*Assumptions!$D$8+'Results Scenario B'!C8*Assumptions!$B$6*Assumptions!$C$6*Assumptions!$B$61*Assumptions!$D$6*Assumptions!$B$88/Assumptions!$B$6)/('Results Scenario B'!C8*Assumptions!$B$6*Assumptions!$C$6*Assumptions!$B$61+'Results Scenario B'!D8*Assumptions!$B$7*Assumptions!$C$7*Assumptions!$B$61+'Results Scenario B'!E8*Assumptions!$B$8*Assumptions!$C$8*Assumptions!$B$61+'Results Scenario B'!F8*Assumptions!$B$9*Assumptions!$C$9*Assumptions!$B$61+'Results Scenario B'!G8*Assumptions!$B$10*Assumptions!$C$10*Assumptions!$B$61+'Results Scenario B'!H8*Assumptions!$B$11*Assumptions!$C$11*Assumptions!$B$61) -> 0.20664944 | O45: =('Results Scenario B'!D9*Assumptions!$B$7*Assumptions!$C$7*Assumptions!$B$61*Assumptions!$D$7+'Results Scenario B'!E9*Assumptions!$B$8*Assumptions!$C$8*Assumptions!$B$61*Assumptions!$D$8+'Results Scenario B'!C9*Assumptions!$B$6*Assumptions!$C$6*Assumptions!$B$61*Assumptions!$D$6*Assumptions!$B$88/Assumptions!$B$6)/('Results Scenario B'!C9*Assumptions!$B$6*Assumptions!$C$6*Assumptions!$B$61+'Results Scenario B'!D9*Assumptions!$B$7*Assumptions!$C$7*Assumptions!$B$61+'Results Scenario B'!E9*Assumptions!$B$8*Assumptions!$C$8*Assumptions!$B$61+'Results Scenario B'!F9*Assumptions!$B$9*Assumptions!$C$9*Assumptions!$B$61+'Results Scenario B'!G9*Assumptions!$B$10*Assumptions!$C$10*Assumptions!$B$61+'Results Scenario B'!H9*Assumptions!$B$11*Assumptions!$C$11*Assumptions!$B$61) -> 0.21118592 | P45: =('Results Scenario B'!D10*Assumptions!$B$7*Assumptions!$C$7*Assumptions!$B$61*Assumptions!$D$7+'Results Scenario B'!E10*Assumptions!$B$8*Assumptions!$C$8*Assumptions!$B$61*Assumptions!$D$8+'Results Scenario B'!C10*Assumptions!$B$6*Assumptions!$C$6*Assumptions!$B$61*Assumptions!$D$6*Assumptions!$B$88/Assumptions!$B$6)/('Results Scenario B'!C10*Assumptions!$B$6*Assumptions!$C$6*Assumptions!$B$61+'Results Scenario B'!D10*Assumptions!$B$7*Assumptions!$C$7*Assumptions!$B$61+'Results Scenario B'!E10*Assumptions!$B$8*Assumptions!$C$8*Assumptions!$B$61+'Results Scenario B'!F10*Assumptions!$B$9*Assumptions!$C$9*Assumptions!$B$61+'Results Scenario B'!G10*Assumptions!$B$10*Assumptions!$C$10*Assumptions!$B$61+'Results Scenario B'!H10*Assumptions!$B$11*Assumptions!$C$11*Assumptions!$B$61) -> 0.21568344 | Q45: =('Results Scenario B'!D11*Assumptions!$B$7*Assumptions!$C$7*Assumptions!$B$61*Assumptions!$D$7+'Results Scenario B'!E11*Assumptions!$B$8*Assumptions!$C$8*Assumptions!$B$61*Assumptions!$D$8+'Results Scenario B'!C11*Assumptions!$B$6*Assumptions!$C$6*Assumptions!$B$61*Assumptions!$D$6*Assumptions!$B$88/Assumptions!$B$6)/('Results Scenario B'!C11*Assumptions!$B$6*Assumptions!$C$6*Assumptions!$B$61+'Results Scenario B'!D11*Assumptions!$B$7*Assumptions!$C$7*Assumptions!$B$61+'Results Scenario B'!E11*Assumptions!$B$8*Assumptions!$C$8*Assumptions!$B$61+'Results Scenario B'!F11*Assumptions!$B$9*Assumptions!$C$9*Assumptions!$B$61+'Results Scenario B'!G11*Assumptions!$B$10*Assumptions!$C$10*Assumptions!$B$61+'Results Scenario B'!H11*Assumptions!$B$11*Assumptions!$C$11*Assumptions!$B$61) -> 0.22012924 | R45: =('Results Scenario B'!D12*Assumptions!$B$7*Assumptions!$C$7*Assumptions!$B$61*Assumptions!$D$7+'Results Scenario B'!E12*Assumptions!$B$8*Assumptions!$C$8*Assumptions!$B$61*Assumptions!$D$8+'Results Scenario B'!C12*Assumptions!$B$6*Assumptions!$C$6*Assumptions!$B$61*Assumptions!$D$6*Assumptions!$B$88/Assumptions!$B$6)/('Results Scenario B'!C12*Assumptions!$B$6*Assumptions!$C$6*Assumptions!$B$61+'Results Scenario B'!D12*Assumptions!$B$7*Assumptions!$C$7*Assumptions!$B$61+'Results Scenario B'!E12*Assumptions!$B$8*Assumptions!$C$8*Assumptions!$B$61+'Results Scenario B'!F12*Assumptions!$B$9*Assumptions!$C$9*Assumptions!$B$61+'Results Scenario B'!G12*Assumptions!$B$10*Assumptions!$C$10*Assumptions!$B$61+'Results Scenario B'!H12*Assumptions!$B$11*Assumptions!$C$11*Assumptions!$B$61) -> 0.22450868 | S45: =('Results Scenario B'!D13*Assumptions!$B$7*Assumptions!$C$7*Assumptions!$B$61*Assumptions!$D$7+'Results Scenario B'!E13*Assumptions!$B$8*Assumptions!$C$8*Assumptions!$B$61*Assumptions!$D$8+'Results Scenario B'!C13*Assumptions!$B$6*Assumptions!$C$6*Assumptions!$B$61*Assumptions!$D$6*Assumptions!$B$88/Assumptions!$B$6)/('Results Scenario B'!C13*Assumptions!$B$6*Assumptions!$C$6*Assumptions!$B$61+'Results Scenario B'!D13*Assumptions!$B$7*Assumptions!$C$7*Assumptions!$B$61+'Results Scenario B'!E13*Assumptions!$B$8*Assumptions!$C$8*Assumptions!$B$61+'Results Scenario B'!F13*Assumptions!$B$9*Assumptions!$C$9*Assumptions!$B$61+'Results Scenario B'!G13*Assumptions!$B$10*Assumptions!$C$10*Assumptions!$B$61+'Results Scenario B'!H13*Assumptions!$B$11*Assumptions!$C$11*Assumptions!$B$61) -> 0.22880482 | T45: =('Results Scenario B'!D14*Assumptions!$B$7*Assumptions!$C$7*Assumptions!$B$61*Assumptions!$D$7+'Results Scenario B'!E14*Assumptions!$B$8*Assumptions!$C$8*Assumptions!$B$61*Assumptions!$D$8+'Results Scenario B'!C14*Assumptions!$B$6*Assumptions!$C$6*Assumptions!$B$61*Assumptions!$D$6*Assumptions!$B$88/Assumptions!$B$6)/('Results Scenario B'!C14*Assumptions!$B$6*Assumptions!$C$6*Assumptions!$B$61+'Results Scenario B'!D14*Assumptions!$B$7*Assumptions!$C$7*Assumptions!$B$61+'Results Scenario B'!E14*Assumptions!$B$8*Assumptions!$C$8*Assumptions!$B$61+'Results Scenario B'!F14*Assumptions!$B$9*Assumptions!$C$9*Assumptions!$B$61+'Results Scenario B'!G14*Assumptions!$B$10*Assumptions!$C$10*Assumptions!$B$61+'Results Scenario B'!H14*Assumptions!$B$11*Assumptions!$C$11*Assumptions!$B$61) -> 0.23299792 | U45: =('Results Scenario B'!D15*Assumptions!$B$7*Assumptions!$C$7*Assumptions!$B$61*Assumptions!$D$7+'Results Scenario B'!E15*Assumptions!$B$8*Assumptions!$C$8*Assumptions!$B$61*Assumptions!$D$8+'Results Scenario B'!C15*Assumptions!$B$6*Assumptions!$C$6*Assumptions!$B$61*Assumptions!$D$6*Assumptions!$B$88/Assumptions!$B$6)/('Results Scenario B'!C15*Assumptions!$B$6*Assumptions!$C$6*Assumptions!$B$61+'Results Scenario B'!D15*Assumptions!$B$7*Assumptions!$C$7*Assumptions!$B$61+'Results Scenario B'!E15*Assumptions!$B$8*Assumptions!$C$8*Assumptions!$B$61+'Results Scenario B'!F15*Assumptions!$B$9*Assumptions!$C$9*Assumptions!$B$61+'Results Scenario B'!G15*Assumptions!$B$10*Assumptions!$C$10*Assumptions!$B$61+'Results Scenario B'!H15*Assumptions!$B$11*Assumptions!$C$11*Assumptions!$B$61) -> 0.2370649 | V45: =('Results Scenario B'!D16*Assumptions!$B$7*Assumptions!$C$7*Assumptions!$B$61*Assumptions!$D$7+'Results Scenario B'!E16*Assumptions!$B$8*Assumptions!$C$8*Assumptions!$B$61*Assumptions!$D$8+'Results Scenario B'!C16*Assumptions!$B$6*Assumptions!$C$6*Assumptions!$B$61*Assumptions!$D$6*Assumptions!$B$88/Assumptions!$B$6)/('Results Scenario B'!C16*Assumptions!$B$6*Assumptions!$C$6*Assumptions!$B$61+'Results Scenario B'!D16*Assumptions!$B$7*Assumptions!$C$7*Assumptions!$B$61+'Results Scenario B'!E16*Assumptions!$B$8*Assumptions!$C$8*Assumptions!$B$61+'Results Scenario B'!F16*Assumptions!$B$9*Assumptions!$C$9*Assumptions!$B$61+'Results Scenario B'!G16*Assumptions!$B$10*Assumptions!$C$10*Assumptions!$B$61+'Results Scenario B'!H16*Assumptions!$B$11*Assumptions!$C$11*Assumptions!$B$61) -> 0.2409787 | W45: =('Results Scenario B'!D17*Assumptions!$B$7*Assumptions!$C$7*Assumptions!$B$61*Assumptions!$D$7+'Results Scenario B'!E17*Assumptions!$B$8*Assumptions!$C$8*Assumptions!$B$61*Assumptions!$D$8+'Results Scenario B'!C17*Assumptions!$B$6*Assumptions!$C$6*Assumptions!$B$61*Assumptions!$D$6*Assumptions!$B$88/Assumptions!$B$6)/('Results Scenario B'!C17*Assumptions!$B$6*Assumptions!$C$6*Assumptions!$B$61+'Results Scenario B'!D17*Assumptions!$B$7*Assumptions!$C$7*Assumptions!$B$61+'Results Scenario B'!E17*Assumptions!$B$8*Assumptions!$C$8*Assumptions!$B$61+'Results Scenario B'!F17*Assumptions!$B$9*Assumptions!$C$9*Assumptions!$B$61+'Results Scenario B'!G17*Assumptions!$B$10*Assumptions!$C$10*Assumptions!$B$61+'Results Scenario B'!H17*Assumptions!$B$11*Assumptions!$C$11*Assumptions!$B$61) -> 0.24470772 | X45: =('Results Scenario B'!D18*Assumptions!$B$7*Assumptions!$C$7*Assumptions!$B$61*Assumptions!$D$7+'Results Scenario B'!E18*Assumptions!$B$8*Assumptions!$C$8*Assumptions!$B$61*Assumptions!$D$8+'Results Scenario B'!C18*Assumptions!$B$6*Assumptions!$C$6*Assumptions!$B$61*Assumptions!$D$6*Assumptions!$B$88/Assumptions!$B$6)/('Results Scenario B'!C18*Assumptions!$B$6*Assumptions!$C$6*Assumptions!$B$61+'Results Scenario B'!D18*Assumptions!$B$7*Assumptions!$C$7*Assumptions!$B$61+'Results Scenario B'!E18*Assumptions!$B$8*Assumptions!$C$8*Assumptions!$B$61+'Results Scenario B'!F18*Assumptions!$B$9*Assumptions!$C$9*Assumptions!$B$61+'Results Scenario B'!G18*Assumptions!$B$10*Assumptions!$C$10*Assumptions!$B$61+'Results Scenario B'!H18*Assumptions!$B$11*Assumptions!$C$11*Assumptions!$B$61) -> 0.24821527 | Y45: =('Results Scenario B'!D19*Assumptions!$B$7*Assumptions!$C$7*Assumptions!$B$61*Assumptions!$D$7+'Results Scenario B'!E19*Assumptions!$B$8*Assumptions!$C$8*Assumptions!$B$61*Assumptions!$D$8+'Results Scenario B'!C19*Assumptions!$B$6*Assumptions!$C$6*Assumptions!$B$61*Assumptions!$D$6*Assumptions!$B$88/Assumptions!$B$6)/('Results Scenario B'!C19*Assumptions!$B$6*Assumptions!$C$6*Assumptions!$B$61+'Results Scenario B'!D19*Assumptions!$B$7*Assumptions!$C$7*Assumptions!$B$61+'Results Scenario B'!E19*Assumptions!$B$8*Assumptions!$C$8*Assumptions!$B$61+'Results Scenario B'!F19*Assumptions!$B$9*Assumptions!$C$9*Assumptions!$B$61+'Results Scenario B'!G19*Assumptions!$B$10*Assumptions!$C$10*Assumptions!$B$61+'Results Scenario B'!H19*Assumptions!$B$11*Assumptions!$C$11*Assumptions!$B$61) -> 0.25145916 | Z45: =('Results Scenario B'!D20*Assumptions!$B$7*Assumptions!$C$7*Assumptions!$B$61*Assumptions!$D$7+'Results Scenario B'!E20*Assumptions!$B$8*Assumptions!$C$8*Assumptions!$B$61*Assumptions!$D$8+'Results Scenario B'!C20*Assumptions!$B$6*Assumptions!$C$6*Assumptions!$B$61*Assumptions!$D$6*Assumptions!$B$88/Assumptions!$B$6)/('Results Scenario B'!C20*Assumptions!$B$6*Assumptions!$C$6*Assumptions!$B$61+'Results Scenario B'!D20*Assumptions!$B$7*Assumptions!$C$7*Assumptions!$B$61+'Results Scenario B'!E20*Assumptions!$B$8*Assumptions!$C$8*Assumptions!$B$61+'Results Scenario B'!F20*Assumptions!$B$9*Assumptions!$C$9*Assumptions!$B$61+'Results Scenario B'!G20*Assumptions!$B$10*Assumptions!$C$10*Assumptions!$B$61+'Results Scenario B'!H20*Assumptions!$B$11*Assumptions!$C$11*Assumptions!$B$61) -> 0.25439158 | AA45: =('Results Scenario B'!D21*Assumptions!$B$7*Assumptions!$C$7*Assumptions!$B$61*Assumptions!$D$7+'Results Scenario B'!E21*Assumptions!$B$8*Assumptions!$C$8*Assumptions!$B$61*Assumptions!$D$8+'Results Scenario B'!C21*Assumptions!$B$6*Assumptions!$C$6*Assumptions!$B$61*Assumptions!$D$6*Assumptions!$B$88/Assumptions!$B$6)/('Results Scenario B'!C21*Assumptions!$B$6*Assumptions!$C$6*Assumptions!$B$61+'Results Scenario B'!D21*Assumptions!$B$7*Assumptions!$C$7*Assumptions!$B$61+'Results Scenario B'!E21*Assumptions!$B$8*Assumptions!$C$8*Assumptions!$B$61+'Results Scenario B'!F21*Assumptions!$B$9*Assumptions!$C$9*Assumptions!$B$61+'Results Scenario B'!G21*Assumptions!$B$10*Assumptions!$C$10*Assumptions!$B$61+'Results Scenario B'!H21*Assumptions!$B$11*Assumptions!$C$11*Assumptions!$B$61) -> 0.25695944 | AB45: =('Results Scenario B'!D22*Assumptions!$B$7*Assumptions!$C$7*Assumptions!$B$61*Assumptions!$D$7+'Results Scenario B'!E22*Assumptions!$B$8*Assumptions!$C$8*Assumptions!$B$61*Assumptions!$D$8+'Results Scenario B'!C22*Assumptions!$B$6*Assumptions!$C$6*Assumptions!$B$61*Assumptions!$D$6*Assumptions!$B$88/Assumptions!$B$6)/('Results Scenario B'!C22*Assumptions!$B$6*Assumptions!$C$6*Assumptions!$B$61+'Results Scenario B'!D22*Assumptions!$B$7*Assumptions!$C$7*Assumptions!$B$61+'Results Scenario B'!E22*Assumptions!$B$8*Assumptions!$C$8*Assumptions!$B$61+'Results Scenario B'!F22*Assumptions!$B$9*Assumptions!$C$9*Assumptions!$B$61+'Results Scenario B'!G22*Assumptions!$B$10*Assumptions!$C$10*Assumptions!$B$61+'Results Scenario B'!H22*Assumptions!$B$11*Assumptions!$C$11*Assumptions!$B$61) -> 0.25910543 | AC45: =('Results Scenario B'!D23*Assumptions!$B$7*Assumptions!$C$7*Assumptions!$B$61*Assumptions!$D$7+'Results Scenario B'!E23*Assumptions!$B$8*Assumptions!$C$8*Assumptions!$B$61*Assumptions!$D$8+'Results Scenario B'!C23*Assumptions!$B$6*Assumptions!$C$6*Assumptions!$B$61*Assumptions!$D$6*Assumptions!$B$88/Assumptions!$B$6)/('Results Scenario B'!C23*Assumptions!$B$6*Assumptions!$C$6*Assumptions!$B$61+'Results Scenario B'!D23*Assumptions!$B$7*Assumptions!$C$7*Assumptions!$B$61+'Results Scenario B'!E23*Assumptions!$B$8*Assumptions!$C$8*Assumptions!$B$61+'Results Scenario B'!F23*Assumptions!$B$9*Assumptions!$C$9*Assumptions!$B$61+'Results Scenario B'!G23*Assumptions!$B$10*Assumptions!$C$10*Assumptions!$B$61+'Results Scenario B'!H23*Assumptions!$B$11*Assumptions!$C$11*Assumptions!$B$61) -> 0.26077001 | AD45: =('Results Scenario B'!D24*Assumptions!$B$7*Assumptions!$C$7*Assumptions!$B$61*Assumptions!$D$7+'Results Scenario B'!E24*Assumptions!$B$8*Assumptions!$C$8*Assumptions!$B$61*Assumptions!$D$8+'Results Scenario B'!C24*Assumptions!$B$6*Assumptions!$C$6*Assumptions!$B$61*Assumptions!$D$6*Assumptions!$B$88/Assumptions!$B$6)/('Results Scenario B'!C24*Assumptions!$B$6*Assumptions!$C$6*Assumptions!$B$61+'Results Scenario B'!D24*Assumptions!$B$7*Assumptions!$C$7*Assumptions!$B$61+'Results Scenario B'!E24*Assumptions!$B$8*Assumptions!$C$8*Assumptions!$B$61+'Results Scenario B'!F24*Assumptions!$B$9*Assumptions!$C$9*Assumptions!$B$61+'Results Scenario B'!G24*Assumptions!$B$10*Assumptions!$C$10*Assumptions!$B$61+'Results Scenario B'!H24*Assumptions!$B$11*Assumptions!$C$11*Assumptions!$B$61) -> 0.26189491 | AE45: =('Results Scenario B'!D25*Assumptions!$B$7*Assumptions!$C$7*Assumptions!$B$61*Assumptions!$D$7+'Results Scenario B'!E25*Assumptions!$B$8*Assumptions!$C$8*Assumptions!$B$61*Assumptions!$D$8+'Results Scenario B'!C25*Assumptions!$B$6*Assumptions!$C$6*Assumptions!$B$61*Assumptions!$D$6*Assumptions!$B$88/Assumptions!$B$6)/('Results Scenario B'!C25*Assumptions!$B$6*Assumptions!$C$6*Assumptions!$B$61+'Results Scenario B'!D25*Assumptions!$B$7*Assumptions!$C$7*Assumptions!$B$61+'Results Scenario B'!E25*Assumptions!$B$8*Assumptions!$C$8*Assumptions!$B$61+'Results Scenario B'!F25*Assumptions!$B$9*Assumptions!$C$9*Assumptions!$B$61+'Results Scenario B'!G25*Assumptions!$B$10*Assumptions!$C$10*Assumptions!$B$61+'Results Scenario B'!H25*Assumptions!$B$11*Assumptions!$C$11*Assumptions!$B$61) -> 0.26242816 | AF45: =('Results Scenario B'!D26*Assumptions!$B$7*Assumptions!$C$7*Assumptions!$B$61*Assumptions!$D$7+'Results Scenario B'!E26*Assumptions!$B$8*Assumptions!$C$8*Assumptions!$B$61*Assumptions!$D$8+'Results Scenario B'!C26*Assumptions!$B$6*Assumptions!$C$6*Assumptions!$B$61*Assumptions!$D$6*Assumptions!$B$88/Assumptions!$B$6)/('Results Scenario B'!C26*Assumptions!$B$6*Assumptions!$C$6*Assumptions!$B$61+'Results Scenario B'!D26*Assumptions!$B$7*Assumptions!$C$7*Assumptions!$B$61+'Results Scenario B'!E26*Assumptions!$B$8*Assumptions!$C$8*Assumptions!$B$61+'Results Scenario B'!F26*Assumptions!$B$9*Assumptions!$C$9*Assumptions!$B$61+'Results Scenario B'!G26*Assumptions!$B$10*Assumptions!$C$10*Assumptions!$B$61+'Results Scenario B'!H26*Assumptions!$B$11*Assumptions!$C$11*Assumptions!$B$61) -> 0.26233066 | AG45: =('Results Scenario B'!D27*Assumptions!$B$7*Assumptions!$C$7*Assumptions!$B$61*Assumptions!$D$7+'Results Scenario B'!E27*Assumptions!$B$8*Assumptions!$C$8*Assumptions!$B$61*Assumptions!$D$8+'Results Scenario B'!C27*Assumptions!$B$6*Assumptions!$C$6*Assumptions!$B$61*Assumptions!$D$6*Assumptions!$B$88/Assumptions!$B$6)/('Results Scenario B'!C27*Assumptions!$B$6*Assumptions!$C$6*Assumptions!$B$61+'Results Scenario B'!D27*Assumptions!$B$7*Assumptions!$C$7*Assumptions!$B$61+'Results Scenario B'!E27*Assumptions!$B$8*Assumptions!$C$8*Assumptions!$B$61+'Results Scenario B'!F27*Assumptions!$B$9*Assumptions!$C$9*Assumptions!$B$61+'Results Scenario B'!G27*Assumptions!$B$10*Assumptions!$C$10*Assumptions!$B$61+'Results Scenario B'!H27*Assumptions!$B$11*Assumptions!$C$11*Assumptions!$B$61) -> 0.26158355 | AH45: =('Results Scenario B'!D28*Assumptions!$B$7*Assumptions!$C$7*Assumptions!$B$61*Assumptions!$D$7+'Results Scenario B'!E28*Assumptions!$B$8*Assumptions!$C$8*Assumptions!$B$61*Assumptions!$D$8+'Results Scenario B'!C28*Assumptions!$B$6*Assumptions!$C$6*Assumptions!$B$61*Assumptions!$D$6*Assumptions!$B$88/Assumptions!$B$6)/('Results Scenario B'!C28*Assumptions!$B$6*Assumptions!$C$6*Assumptions!$B$61+'Results Scenario B'!D28*Assumptions!$B$7*Assumptions!$C$7*Assumptions!$B$61+'Results Scenario B'!E28*Assumptions!$B$8*Assumptions!$C$8*Assumptions!$B$61+'Results Scenario B'!F28*Assumptions!$B$9*Assumptions!$C$9*Assumptions!$B$61+'Results Scenario B'!G28*Assumptions!$B$10*Assumptions!$C$10*Assumptions!$B$61+'Results Scenario B'!H28*Assumptions!$B$11*Assumptions!$C$11*Assumptions!$B$61) -> 0.26019514 | AI45: =('Results Scenario B'!D29*Assumptions!$B$7*Assumptions!$C$7*Assumptions!$B$61*Assumptions!$D$7+'Results Scenario B'!E29*Assumptions!$B$8*Assumptions!$C$8*Assumptions!$B$61*Assumptions!$D$8+'Results Scenario B'!C29*Assumptions!$B$6*Assumptions!$C$6*Assumptions!$B$61*Assumptions!$D$6*Assumptions!$B$88/Assumptions!$B$6)/('Results Scenario B'!C29*Assumptions!$B$6*Assumptions!$C$6*Assumptions!$B$61+'Results Scenario B'!D29*Assumptions!$B$7*Assumptions!$C$7*Assumptions!$B$61+'Results Scenario B'!E29*Assumptions!$B$8*Assumptions!$C$8*Assumptions!$B$61+'Results Scenario B'!F29*Assumptions!$B$9*Assumptions!$C$9*Assumptions!$B$61+'Results Scenario B'!G29*Assumptions!$B$10*Assumptions!$C$10*Assumptions!$B$61+'Results Scenario B'!H29*Assumptions!$B$11*Assumptions!$C$11*Assumptions!$B$61) -> 0.25820524 | AJ45: =('Results Scenario B'!D30*Assumptions!$B$7*Assumptions!$C$7*Assumptions!$B$61*Assumptions!$D$7+'Results Scenario B'!E30*Assumptions!$B$8*Assumptions!$C$8*Assumptions!$B$61*Assumptions!$D$8+'Results Scenario B'!C30*Assumptions!$B$6*Assumptions!$C$6*Assumptions!$B$61*Assumptions!$D$6*Assumptions!$B$88/Assumptions!$B$6)/('Results Scenario B'!C30*Assumptions!$B$6*Assumptions!$C$6*Assumptions!$B$61+'Results Scenario B'!D30*Assumptions!$B$7*Assumptions!$C$7*Assumptions!$B$61+'Results Scenario B'!E30*Assumptions!$B$8*Assumptions!$C$8*Assumptions!$B$61+'Results Scenario B'!F30*Assumptions!$B$9*Assumptions!$C$9*Assumptions!$B$61+'Results Scenario B'!G30*Assumptions!$B$10*Assumptions!$C$10*Assumptions!$B$61+'Results Scenario B'!H30*Assumptions!$B$11*Assumptions!$C$11*Assumptions!$B$61) -> 0.25568576 | AK45: =('Results Scenario B'!D31*Assumptions!$B$7*Assumptions!$C$7*Assumptions!$B$61*Assumptions!$D$7+'Results Scenario B'!E31*Assumptions!$B$8*Assumptions!$C$8*Assumptions!$B$61*Assumptions!$D$8+'Results Scenario B'!C31*Assumptions!$B$6*Assumptions!$C$6*Assumptions!$B$61*Assumptions!$D$6*Assumptions!$B$88/Assumptions!$B$6)/('Results Scenario B'!C31*Assumptions!$B$6*Assumptions!$C$6*Assumptions!$B$61+'Results Scenario B'!D31*Assumptions!$B$7*Assumptions!$C$7*Assumptions!$B$61+'Results Scenario B'!E31*Assumptions!$B$8*Assumptions!$C$8*Assumptions!$B$61+'Results Scenario B'!F31*Assumptions!$B$9*Assumptions!$C$9*Assumptions!$B$61+'Results Scenario B'!G31*Assumptions!$B$10*Assumptions!$C$10*Assumptions!$B$61+'Results Scenario B'!H31*Assumptions!$B$11*Assumptions!$C$11*Assumptions!$B$61) -> 0.25273637 | AL45: =('Results Scenario B'!D32*Assumptions!$B$7*Assumptions!$C$7*Assumptions!$B$61*Assumptions!$D$7+'Results Scenario B'!E32*Assumptions!$B$8*Assumptions!$C$8*Assumptions!$B$61*Assumptions!$D$8+'Results Scenario B'!C32*Assumptions!$B$6*Assumptions!$C$6*Assumptions!$B$61*Assumptions!$D$6*Assumptions!$B$88/Assumptions!$B$6)/('Results Scenario B'!C32*Assumptions!$B$6*Assumptions!$C$6*Assumptions!$B$61+'Results Scenario B'!D32*Assumptions!$B$7*Assumptions!$C$7*Assumptions!$B$61+'Results Scenario B'!E32*Assumptions!$B$8*Assumptions!$C$8*Assumptions!$B$61+'Results Scenario B'!F32*Assumptions!$B$9*Assumptions!$C$9*Assumptions!$B$61+'Results Scenario B'!G32*Assumptions!$B$10*Assumptions!$C$10*Assumptions!$B$61+'Results Scenario B'!H32*Assumptions!$B$11*Assumptions!$C$11*Assumptions!$B$61) -> 0.24947606 | AM45: =('Results Scenario B'!D33*Assumptions!$B$7*Assumptions!$C$7*Assumptions!$B$61*Assumptions!$D$7+'Results Scenario B'!E33*Assumptions!$B$8*Assumptions!$C$8*Assumptions!$B$61*Assumptions!$D$8+'Results Scenario B'!C33*Assumptions!$B$6*Assumptions!$C$6*Assumptions!$B$61*Assumptions!$D$6*Assumptions!$B$88/Assumptions!$B$6)/('Results Scenario B'!C33*Assumptions!$B$6*Assumptions!$C$6*Assumptions!$B$61+'Results Scenario B'!D33*Assumptions!$B$7*Assumptions!$C$7*Assumptions!$B$61+'Results Scenario B'!E33*Assumptions!$B$8*Assumptions!$C$8*Assumptions!$B$61+'Results Scenario B'!F33*Assumptions!$B$9*Assumptions!$C$9*Assumptions!$B$61+'Results Scenario B'!G33*Assumptions!$B$10*Assumptions!$C$10*Assumptions!$B$61+'Results Scenario B'!H33*Assumptions!$B$11*Assumptions!$C$11*Assumptions!$B$61) -> 0.24603203 | AN45: =('Results Scenario B'!D34*Assumptions!$B$7*Assumptions!$C$7*Assumptions!$B$61*Assumptions!$D$7+'Results Scenario B'!E34*Assumptions!$B$8*Assumptions!$C$8*Assumptions!$B$61*Assumptions!$D$8+'Results Scenario B'!C34*Assumptions!$B$6*Assumptions!$C$6*Assumptions!$B$61*Assumptions!$D$6*Assumptions!$B$88/Assumptions!$B$6)/('Results Scenario B'!C34*Assumptions!$B$6*Assumptions!$C$6*Assumptions!$B$61+'Results Scenario B'!D34*Assumptions!$B$7*Assumptions!$C$7*Assumptions!$B$61+'Results Scenario B'!E34*Assumptions!$B$8*Assumptions!$C$8*Assumptions!$B$61+'Results Scenario B'!F34*Assumptions!$B$9*Assumptions!$C$9*Assumptions!$B$61+'Results Scenario B'!G34*Assumptions!$B$10*Assumptions!$C$10*Assumptions!$B$61+'Results Scenario B'!H34*Assumptions!$B$11*Assumptions!$C$11*Assumptions!$B$61) -> 0.24252822 | AO45: =('Results Scenario B'!D35*Assumptions!$B$7*Assumptions!$C$7*Assumptions!$B$61*Assumptions!$D$7+'Results Scenario B'!E35*Assumptions!$B$8*Assumptions!$C$8*Assumptions!$B$61*Assumptions!$D$8+'Results Scenario B'!C35*Assumptions!$B$6*Assumptions!$C$6*Assumptions!$B$61*Assumptions!$D$6*Assumptions!$B$88/Assumptions!$B$6)/('Results Scenario B'!C35*Assumptions!$B$6*Assumptions!$C$6*Assumptions!$B$61+'Results Scenario B'!D35*Assumptions!$B$7*Assumptions!$C$7*Assumptions!$B$61+'Results Scenario B'!E35*Assumptions!$B$8*Assumptions!$C$8*Assumptions!$B$61+'Results Scenario B'!F35*Assumptions!$B$9*Assumptions!$C$9*Assumptions!$B$61+'Results Scenario B'!G35*Assumptions!$B$10*Assumptions!$C$10*Assumptions!$B$61+'Results Scenario B'!H35*Assumptions!$B$11*Assumptions!$C$11*Assumptions!$B$61) -> 0.23907546 | AP45: =('Results Scenario B'!D36*Assumptions!$B$7*Assumptions!$C$7*Assumptions!$B$61*Assumptions!$D$7+'Results Scenario B'!E36*Assumptions!$B$8*Assumptions!$C$8*Assumptions!$B$61*Assumptions!$D$8+'Results Scenario B'!C36*Assumptions!$B$6*Assumptions!$C$6*Assumptions!$B$61*Assumptions!$D$6*Assumptions!$B$88/Assumptions!$B$6)/('Results Scenario B'!C36*Assumptions!$B$6*Assumptions!$C$6*Assumptions!$B$61+'Results Scenario B'!D36*Assumptions!$B$7*Assumptions!$C$7*Assumptions!$B$61+'Results Scenario B'!E36*Assumptions!$B$8*Assumptions!$C$8*Assumptions!$B$61+'Results Scenario B'!F36*Assumptions!$B$9*Assumptions!$C$9*Assumptions!$B$61+'Results Scenario B'!G36*Assumptions!$B$10*Assumptions!$C$10*Assumptions!$B$61+'Results Scenario B'!H36*Assumptions!$B$11*Assumptions!$C$11*Assumptions!$B$61) -> 0.23576471 | AQ45: =('Results Scenario B'!D37*Assumptions!$B$7*Assumptions!$C$7*Assumptions!$B$61*Assumptions!$D$7+'Results Scenario B'!E37*Assumptions!$B$8*Assumptions!$C$8*Assumptions!$B$61*Assumptions!$D$8+'Results Scenario B'!C37*Assumptions!$B$6*Assumptions!$C$6*Assumptions!$B$61*Assumptions!$D$6*Assumptions!$B$88/Assumptions!$B$6)/('Results Scenario B'!C37*Assumptions!$B$6*Assumptions!$C$6*Assumptions!$B$61+'Results Scenario B'!D37*Assumptions!$B$7*Assumptions!$C$7*Assumptions!$B$61+'Results Scenario B'!E37*Assumptions!$B$8*Assumptions!$C$8*Assumptions!$B$61+'Results Scenario B'!F37*Assumptions!$B$9*Assumptions!$C$9*Assumptions!$B$61+'Results Scenario B'!G37*Assumptions!$B$10*Assumptions!$C$10*Assumptions!$B$61+'Results Scenario B'!H37*Assumptions!$B$11*Assumptions!$C$11*Assumptions!$B$61) -> 0.23266384 | AR45: =('Results Scenario B'!D38*Assumptions!$B$7*Assumptions!$C$7*Assumptions!$B$61*Assumptions!$D$7+'Results Scenario B'!E38*Assumptions!$B$8*Assumptions!$C$8*Assumptions!$B$61*Assumptions!$D$8+'Results Scenario B'!C38*Assumptions!$B$6*Assumptions!$C$6*Assumptions!$B$61*Assumptions!$D$6*Assumptions!$B$88/Assumptions!$B$6)/('Results Scenario B'!C38*Assumptions!$B$6*Assumptions!$C$6*Assumptions!$B$61+'Results Scenario B'!D38*Assumptions!$B$7*Assumptions!$C$7*Assumptions!$B$61+'Results Scenario B'!E38*Assumptions!$B$8*Assumptions!$C$8*Assumptions!$B$61+'Results Scenario B'!F38*Assumptions!$B$9*Assumptions!$C$9*Assumptions!$B$61+'Results Scenario B'!G38*Assumptions!$B$10*Assumptions!$C$10*Assumptions!$B$61+'Results Scenario B'!H38*Assumptions!$B$11*Assumptions!$C$11*Assumptions!$B$61) -> 0.22981754 | AS45: =('Results Scenario B'!D39*Assumptions!$B$7*Assumptions!$C$7*Assumptions!$B$61*Assumptions!$D$7+'Results Scenario B'!E39*Assumptions!$B$8*Assumptions!$C$8*Assumptions!$B$61*Assumptions!$D$8+'Results Scenario B'!C39*Assumptions!$B$6*Assumptions!$C$6*Assumptions!$B$61*Assumptions!$D$6*Assumptions!$B$88/Assumptions!$B$6)/('Results Scenario B'!C39*Assumptions!$B$6*Assumptions!$C$6*Assumptions!$B$61+'Results Scenario B'!D39*Assumptions!$B$7*Assumptions!$C$7*Assumptions!$B$61+'Results Scenario B'!E39*Assumptions!$B$8*Assumptions!$C$8*Assumptions!$B$61+'Results Scenario B'!F39*Assumptions!$B$9*Assumptions!$C$9*Assumptions!$B$61+'Results Scenario B'!G39*Assumptions!$B$10*Assumptions!$C$10*Assumptions!$B$61+'Results Scenario B'!H39*Assumptions!$B$11*Assumptions!$C$11*Assumptions!$B$61) -> 0.22724962
I46: Workplace/public AC weight | J46: =(('Results Scenario B'!D4*Assumptions!$B$7*Assumptions!$C$7*Assumptions!$B$61*(1-Assumptions!$D$7)+'Results Scenario B'!E4*Assumptions!$B$8*Assumptions!$C$8*Assumptions!$B$61*(1-Assumptions!$D$8))*0.6)/('Results Scenario B'!C4*Assumptions!$B$6*Assumptions!$C$6*Assumptions!$B$61+'Results Scenario B'!D4*Assumptions!$B$7*Assumptions!$C$7*Assumptions!$B$61+'Results Scenario B'!E4*Assumptions!$B$8*Assumptions!$C$8*Assumptions!$B$61+'Results Scenario B'!F4*Assumptions!$B$9*Assumptions!$C$9*Assumptions!$B$61+'Results Scenario B'!G4*Assumptions!$B$10*Assumptions!$C$10*Assumptions!$B$61+'Results Scenario B'!H4*Assumptions!$B$11*Assumptions!$C$11*Assumptions!$B$61) -> 0.17715544 | K46: =(('Results Scenario B'!D5*Assumptions!$B$7*Assumptions!$C$7*Assumptions!$B$61*(1-Assumptions!$D$7)+'Results Scenario B'!E5*Assumptions!$B$8*Assumptions!$C$8*Assumptions!$B$61*(1-Assumptions!$D$8))*0.6)/('Results Scenario B'!C5*Assumptions!$B$6*Assumptions!$C$6*Assumptions!$B$61+'Results Scenario B'!D5*Assumptions!$B$7*Assumptions!$C$7*Assumptions!$B$61+'Results Scenario B'!E5*Assumptions!$B$8*Assumptions!$C$8*Assumptions!$B$61+'Results Scenario B'!F5*Assumptions!$B$9*Assumptions!$C$9*Assumptions!$B$61+'Results Scenario B'!G5*Assumptions!$B$10*Assumptions!$C$10*Assumptions!$B$61+'Results Scenario B'!H5*Assumptions!$B$11*Assumptions!$C$11*Assumptions!$B$61) -> 0.18090021 | L46: =(('Results Scenario B'!D6*Assumptions!$B$7*Assumptions!$C$7*Assumptions!$B$61*(1-Assumptions!$D$7)+'Results Scenario B'!E6*Assumptions!$B$8*Assumptions!$C$8*Assumptions!$B$61*(1-Assumptions!$D$8))*0.6)/('Results Scenario B'!C6*Assumptions!$B$6*Assumptions!$C$6*Assumptions!$B$61+'Results Scenario B'!D6*Assumptions!$B$7*Assumptions!$C$7*Assumptions!$B$61+'Results Scenario B'!E6*Assumptions!$B$8*Assumptions!$C$8*Assumptions!$B$61+'Results Scenario B'!F6*Assumptions!$B$9*Assumptions!$C$9*Assumptions!$B$61+'Results Scenario B'!G6*Assumptions!$B$10*Assumptions!$C$10*Assumptions!$B$61+'Results Scenario B'!H6*Assumptions!$B$11*Assumptions!$C$11*Assumptions!$B$61) -> 0.18462083 | M46: =(('Results Scenario B'!D7*Assumptions!$B$7*Assumptions!$C$7*Assumptions!$B$61*(1-Assumptions!$D$7)+'Results Scenario B'!E7*Assumptions!$B$8*Assumptions!$C$8*Assumptions!$B$61*(1-Assumptions!$D$8))*0.6)/('Results Scenario B'!C7*Assumptions!$B$6*Assumptions!$C$6*Assumptions!$B$61+'Results Scenario B'!D7*Assumptions!$B$7*Assumptions!$C$7*Assumptions!$B$61+'Results Scenario B'!E7*Assumptions!$B$8*Assumptions!$C$8*Assumptions!$B$61+'Results Scenario B'!F7*Assumptions!$B$9*Assumptions!$C$9*Assumptions!$B$61+'Results Scenario B'!G7*Assumptions!$B$10*Assumptions!$C$10*Assumptions!$B$61+'Results Scenario B'!H7*Assumptions!$B$11*Assumptions!$C$11*Assumptions!$B$61) -> 0.18830987 | N46: =(('Results Scenario B'!D8*Assumptions!$B$7*Assumptions!$C$7*Assumptions!$B$61*(1-Assumptions!$D$7)+'Results Scenario B'!E8*Assumptions!$B$8*Assumptions!$C$8*Assumptions!$B$61*(1-Assumptions!$D$8))*0.6)/('Results Scenario B'!C8*Assumptions!$B$6*Assumptions!$C$6*Assumptions!$B$61+'Results Scenario B'!D8*Assumptions!$B$7*Assumptions!$C$7*Assumptions!$B$61+'Results Scenario B'!E8*Assumptions!$B$8*Assumptions!$C$8*Assumptions!$B$61+'Results Scenario B'!F8*Assumptions!$B$9*Assumptions!$C$9*Assumptions!$B$61+'Results Scenario B'!G8*Assumptions!$B$10*Assumptions!$C$10*Assumptions!$B$61+'Results Scenario B'!H8*Assumptions!$B$11*Assumptions!$C$11*Assumptions!$B$61) -> 0.19195939 | O46: =(('Results Scenario B'!D9*Assumptions!$B$7*Assumptions!$C$7*Assumptions!$B$61*(1-Assumptions!$D$7)+'Results Scenario B'!E9*Assumptions!$B$8*Assumptions!$C$8*Assumptions!$B$61*(1-Assumptions!$D$8))*0.6)/('Results Scenario B'!C9*Assumptions!$B$6*Assumptions!$C$6*Assumptions!$B$61+'Results Scenario B'!D9*Assumptions!$B$7*Assumptions!$C$7*Assumptions!$B$61+'Results Scenario B'!E9*Assumptions!$B$8*Assumptions!$C$8*Assumptions!$B$61+'Results Scenario B'!F9*Assumptions!$B$9*Assumptions!$C$9*Assumptions!$B$61+'Results Scenario B'!G9*Assumptions!$B$10*Assumptions!$C$10*Assumptions!$B$61+'Results Scenario B'!H9*Assumptions!$B$11*Assumptions!$C$11*Assumptions!$B$61) -> 0.19556086 | P46: =(('Results Scenario B'!D10*Assumptions!$B$7*Assumptions!$C$7*Assumptions!$B$61*(1-Assumptions!$D$7)+'Results Scenario B'!E10*Assumptions!$B$8*Assumptions!$C$8*Assumptions!$B$61*(1-Assumptions!$D$8))*0.6)/('Results Scenario B'!C10*Assumptions!$B$6*Assumptions!$C$6*Assumptions!$B$61+'Results Scenario B'!D10*Assumptions!$B$7*Assumptions!$C$7*Assumptions!$B$61+'Results Scenario B'!E10*Assumptions!$B$8*Assumptions!$C$8*Assumptions!$B$61+'Results Scenario B'!F10*Assumptions!$B$9*Assumptions!$C$9*Assumptions!$B$61+'Results Scenario B'!G10*Assumptions!$B$10*Assumptions!$C$10*Assumptions!$B$61+'Results Scenario B'!H10*Assumptions!$B$11*Assumptions!$C$11*Assumptions!$B$61) -> 0.19910501 | Q46: =(('Results Scenario B'!D11*Assumptions!$B$7*Assumptions!$C$7*Assumptions!$B$61*(1-Assumptions!$D$7)+'Results Scenario B'!E11*Assumptions!$B$8*Assumptions!$C$8*Assumptions!$B$61*(1-Assumptions!$D$8))*0.6)/('Results Scenario B'!C11*Assumptions!$B$6*Assumptions!$C$6*Assumptions!$B$61+'Results Scenario B'!D11*Assumptions!$B$7*Assumptions!$C$7*Assumptions!$B$61+'Results Scenario B'!E11*Assumptions!$B$8*Assumptions!$C$8*Assumptions!$B$61+'Results Scenario B'!F11*Assumptions!$B$9*Assumptions!$C$9*Assumptions!$B$61+'Results Scenario B'!G11*Assumptions!$B$10*Assumptions!$C$10*Assumptions!$B$61+'Results Scenario B'!H11*Assumptions!$B$11*Assumptions!$C$11*Assumptions!$B$61) -> 0.20258176 | R46: =(('Results Scenario B'!D12*Assumptions!$B$7*Assumptions!$C$7*Assumptions!$B$61*(1-Assumptions!$D$7)+'Results Scenario B'!E12*Assumptions!$B$8*Assumptions!$C$8*Assumptions!$B$61*(1-Assumptions!$D$8))*0.6)/('Results Scenario B'!C12*Assumptions!$B$6*Assumptions!$C$6*Assumptions!$B$61+'Results Scenario B'!D12*Assumptions!$B$7*Assumptions!$C$7*Assumptions!$B$61+'Results Scenario B'!E12*Assumptions!$B$8*Assumptions!$C$8*Assumptions!$B$61+'Results Scenario B'!F12*Assumptions!$B$9*Assumptions!$C$9*Assumptions!$B$61+'Results Scenario B'!G12*Assumptions!$B$10*Assumptions!$C$10*Assumptions!$B$61+'Results Scenario B'!H12*Assumptions!$B$11*Assumptions!$C$11*Assumptions!$B$61) -> 0.20598004 | S46: =(('Results Scenario B'!D13*Assumptions!$B$7*Assumptions!$C$7*Assumptions!$B$61*(1-Assumptions!$D$7)+'Results Scenario B'!E13*Assumptions!$B$8*Assumptions!$C$8*Assumptions!$B$61*(1-Assumptions!$D$8))*0.6)/('Results Scenario B'!C13*Assumptions!$B$6*Assumptions!$C$6*Assumptions!$B$61+'Results Scenario B'!D13*Assumptions!$B$7*Assumptions!$C$7*Assumptions!$B$61+'Results Scenario B'!E13*Assumptions!$B$8*Assumptions!$C$8*Assumptions!$B$61+'Results Scenario B'!F13*Assumptions!$B$9*Assumptions!$C$9*Assumptions!$B$61+'Results Scenario B'!G13*Assumptions!$B$10*Assumptions!$C$10*Assumptions!$B$61+'Results Scenario B'!H13*Assumptions!$B$11*Assumptions!$C$11*Assumptions!$B$61) -> 0.20928769 | T46: =(('Results Scenario B'!D14*Assumptions!$B$7*Assumptions!$C$7*Assumptions!$B$61*(1-Assumptions!$D$7)+'Results Scenario B'!E14*Assumptions!$B$8*Assumptions!$C$8*Assumptions!$B$61*(1-Assumptions!$D$8))*0.6)/('Results Scenario B'!C14*Assumptions!$B$6*Assumptions!$C$6*Assumptions!$B$61+'Results Scenario B'!D14*Assumptions!$B$7*Assumptions!$C$7*Assumptions!$B$61+'Results Scenario B'!E14*Assumptions!$B$8*Assumptions!$C$8*Assumptions!$B$61+'Results Scenario B'!F14*Assumptions!$B$9*Assumptions!$C$9*Assumptions!$B$61+'Results Scenario B'!G14*Assumptions!$B$10*Assumptions!$C$10*Assumptions!$B$61+'Results Scenario B'!H14*Assumptions!$B$11*Assumptions!$C$11*Assumptions!$B$61) -> 0.21249123 | U46: =(('Results Scenario B'!D15*Assumptions!$B$7*Assumptions!$C$7*Assumptions!$B$61*(1-Assumptions!$D$7)+'Results Scenario B'!E15*Assumptions!$B$8*Assumptions!$C$8*Assumptions!$B$61*(1-Assumptions!$D$8))*0.6)/('Results Scenario B'!C15*Assumptions!$B$6*Assumptions!$C$6*Assumptions!$B$61+'Results Scenario B'!D15*Assumptions!$B$7*Assumptions!$C$7*Assumptions!$B$61+'Results Scenario B'!E15*Assumptions!$B$8*Assumptions!$C$8*Assumptions!$B$61+'Results Scenario B'!F15*Assumptions!$B$9*Assumptions!$C$9*Assumptions!$B$61+'Results Scenario B'!G15*Assumptions!$B$10*Assumptions!$C$10*Assumptions!$B$61+'Results Scenario B'!H15*Assumptions!$B$11*Assumptions!$C$11*Assumptions!$B$61) -> 0.2155758 | V46: =(('Results Scenario B'!D16*Assumptions!$B$7*Assumptions!$C$7*Assumptions!$B$61*(1-Assumptions!$D$7)+'Results Scenario B'!E16*Assumptions!$B$8*Assumptions!$C$8*Assumptions!$B$61*(1-Assumptions!$D$8))*0.6)/('Results Scenario B'!C16*Assumptions!$B$6*Assumptions!$C$6*Assumptions!$B$61+'Results Scenario B'!D16*Assumptions!$B$7*Assumptions!$C$7*Assumptions!$B$61+'Results Scenario B'!E16*Assumptions!$B$8*Assumptions!$C$8*Assumptions!$B$61+'Results Scenario B'!F16*Assumptions!$B$9*Assumptions!$C$9*Assumptions!$B$61+'Results Scenario B'!G16*Assumptions!$B$10*Assumptions!$C$10*Assumptions!$B$61+'Results Scenario B'!H16*Assumptions!$B$11*Assumptions!$C$11*Assumptions!$B$61) -> 0.21852497 | W46: =(('Results Scenario B'!D17*Assumptions!$B$7*Assumptions!$C$7*Assumptions!$B$61*(1-Assumptions!$D$7)+'Results Scenario B'!E17*Assumptions!$B$8*Assumptions!$C$8*Assumptions!$B$61*(1-Assumptions!$D$8))*0.6)/('Results Scenario B'!C17*Assumptions!$B$6*Assumptions!$C$6*Assumptions!$B$61+'Results Scenario B'!D17*Assumptions!$B$7*Assumptions!$C$7*Assumptions!$B$61+'Results Scenario B'!E17*Assumptions!$B$8*Assumptions!$C$8*Assumptions!$B$61+'Results Scenario B'!F17*Assumptions!$B$9*Assumptions!$C$9*Assumptions!$B$61+'Results Scenario B'!G17*Assumptions!$B$10*Assumptions!$C$10*Assumptions!$B$61+'Results Scenario B'!H17*Assumptions!$B$11*Assumptions!$C$11*Assumptions!$B$61) -> 0.2213205 | X46: =(('Results Scenario B'!D18*Assumptions!$B$7*Assumptions!$C$7*Assumptions!$B$61*(1-Assumptions!$D$7)+'Results Scenario B'!E18*Assumptions!$B$8*Assumptions!$C$8*Assumptions!$B$61*(1-Assumptions!$D$8))*0.6)/('Results Scenario B'!C18*Assumptions!$B$6*Assumptions!$C$6*Assumptions!$B$61+'Results Scenario B'!D18*Assumptions!$B$7*Assumptions!$C$7*Assumptions!$B$61+'Results Scenario B'!E18*Assumptions!$B$8*Assumptions!$C$8*Assumptions!$B$61+'Results Scenario B'!F18*Assumptions!$B$9*Assumptions!$C$9*Assumptions!$B$61+'Results Scenario B'!G18*Assumptions!$B$10*Assumptions!$C$10*Assumptions!$B$61+'Results Scenario B'!H18*Assumptions!$B$11*Assumptions!$C$11*Assumptions!$B$61) -> 0.22394218 | Y46: =(('Results Scenario B'!D19*Assumptions!$B$7*Assumptions!$C$7*Assumptions!$B$61*(1-Assumptions!$D$7)+'Results Scenario B'!E19*Assumptions!$B$8*Assumptions!$C$8*Assumptions!$B$61*(1-Assumptions!$D$8))*0.6)/('Results Scenario B'!C19*Assumptions!$B$6*Assumptions!$C$6*Assumptions!$B$61+'Results Scenario B'!D19*Assumptions!$B$7*Assumptions!$C$7*Assumptions!$B$61+'Results Scenario B'!E19*Assumptions!$B$8*Assumptions!$C$8*Assumptions!$B$61+'Results Scenario B'!F19*Assumptions!$B$9*Assumptions!$C$9*Assumptions!$B$61+'Results Scenario B'!G19*Assumptions!$B$10*Assumptions!$C$10*Assumptions!$B$61+'Results Scenario B'!H19*Assumptions!$B$11*Assumptions!$C$11*Assumptions!$B$61) -> 0.22636733 | Z46: =(('Results Scenario B'!D20*Assumptions!$B$7*Assumptions!$C$7*Assumptions!$B$61*(1-Assumptions!$D$7)+'Results Scenario B'!E20*Assumptions!$B$8*Assumptions!$C$8*Assumptions!$B$61*(1-Assumptions!$D$8))*0.6)/('Results Scenario B'!C20*Assumptions!$B$6*Assumptions!$C$6*Assumptions!$B$61+'Results Scenario B'!D20*Assumptions!$B$7*Assumptions!$C$7*Assumptions!$B$61+'Results Scenario B'!E20*Assumptions!$B$8*Assumptions!$C$8*Assumptions!$B$61+'Results Scenario B'!F20*Assumptions!$B$9*Assumptions!$C$9*Assumptions!$B$61+'Results Scenario B'!G20*Assumptions!$B$10*Assumptions!$C$10*Assumptions!$B$61+'Results Scenario B'!H20*Assumptions!$B$11*Assumptions!$C$11*Assumptions!$B$61) -> 0.22857021 | AA46: =(('Results Scenario B'!D21*Assumptions!$B$7*Assumptions!$C$7*Assumptions!$B$61*(1-Assumptions!$D$7)+'Results Scenario B'!E21*Assumptions!$B$8*Assumptions!$C$8*Assumptions!$B$61*(1-Assumptions!$D$8))*0.6)/('Results Scenario B'!C21*Assumptions!$B$6*Assumptions!$C$6*Assumptions!$B$61+'Results Scenario B'!D21*Assumptions!$B$7*Assumptions!$C$7*Assumptions!$B$61+'Results Scenario B'!E21*Assumptions!$B$8*Assumptions!$C$8*Assumptions!$B$61+'Results Scenario B'!F21*Assumptions!$B$9*Assumptions!$C$9*Assumptions!$B$61+'Results Scenario B'!G21*Assumptions!$B$10*Assumptions!$C$10*Assumptions!$B$61+'Results Scenario B'!H21*Assumptions!$B$11*Assumptions!$C$11*Assumptions!$B$61) -> 0.23052105 | AB46: =(('Results Scenario B'!D22*Assumptions!$B$7*Assumptions!$C$7*Assumptions!$B$61*(1-Assumptions!$D$7)+'Results Scenario B'!E22*Assumptions!$B$8*Assumptions!$C$8*Assumptions!$B$61*(1-Assumptions!$D$8))*0.6)/('Results Scenario B'!C22*Assumptions!$B$6*Assumptions!$C$6*Assumptions!$B$61+'Results Scenario B'!D22*Assumptions!$B$7*Assumptions!$C$7*Assumptions!$B$61+'Results Scenario B'!E22*Assumptions!$B$8*Assumptions!$C$8*Assumptions!$B$61+'Results Scenario B'!F22*Assumptions!$B$9*Assumptions!$C$9*Assumptions!$B$61+'Results Scenario B'!G22*Assumptions!$B$10*Assumptions!$C$10*Assumptions!$B$61+'Results Scenario B'!H22*Assumptions!$B$11*Assumptions!$C$11*Assumptions!$B$61) -> 0.23218508 | AC46: =(('Results Scenario B'!D23*Assumptions!$B$7*Assumptions!$C$7*Assumptions!$B$61*(1-Assumptions!$D$7)+'Results Scenario B'!E23*Assumptions!$B$8*Assumptions!$C$8*Assumptions!$B$61*(1-Assumptions!$D$8))*0.6)/('Results Scenario B'!C23*Assumptions!$B$6*Assumptions!$C$6*Assumptions!$B$61+'Results Scenario B'!D23*Assumptions!$B$7*Assumptions!$C$7*Assumptions!$B$61+'Results Scenario B'!E23*Assumptions!$B$8*Assumptions!$C$8*Assumptions!$B$61+'Results Scenario B'!F23*Assumptions!$B$9*Assumptions!$C$9*Assumptions!$B$61+'Results Scenario B'!G23*Assumptions!$B$10*Assumptions!$C$10*Assumptions!$B$61+'Results Scenario B'!H23*Assumptions!$B$11*Assumptions!$C$11*Assumptions!$B$61) -> 0.23352174 | AD46: =(('Results Scenario B'!D24*Assumptions!$B$7*Assumptions!$C$7*Assumptions!$B$61*(1-Assumptions!$D$7)+'Results Scenario B'!E24*Assumptions!$B$8*Assumptions!$C$8*Assumptions!$B$61*(1-Assumptions!$D$8))*0.6)/('Results Scenario B'!C24*Assumptions!$B$6*Assumptions!$C$6*Assumptions!$B$61+'Results Scenario B'!D24*Assumptions!$B$7*Assumptions!$C$7*Assumptions!$B$61+'Results Scenario B'!E24*Assumptions!$B$8*Assumptions!$C$8*Assumptions!$B$61+'Results Scenario B'!F24*Assumptions!$B$9*Assumptions!$C$9*Assumptions!$B$61+'Results Scenario B'!G24*Assumptions!$B$10*Assumptions!$C$10*Assumptions!$B$61+'Results Scenario B'!H24*Assumptions!$B$11*Assumptions!$C$11*Assumptions!$B$61) -> 0.23448515 | AE46: =(('Results Scenario B'!D25*Assumptions!$B$7*Assumptions!$C$7*Assumptions!$B$61*(1-Assumptions!$D$7)+'Results Scenario B'!E25*Assumptions!$B$8*Assumptions!$C$8*Assumptions!$B$61*(1-Assumptions!$D$8))*0.6)/('Results Scenario B'!C25*Assumptions!$B$6*Assumptions!$C$6*Assumptions!$B$61+'Results Scenario B'!D25*Assumptions!$B$7*Assumptions!$C$7*Assumptions!$B$61+'Results Scenario B'!E25*Assumptions!$B$8*Assumptions!$C$8*Assumptions!$B$61+'Results Scenario B'!F25*Assumptions!$B$9*Assumptions!$C$9*Assumptions!$B$61+'Results Scenario B'!G25*Assumptions!$B$10*Assumptions!$C$10*Assumptions!$B$61+'Results Scenario B'!H25*Assumptions!$B$11*Assumptions!$C$11*Assumptions!$B$61) -> 0.23502657 | AF46: =(('Results Scenario B'!D26*Assumptions!$B$7*Assumptions!$C$7*Assumptions!$B$61*(1-Assumptions!$D$7)+'Results Scenario B'!E26*Assumptions!$B$8*Assumptions!$C$8*Assumptions!$B$61*(1-Assumptions!$D$8))*0.6)/('Results Scenario B'!C26*Assumptions!$B$6*Assumptions!$C$6*Assumptions!$B$61+'Results Scenario B'!D26*Assumptions!$B$7*Assumptions!$C$7*Assumptions!$B$61+'Results Scenario B'!E26*Assumptions!$B$8*Assumptions!$C$8*Assumptions!$B$61+'Results Scenario B'!F26*Assumptions!$B$9*Assumptions!$C$9*Assumptions!$B$61+'Results Scenario B'!G26*Assumptions!$B$10*Assumptions!$C$10*Assumptions!$B$61+'Results Scenario B'!H26*Assumptions!$B$11*Assumptions!$C$11*Assumptions!$B$61) -> 0.23509983 | AG46: =(('Results Scenario B'!D27*Assumptions!$B$7*Assumptions!$C$7*Assumptions!$B$61*(1-Assumptions!$D$7)+'Results Scenario B'!E27*Assumptions!$B$8*Assumptions!$C$8*Assumptions!$B$61*(1-Assumptions!$D$8))*0.6)/('Results Scenario B'!C27*Assumptions!$B$6*Assumptions!$C$6*Assumptions!$B$61+'Results Scenario B'!D27*Assumptions!$B$7*Assumptions!$C$7*Assumptions!$B$61+'Results Scenario B'!E27*Assumptions!$B$8*Assumptions!$C$8*Assumptions!$B$61+'Results Scenario B'!F27*Assumptions!$B$9*Assumptions!$C$9*Assumptions!$B$61+'Results Scenario B'!G27*Assumptions!$B$10*Assumptions!$C$10*Assumptions!$B$61+'Results Scenario B'!H27*Assumptions!$B$11*Assumptions!$C$11*Assumptions!$B$61) -> 0.2346693 | AH46: =(('Results Scenario B'!D28*Assumptions!$B$7*Assumptions!$C$7*Assumptions!$B$61*(1-Assumptions!$D$7)+'Results Scenario B'!E28*Assumptions!$B$8*Assumptions!$C$8*Assumptions!$B$61*(1-Assumptions!$D$8))*0.6)/('Results Scenario B'!C28*Assumptions!$B$6*Assumptions!$C$6*Assumptions!$B$61+'Results Scenario B'!D28*Assumptions!$B$7*Assumptions!$C$7*Assumptions!$B$61+'Results Scenario B'!E28*Assumptions!$B$8*Assumptions!$C$8*Assumptions!$B$61+'Results Scenario B'!F28*Assumptions!$B$9*Assumptions!$C$9*Assumptions!$B$61+'Results Scenario B'!G28*Assumptions!$B$10*Assumptions!$C$10*Assumptions!$B$61+'Results Scenario B'!H28*Assumptions!$B$11*Assumptions!$C$11*Assumptions!$B$61) -> 0.23371888 | AI46: =(('Results Scenario B'!D29*Assumptions!$B$7*Assumptions!$C$7*Assumptions!$B$61*(1-Assumptions!$D$7)+'Results Scenario B'!E29*Assumptions!$B$8*Assumptions!$C$8*Assumptions!$B$61*(1-Assumptions!$D$8))*0.6)/('Results Scenario B'!C29*Assumptions!$B$6*Assumptions!$C$6*Assumptions!$B$61+'Results Scenario B'!D29*Assumptions!$B$7*Assumptions!$C$7*Assumptions!$B$61+'Results Scenario B'!E29*Assumptions!$B$8*Assumptions!$C$8*Assumptions!$B$61+'Results Scenario B'!F29*Assumptions!$B$9*Assumptions!$C$9*Assumptions!$B$61+'Results Scenario B'!G29*Assumptions!$B$10*Assumptions!$C$10*Assumptions!$B$61+'Results Scenario B'!H29*Assumptions!$B$11*Assumptions!$C$11*Assumptions!$B$61) -> 0.23225961 | AJ46: =(('Results Scenario B'!D30*Assumptions!$B$7*Assumptions!$C$7*Assumptions!$B$61*(1-Assumptions!$D$7)+'Results Scenario B'!E30*Assumptions!$B$8*Assumptions!$C$8*Assumptions!$B$61*(1-Assumptions!$D$8))*0.6)/('Results Scenario B'!C30*Assumptions!$B$6*Assumptions!$C$6*Assumptions!$B$61+'Results Scenario B'!D30*Assumptions!$B$7*Assumptions!$C$7*Assumptions!$B$61+'Results Scenario B'!E30*Assumptions!$B$8*Assumptions!$C$8*Assumptions!$B$61+'Results Scenario B'!F30*Assumptions!$B$9*Assumptions!$C$9*Assumptions!$B$61+'Results Scenario B'!G30*Assumptions!$B$10*Assumptions!$C$10*Assumptions!$B$61+'Results Scenario B'!H30*Assumptions!$B$11*Assumptions!$C$11*Assumptions!$B$61) -> 0.23033333 | AK46: =(('Results Scenario B'!D31*Assumptions!$B$7*Assumptions!$C$7*Assumptions!$B$61*(1-Assumptions!$D$7)+'Results Scenario B'!E31*Assumptions!$B$8*Assumptions!$C$8*Assumptions!$B$61*(1-Assumptions!$D$8))*0.6)/('Results Scenario B'!C31*Assumptions!$B$6*Assumptions!$C$6*Assumptions!$B$61+'Results Scenario B'!D31*Assumptions!$B$7*Assumptions!$C$7*Assumptions!$B$61+'Results Scenario B'!E31*Assumptions!$B$8*Assumptions!$C$8*Assumptions!$B$61+'Results Scenario B'!F31*Assumptions!$B$9*Assumptions!$C$9*Assumptions!$B$61+'Results Scenario B'!G31*Assumptions!$B$10*Assumptions!$C$10*Assumptions!$B$61+'Results Scenario B'!H31*Assumptions!$B$11*Assumptions!$C$11*Assumptions!$B$61) -> 0.22801113 | AL46: =(('Results Scenario B'!D32*Assumptions!$B$7*Assumptions!$C$7*Assumptions!$B$61*(1-Assumptions!$D$7)+'Results Scenario B'!E32*Assumptions!$B$8*Assumptions!$C$8*Assumptions!$B$61*(1-Assumptions!$D$8))*0.6)/('Results Scenario B'!C32*Assumptions!$B$6*Assumptions!$C$6*Assumptions!$B$61+'Results Scenario B'!D32*Assumptions!$B$7*Assumptions!$C$7*Assumptions!$B$61+'Results Scenario B'!E32*Assumptions!$B$8*Assumptions!$C$8*Assumptions!$B$61+'Results Scenario B'!F32*Assumptions!$B$9*Assumptions!$C$9*Assumptions!$B$61+'Results Scenario B'!G32*Assumptions!$B$10*Assumptions!$C$10*Assumptions!$B$61+'Results Scenario B'!H32*Assumptions!$B$11*Assumptions!$C$11*Assumptions!$B$61) -> 0.22538669 | AM46: =(('Results Scenario B'!D33*Assumptions!$B$7*Assumptions!$C$7*Assumptions!$B$61*(1-Assumptions!$D$7)+'Results Scenario B'!E33*Assumptions!$B$8*Assumptions!$C$8*Assumptions!$B$61*(1-Assumptions!$D$8))*0.6)/('Results Scenario B'!C33*Assumptions!$B$6*Assumptions!$C$6*Assumptions!$B$61+'Results Scenario B'!D33*Assumptions!$B$7*Assumptions!$C$7*Assumptions!$B$61+'Results Scenario B'!E33*Assumptions!$B$8*Assumptions!$C$8*Assumptions!$B$61+'Results Scenario B'!F33*Assumptions!$B$9*Assumptions!$C$9*Assumptions!$B$61+'Results Scenario B'!G33*Assumptions!$B$10*Assumptions!$C$10*Assumptions!$B$61+'Results Scenario B'!H33*Assumptions!$B$11*Assumptions!$C$11*Assumptions!$B$61) -> 0.22256623 | AN46: =(('Results Scenario B'!D34*Assumptions!$B$7*Assumptions!$C$7*Assumptions!$B$61*(1-Assumptions!$D$7)+'Results Scenario B'!E34*Assumptions!$B$8*Assumptions!$C$8*Assumptions!$B$61*(1-Assumptions!$D$8))*0.6)/('Results Scenario B'!C34*Assumptions!$B$6*Assumptions!$C$6*Assumptions!$B$61+'Results Scenario B'!D34*Assumptions!$B$7*Assumptions!$C$7*Assumptions!$B$61+'Results Scenario B'!E34*Assumptions!$B$8*Assumptions!$C$8*Assumptions!$B$61+'Results Scenario B'!F34*Assumptions!$B$9*Assumptions!$C$9*Assumptions!$B$61+'Results Scenario B'!G34*Assumptions!$B$10*Assumptions!$C$10*Assumptions!$B$61+'Results Scenario B'!H34*Assumptions!$B$11*Assumptions!$C$11*Assumptions!$B$61) -> 0.21965747 | AO46: =(('Results Scenario B'!D35*Assumptions!$B$7*Assumptions!$C$7*Assumptions!$B$61*(1-Assumptions!$D$7)+'Results Scenario B'!E35*Assumptions!$B$8*Assumptions!$C$8*Assumptions!$B$61*(1-Assumptions!$D$8))*0.6)/('Results Scenario B'!C35*Assumptions!$B$6*Assumptions!$C$6*Assumptions!$B$61+'Results Scenario B'!D35*Assumptions!$B$7*Assumptions!$C$7*Assumptions!$B$61+'Results Scenario B'!E35*Assumptions!$B$8*Assumptions!$C$8*Assumptions!$B$61+'Results Scenario B'!F35*Assumptions!$B$9*Assumptions!$C$9*Assumptions!$B$61+'Results Scenario B'!G35*Assumptions!$B$10*Assumptions!$C$10*Assumptions!$B$61+'Results Scenario B'!H35*Assumptions!$B$11*Assumptions!$C$11*Assumptions!$B$61) -> 0.21675966 | AP46: =(('Results Scenario B'!D36*Assumptions!$B$7*Assumptions!$C$7*Assumptions!$B$61*(1-Assumptions!$D$7)+'Results Scenario B'!E36*Assumptions!$B$8*Assumptions!$C$8*Assumptions!$B$61*(1-Assumptions!$D$8))*0.6)/('Results Scenario B'!C36*Assumptions!$B$6*Assumptions!$C$6*Assumptions!$B$61+'Results Scenario B'!D36*Assumptions!$B$7*Assumptions!$C$7*Assumptions!$B$61+'Results Scenario B'!E36*Assumptions!$B$8*Assumptions!$C$8*Assumptions!$B$61+'Results Scenario B'!F36*Assumptions!$B$9*Assumptions!$C$9*Assumptions!$B$61+'Results Scenario B'!G36*Assumptions!$B$10*Assumptions!$C$10*Assumptions!$B$61+'Results Scenario B'!H36*Assumptions!$B$11*Assumptions!$C$11*Assumptions!$B$61) -> 0.2139565 | AQ46: =(('Results Scenario B'!D37*Assumptions!$B$7*Assumptions!$C$7*Assumptions!$B$61*(1-Assumptions!$D$7)+'Results Scenario B'!E37*Assumptions!$B$8*Assumptions!$C$8*Assumptions!$B$61*(1-Assumptions!$D$8))*0.6)/('Results Scenario B'!C37*Assumptions!$B$6*Assumptions!$C$6*Assumptions!$B$61+'Results Scenario B'!D37*Assumptions!$B$7*Assumptions!$C$7*Assumptions!$B$61+'Results Scenario B'!E37*Assumptions!$B$8*Assumptions!$C$8*Assumptions!$B$61+'Results Scenario B'!F37*Assumptions!$B$9*Assumptions!$C$9*Assumptions!$B$61+'Results Scenario B'!G37*Assumptions!$B$10*Assumptions!$C$10*Assumptions!$B$61+'Results Scenario B'!H37*Assumptions!$B$11*Assumptions!$C$11*Assumptions!$B$61) -> 0.21131221 | AR46: =(('Results Scenario B'!D38*Assumptions!$B$7*Assumptions!$C$7*Assumptions!$B$61*(1-Assumptions!$D$7)+'Results Scenario B'!E38*Assumptions!$B$8*Assumptions!$C$8*Assumptions!$B$61*(1-Assumptions!$D$8))*0.6)/('Results Scenario B'!C38*Assumptions!$B$6*Assumptions!$C$6*Assumptions!$B$61+'Results Scenario B'!D38*Assumptions!$B$7*Assumptions!$C$7*Assumptions!$B$61+'Results Scenario B'!E38*Assumptions!$B$8*Assumptions!$C$8*Assumptions!$B$61+'Results Scenario B'!F38*Assumptions!$B$9*Assumptions!$C$9*Assumptions!$B$61+'Results Scenario B'!G38*Assumptions!$B$10*Assumptions!$C$10*Assumptions!$B$61+'Results Scenario B'!H38*Assumptions!$B$11*Assumptions!$C$11*Assumptions!$B$61) -> 0.20887077 | AS46: =(('Results Scenario B'!D39*Assumptions!$B$7*Assumptions!$C$7*Assumptions!$B$61*(1-Assumptions!$D$7)+'Results Scenario B'!E39*Assumptions!$B$8*Assumptions!$C$8*Assumptions!$B$61*(1-Assumptions!$D$8))*0.6)/('Results Scenario B'!C39*Assumptions!$B$6*Assumptions!$C$6*Assumptions!$B$61+'Results Scenario B'!D39*Assumptions!$B$7*Assumptions!$C$7*Assumptions!$B$61+'Results Scenario B'!E39*Assumptions!$B$8*Assumptions!$C$8*Assumptions!$B$61+'Results Scenario B'!F39*Assumptions!$B$9*Assumptions!$C$9*Assumptions!$B$61+'Results Scenario B'!G39*Assumptions!$B$10*Assumptions!$C$10*Assumptions!$B$61+'Results Scenario B'!H39*Assumptions!$B$11*Assumptions!$C$11*Assumptions!$B$61) -> 0.20665751
I47: Public DC fast weight | J47: =(('Results Scenario B'!D4*Assumptions!$B$7*Assumptions!$C$7*Assumptions!$B$61*(1-Assumptions!$D$7)+'Results Scenario B'!E4*Assumptions!$B$8*Assumptions!$C$8*Assumptions!$B$61*(1-Assumptions!$D$8))*0.4)/('Results Scenario B'!C4*Assumptions!$B$6*Assumptions!$C$6*Assumptions!$B$61+'Results Scenario B'!D4*Assumptions!$B$7*Assumptions!$C$7*Assumptions!$B$61+'Results Scenario B'!E4*Assumptions!$B$8*Assumptions!$C$8*Assumptions!$B$61+'Results Scenario B'!F4*Assumptions!$B$9*Assumptions!$C$9*Assumptions!$B$61+'Results Scenario B'!G4*Assumptions!$B$10*Assumptions!$C$10*Assumptions!$B$61+'Results Scenario B'!H4*Assumptions!$B$11*Assumptions!$C$11*Assumptions!$B$61) -> 0.11810363 | K47: =(('Results Scenario B'!D5*Assumptions!$B$7*Assumptions!$C$7*Assumptions!$B$61*(1-Assumptions!$D$7)+'Results Scenario B'!E5*Assumptions!$B$8*Assumptions!$C$8*Assumptions!$B$61*(1-Assumptions!$D$8))*0.4)/('Results Scenario B'!C5*Assumptions!$B$6*Assumptions!$C$6*Assumptions!$B$61+'Results Scenario B'!D5*Assumptions!$B$7*Assumptions!$C$7*Assumptions!$B$61+'Results Scenario B'!E5*Assumptions!$B$8*Assumptions!$C$8*Assumptions!$B$61+'Results Scenario B'!F5*Assumptions!$B$9*Assumptions!$C$9*Assumptions!$B$61+'Results Scenario B'!G5*Assumptions!$B$10*Assumptions!$C$10*Assumptions!$B$61+'Results Scenario B'!H5*Assumptions!$B$11*Assumptions!$C$11*Assumptions!$B$61) -> 0.12060014 | L47: =(('Results Scenario B'!D6*Assumptions!$B$7*Assumptions!$C$7*Assumptions!$B$61*(1-Assumptions!$D$7)+'Results Scenario B'!E6*Assumptions!$B$8*Assumptions!$C$8*Assumptions!$B$61*(1-Assumptions!$D$8))*0.4)/('Results Scenario B'!C6*Assumptions!$B$6*Assumptions!$C$6*Assumptions!$B$61+'Results Scenario B'!D6*Assumptions!$B$7*Assumptions!$C$7*Assumptions!$B$61+'Results Scenario B'!E6*Assumptions!$B$8*Assumptions!$C$8*Assumptions!$B$61+'Results Scenario B'!F6*Assumptions!$B$9*Assumptions!$C$9*Assumptions!$B$61+'Results Scenario B'!G6*Assumptions!$B$10*Assumptions!$C$10*Assumptions!$B$61+'Results Scenario B'!H6*Assumptions!$B$11*Assumptions!$C$11*Assumptions!$B$61) -> 0.12308055 | M47: =(('Results Scenario B'!D7*Assumptions!$B$7*Assumptions!$C$7*Assumptions!$B$61*(1-Assumptions!$D$7)+'Results Scenario B'!E7*Assumptions!$B$8*Assumptions!$C$8*Assumptions!$B$61*(1-Assumptions!$D$8))*0.4)/('Results Scenario B'!C7*Assumptions!$B$6*Assumptions!$C$6*Assumptions!$B$61+'Results Scenario B'!D7*Assumptions!$B$7*Assumptions!$C$7*Assumptions!$B$61+'Results Scenario B'!E7*Assumptions!$B$8*Assumptions!$C$8*Assumptions!$B$61+'Results Scenario B'!F7*Assumptions!$B$9*Assumptions!$C$9*Assumptions!$B$61+'Results Scenario B'!G7*Assumptions!$B$10*Assumptions!$C$10*Assumptions!$B$61+'Results Scenario B'!H7*Assumptions!$B$11*Assumptions!$C$11*Assumptions!$B$61) -> 0.12553991 | N47: =(('Results Scenario B'!D8*Assumptions!$B$7*Assumptions!$C$7*Assumptions!$B$61*(1-Assumptions!$D$7)+'Results Scenario B'!E8*Assumptions!$B$8*Assumptions!$C$8*Assumptions!$B$61*(1-Assumptions!$D$8))*0.4)/('Results Scenario B'!C8*Assumptions!$B$6*Assumptions!$C$6*Assumptions!$B$61+'Results Scenario B'!D8*Assumptions!$B$7*Assumptions!$C$7*Assumptions!$B$61+'Results Scenario B'!E8*Assumptions!$B$8*Assumptions!$C$8*Assumptions!$B$61+'Results Scenario B'!F8*Assumptions!$B$9*Assumptions!$C$9*Assumptions!$B$61+'Results Scenario B'!G8*Assumptions!$B$10*Assumptions!$C$10*Assumptions!$B$61+'Results Scenario B'!H8*Assumptions!$B$11*Assumptions!$C$11*Assumptions!$B$61) -> 0.12797293 | O47: =(('Results Scenario B'!D9*Assumptions!$B$7*Assumptions!$C$7*Assumptions!$B$61*(1-Assumptions!$D$7)+'Results Scenario B'!E9*Assumptions!$B$8*Assumptions!$C$8*Assumptions!$B$61*(1-Assumptions!$D$8))*0.4)/('Results Scenario B'!C9*Assumptions!$B$6*Assumptions!$C$6*Assumptions!$B$61+'Results Scenario B'!D9*Assumptions!$B$7*Assumptions!$C$7*Assumptions!$B$61+'Results Scenario B'!E9*Assumptions!$B$8*Assumptions!$C$8*Assumptions!$B$61+'Results Scenario B'!F9*Assumptions!$B$9*Assumptions!$C$9*Assumptions!$B$61+'Results Scenario B'!G9*Assumptions!$B$10*Assumptions!$C$10*Assumptions!$B$61+'Results Scenario B'!H9*Assumptions!$B$11*Assumptions!$C$11*Assumptions!$B$61) -> 0.1303739 | P47: =(('Results Scenario B'!D10*Assumptions!$B$7*Assumptions!$C$7*Assumptions!$B$61*(1-Assumptions!$D$7)+'Results Scenario B'!E10*Assumptions!$B$8*Assumptions!$C$8*Assumptions!$B$61*(1-Assumptions!$D$8))*0.4)/('Results Scenario B'!C10*Assumptions!$B$6*Assumptions!$C$6*Assumptions!$B$61+'Results Scenario B'!D10*Assumptions!$B$7*Assumptions!$C$7*Assumptions!$B$61+'Results Scenario B'!E10*Assumptions!$B$8*Assumptions!$C$8*Assumptions!$B$61+'Results Scenario B'!F10*Assumptions!$B$9*Assumptions!$C$9*Assumptions!$B$61+'Results Scenario B'!G10*Assumptions!$B$10*Assumptions!$C$10*Assumptions!$B$61+'Results Scenario B'!H10*Assumptions!$B$11*Assumptions!$C$11*Assumptions!$B$61) -> 0.13273667 | Q47: =(('Results Scenario B'!D11*Assumptions!$B$7*Assumptions!$C$7*Assumptions!$B$61*(1-Assumptions!$D$7)+'Results Scenario B'!E11*Assumptions!$B$8*Assumptions!$C$8*Assumptions!$B$61*(1-Assumptions!$D$8))*0.4)/('Results Scenario B'!C11*Assumptions!$B$6*Assumptions!$C$6*Assumptions!$B$61+'Results Scenario B'!D11*Assumptions!$B$7*Assumptions!$C$7*Assumptions!$B$61+'Results Scenario B'!E11*Assumptions!$B$8*Assumptions!$C$8*Assumptions!$B$61+'Results Scenario B'!F11*Assumptions!$B$9*Assumptions!$C$9*Assumptions!$B$61+'Results Scenario B'!G11*Assumptions!$B$10*Assumptions!$C$10*Assumptions!$B$61+'Results Scenario B'!H11*Assumptions!$B$11*Assumptions!$C$11*Assumptions!$B$61) -> 0.13505451 | R47: =(('Results Scenario B'!D12*Assumptions!$B$7*Assumptions!$C$7*Assumptions!$B$61*(1-Assumptions!$D$7)+'Results Scenario B'!E12*Assumptions!$B$8*Assumptions!$C$8*Assumptions!$B$61*(1-Assumptions!$D$8))*0.4)/('Results Scenario B'!C12*Assumptions!$B$6*Assumptions!$C$6*Assumptions!$B$61+'Results Scenario B'!D12*Assumptions!$B$7*Assumptions!$C$7*Assumptions!$B$61+'Results Scenario B'!E12*Assumptions!$B$8*Assumptions!$C$8*Assumptions!$B$61+'Results Scenario B'!F12*Assumptions!$B$9*Assumptions!$C$9*Assumptions!$B$61+'Results Scenario B'!G12*Assumptions!$B$10*Assumptions!$C$10*Assumptions!$B$61+'Results Scenario B'!H12*Assumptions!$B$11*Assumptions!$C$11*Assumptions!$B$61) -> 0.13732003 | S47: =(('Results Scenario B'!D13*Assumptions!$B$7*Assumptions!$C$7*Assumptions!$B$61*(1-Assumptions!$D$7)+'Results Scenario B'!E13*Assumptions!$B$8*Assumptions!$C$8*Assumptions!$B$61*(1-Assumptions!$D$8))*0.4)/('Results Scenario B'!C13*Assumptions!$B$6*Assumptions!$C$6*Assumptions!$B$61+'Results Scenario B'!D13*Assumptions!$B$7*Assumptions!$C$7*Assumptions!$B$61+'Results Scenario B'!E13*Assumptions!$B$8*Assumptions!$C$8*Assumptions!$B$61+'Results Scenario B'!F13*Assumptions!$B$9*Assumptions!$C$9*Assumptions!$B$61+'Results Scenario B'!G13*Assumptions!$B$10*Assumptions!$C$10*Assumptions!$B$61+'Results Scenario B'!H13*Assumptions!$B$11*Assumptions!$C$11*Assumptions!$B$61) -> 0.13952512 | T47: =(('Results Scenario B'!D14*Assumptions!$B$7*Assumptions!$C$7*Assumptions!$B$61*(1-Assumptions!$D$7)+'Results Scenario B'!E14*Assumptions!$B$8*Assumptions!$C$8*Assumptions!$B$61*(1-Assumptions!$D$8))*0.4)/('Results Scenario B'!C14*Assumptions!$B$6*Assumptions!$C$6*Assumptions!$B$61+'Results Scenario B'!D14*Assumptions!$B$7*Assumptions!$C$7*Assumptions!$B$61+'Results Scenario B'!E14*Assumptions!$B$8*Assumptions!$C$8*Assumptions!$B$61+'Results Scenario B'!F14*Assumptions!$B$9*Assumptions!$C$9*Assumptions!$B$61+'Results Scenario B'!G14*Assumptions!$B$10*Assumptions!$C$10*Assumptions!$B$61+'Results Scenario B'!H14*Assumptions!$B$11*Assumptions!$C$11*Assumptions!$B$61) -> 0.14166082 | U47: =(('Results Scenario B'!D15*Assumptions!$B$7*Assumptions!$C$7*Assumptions!$B$61*(1-Assumptions!$D$7)+'Results Scenario B'!E15*Assumptions!$B$8*Assumptions!$C$8*Assumptions!$B$61*(1-Assumptions!$D$8))*0.4)/('Results Scenario B'!C15*Assumptions!$B$6*Assumptions!$C$6*Assumptions!$B$61+'Results Scenario B'!D15*Assumptions!$B$7*Assumptions!$C$7*Assumptions!$B$61+'Results Scenario B'!E15*Assumptions!$B$8*Assumptions!$C$8*Assumptions!$B$61+'Results Scenario B'!F15*Assumptions!$B$9*Assumptions!$C$9*Assumptions!$B$61+'Results Scenario B'!G15*Assumptions!$B$10*Assumptions!$C$10*Assumptions!$B$61+'Results Scenario B'!H15*Assumptions!$B$11*Assumptions!$C$11*Assumptions!$B$61) -> 0.1437172 | V47: =(('Results Scenario B'!D16*Assumptions!$B$7*Assumptions!$C$7*Assumptions!$B$61*(1-Assumptions!$D$7)+'Results Scenario B'!E16*Assumptions!$B$8*Assumptions!$C$8*Assumptions!$B$61*(1-Assumptions!$D$8))*0.4)/('Results Scenario B'!C16*Assumptions!$B$6*Assumptions!$C$6*Assumptions!$B$61+'Results Scenario B'!D16*Assumptions!$B$7*Assumptions!$C$7*Assumptions!$B$61+'Results Scenario B'!E16*Assumptions!$B$8*Assumptions!$C$8*Assumptions!$B$61+'Results Scenario B'!F16*Assumptions!$B$9*Assumptions!$C$9*Assumptions!$B$61+'Results Scenario B'!G16*Assumptions!$B$10*Assumptions!$C$10*Assumptions!$B$61+'Results Scenario B'!H16*Assumptions!$B$11*Assumptions!$C$11*Assumptions!$B$61) -> 0.14568331 | W47: =(('Results Scenario B'!D17*Assumptions!$B$7*Assumptions!$C$7*Assumptions!$B$61*(1-Assumptions!$D$7)+'Results Scenario B'!E17*Assumptions!$B$8*Assumptions!$C$8*Assumptions!$B$61*(1-Assumptions!$D$8))*0.4)/('Results Scenario B'!C17*Assumptions!$B$6*Assumptions!$C$6*Assumptions!$B$61+'Results Scenario B'!D17*Assumptions!$B$7*Assumptions!$C$7*Assumptions!$B$61+'Results Scenario B'!E17*Assumptions!$B$8*Assumptions!$C$8*Assumptions!$B$61+'Results Scenario B'!F17*Assumptions!$B$9*Assumptions!$C$9*Assumptions!$B$61+'Results Scenario B'!G17*Assumptions!$B$10*Assumptions!$C$10*Assumptions!$B$61+'Results Scenario B'!H17*Assumptions!$B$11*Assumptions!$C$11*Assumptions!$B$61) -> 0.147547 | X47: =(('Results Scenario B'!D18*Assumptions!$B$7*Assumptions!$C$7*Assumptions!$B$61*(1-Assumptions!$D$7)+'Results Scenario B'!E18*Assumptions!$B$8*Assumptions!$C$8*Assumptions!$B$61*(1-Assumptions!$D$8))*0.4)/('Results Scenario B'!C18*Assumptions!$B$6*Assumptions!$C$6*Assumptions!$B$61+'Results Scenario B'!D18*Assumptions!$B$7*Assumptions!$C$7*Assumptions!$B$61+'Results Scenario B'!E18*Assumptions!$B$8*Assumptions!$C$8*Assumptions!$B$61+'Results Scenario B'!F18*Assumptions!$B$9*Assumptions!$C$9*Assumptions!$B$61+'Results Scenario B'!G18*Assumptions!$B$10*Assumptions!$C$10*Assumptions!$B$61+'Results Scenario B'!H18*Assumptions!$B$11*Assumptions!$C$11*Assumptions!$B$61) -> 0.14929479 | Y47: =(('Results Scenario B'!D19*Assumptions!$B$7*Assumptions!$C$7*Assumptions!$B$61*(1-Assumptions!$D$7)+'Results Scenario B'!E19*Assumptions!$B$8*Assumptions!$C$8*Assumptions!$B$61*(1-Assumptions!$D$8))*0.4)/('Results Scenario B'!C19*Assumptions!$B$6*Assumptions!$C$6*Assumptions!$B$61+'Results Scenario B'!D19*Assumptions!$B$7*Assumptions!$C$7*Assumptions!$B$61+'Results Scenario B'!E19*Assumptions!$B$8*Assumptions!$C$8*Assumptions!$B$61+'Results Scenario B'!F19*Assumptions!$B$9*Assumptions!$C$9*Assumptions!$B$61+'Results Scenario B'!G19*Assumptions!$B$10*Assumptions!$C$10*Assumptions!$B$61+'Results Scenario B'!H19*Assumptions!$B$11*Assumptions!$C$11*Assumptions!$B$61) -> 0.15091156 | Z47: =(('Results Scenario B'!D20*Assumptions!$B$7*Assumptions!$C$7*Assumptions!$B$61*(1-Assumptions!$D$7)+'Results Scenario B'!E20*Assumptions!$B$8*Assumptions!$C$8*Assumptions!$B$61*(1-Assumptions!$D$8))*0.4)/('Results Scenario B'!C20*Assumptions!$B$6*Assumptions!$C$6*Assumptions!$B$61+'Results Scenario B'!D20*Assumptions!$B$7*Assumptions!$C$7*Assumptions!$B$61+'Results Scenario B'!E20*Assumptions!$B$8*Assumptions!$C$8*Assumptions!$B$61+'Results Scenario B'!F20*Assumptions!$B$9*Assumptions!$C$9*Assumptions!$B$61+'Results Scenario B'!G20*Assumptions!$B$10*Assumptions!$C$10*Assumptions!$B$61+'Results Scenario B'!H20*Assumptions!$B$11*Assumptions!$C$11*Assumptions!$B$61) -> 0.15238014 | AA47: =(('Results Scenario B'!D21*Assumptions!$B$7*Assumptions!$C$7*Assumptions!$B$61*(1-Assumptions!$D$7)+'Results Scenario B'!E21*Assumptions!$B$8*Assumptions!$C$8*Assumptions!$B$61*(1-Assumptions!$D$8))*0.4)/('Results Scenario B'!C21*Assumptions!$B$6*Assumptions!$C$6*Assumptions!$B$61+'Results Scenario B'!D21*Assumptions!$B$7*Assumptions!$C$7*Assumptions!$B$61+'Results Scenario B'!E21*Assumptions!$B$8*Assumptions!$C$8*Assumptions!$B$61+'Results Scenario B'!F21*Assumptions!$B$9*Assumptions!$C$9*Assumptions!$B$61+'Results Scenario B'!G21*Assumptions!$B$10*Assumptions!$C$10*Assumptions!$B$61+'Results Scenario B'!H21*Assumptions!$B$11*Assumptions!$C$11*Assumptions!$B$61) -> 0.1536807 | AB47: =(('Results Scenario B'!D22*Assumptions!$B$7*Assumptions!$C$7*Assumptions!$B$61*(1-Assumptions!$D$7)+'Results Scenario B'!E22*Assumptions!$B$8*Assumptions!$C$8*Assumptions!$B$61*(1-Assumptions!$D$8))*0.4)/('Results Scenario B'!C22*Assumptions!$B$6*Assumptions!$C$6*Assumptions!$B$61+'Results Scenario B'!D22*Assumptions!$B$7*Assumptions!$C$7*Assumptions!$B$61+'Results Scenario B'!E22*Assumptions!$B$8*Assumptions!$C$8*Assumptions!$B$61+'Results Scenario B'!F22*Assumptions!$B$9*Assumptions!$C$9*Assumptions!$B$61+'Results Scenario B'!G22*Assumptions!$B$10*Assumptions!$C$10*Assumptions!$B$61+'Results Scenario B'!H22*Assumptions!$B$11*Assumptions!$C$11*Assumptions!$B$61) -> 0.15479005 | AC47: =(('Results Scenario B'!D23*Assumptions!$B$7*Assumptions!$C$7*Assumptions!$B$61*(1-Assumptions!$D$7)+'Results Scenario B'!E23*Assumptions!$B$8*Assumptions!$C$8*Assumptions!$B$61*(1-Assumptions!$D$8))*0.4)/('Results Scenario B'!C23*Assumptions!$B$6*Assumptions!$C$6*Assumptions!$B$61+'Results Scenario B'!D23*Assumptions!$B$7*Assumptions!$C$7*Assumptions!$B$61+'Results Scenario B'!E23*Assumptions!$B$8*Assumptions!$C$8*Assumptions!$B$61+'Results Scenario B'!F23*Assumptions!$B$9*Assumptions!$C$9*Assumptions!$B$61+'Results Scenario B'!G23*Assumptions!$B$10*Assumptions!$C$10*Assumptions!$B$61+'Results Scenario B'!H23*Assumptions!$B$11*Assumptions!$C$11*Assumptions!$B$61) -> 0.15568116 | AD47: =(('Results Scenario B'!D24*Assumptions!$B$7*Assumptions!$C$7*Assumptions!$B$61*(1-Assumptions!$D$7)+'Results Scenario B'!E24*Assumptions!$B$8*Assumptions!$C$8*Assumptions!$B$61*(1-Assumptions!$D$8))*0.4)/('Results Scenario B'!C24*Assumptions!$B$6*Assumptions!$C$6*Assumptions!$B$61+'Results Scenario B'!D24*Assumptions!$B$7*Assumptions!$C$7*Assumptions!$B$61+'Results Scenario B'!E24*Assumptions!$B$8*Assumptions!$C$8*Assumptions!$B$61+'Results Scenario B'!F24*Assumptions!$B$9*Assumptions!$C$9*Assumptions!$B$61+'Results Scenario B'!G24*Assumptions!$B$10*Assumptions!$C$10*Assumptions!$B$61+'Results Scenario B'!H24*Assumptions!$B$11*Assumptions!$C$11*Assumptions!$B$61) -> 0.15632343 | AE47: =(('Results Scenario B'!D25*Assumptions!$B$7*Assumptions!$C$7*Assumptions!$B$61*(1-Assumptions!$D$7)+'Results Scenario B'!E25*Assumptions!$B$8*Assumptions!$C$8*Assumptions!$B$61*(1-Assumptions!$D$8))*0.4)/('Results Scenario B'!C25*Assumptions!$B$6*Assumptions!$C$6*Assumptions!$B$61+'Results Scenario B'!D25*Assumptions!$B$7*Assumptions!$C$7*Assumptions!$B$61+'Results Scenario B'!E25*Assumptions!$B$8*Assumptions!$C$8*Assumptions!$B$61+'Results Scenario B'!F25*Assumptions!$B$9*Assumptions!$C$9*Assumptions!$B$61+'Results Scenario B'!G25*Assumptions!$B$10*Assumptions!$C$10*Assumptions!$B$61+'Results Scenario B'!H25*Assumptions!$B$11*Assumptions!$C$11*Assumptions!$B$61) -> 0.15668438 | AF47: =(('Results Scenario B'!D26*Assumptions!$B$7*Assumptions!$C$7*Assumptions!$B$61*(1-Assumptions!$D$7)+'Results Scenario B'!E26*Assumptions!$B$8*Assumptions!$C$8*Assumptions!$B$61*(1-Assumptions!$D$8))*0.4)/('Results Scenario B'!C26*Assumptions!$B$6*Assumptions!$C$6*Assumptions!$B$61+'Results Scenario B'!D26*Assumptions!$B$7*Assumptions!$C$7*Assumptions!$B$61+'Results Scenario B'!E26*Assumptions!$B$8*Assumptions!$C$8*Assumptions!$B$61+'Results Scenario B'!F26*Assumptions!$B$9*Assumptions!$C$9*Assumptions!$B$61+'Results Scenario B'!G26*Assumptions!$B$10*Assumptions!$C$10*Assumptions!$B$61+'Results Scenario B'!H26*Assumptions!$B$11*Assumptions!$C$11*Assumptions!$B$61) -> 0.15673322 | AG47: =(('Results Scenario B'!D27*Assumptions!$B$7*Assumptions!$C$7*Assumptions!$B$61*(1-Assumptions!$D$7)+'Results Scenario B'!E27*Assumptions!$B$8*Assumptions!$C$8*Assumptions!$B$61*(1-Assumptions!$D$8))*0.4)/('Results Scenario B'!C27*Assumptions!$B$6*Assumptions!$C$6*Assumptions!$B$61+'Results Scenario B'!D27*Assumptions!$B$7*Assumptions!$C$7*Assumptions!$B$61+'Results Scenario B'!E27*Assumptions!$B$8*Assumptions!$C$8*Assumptions!$B$61+'Results Scenario B'!F27*Assumptions!$B$9*Assumptions!$C$9*Assumptions!$B$61+'Results Scenario B'!G27*Assumptions!$B$10*Assumptions!$C$10*Assumptions!$B$61+'Results Scenario B'!H27*Assumptions!$B$11*Assumptions!$C$11*Assumptions!$B$61) -> 0.1564462 | AH47: =(('Results Scenario B'!D28*Assumptions!$B$7*Assumptions!$C$7*Assumptions!$B$61*(1-Assumptions!$D$7)+'Results Scenario B'!E28*Assumptions!$B$8*Assumptions!$C$8*Assumptions!$B$61*(1-Assumptions!$D$8))*0.4)/('Results Scenario B'!C28*Assumptions!$B$6*Assumptions!$C$6*Assumptions!$B$61+'Results Scenario B'!D28*Assumptions!$B$7*Assumptions!$C$7*Assumptions!$B$61+'Results Scenario B'!E28*Assumptions!$B$8*Assumptions!$C$8*Assumptions!$B$61+'Results Scenario B'!F28*Assumptions!$B$9*Assumptions!$C$9*Assumptions!$B$61+'Results Scenario B'!G28*Assumptions!$B$10*Assumptions!$C$10*Assumptions!$B$61+'Results Scenario B'!H28*Assumptions!$B$11*Assumptions!$C$11*Assumptions!$B$61) -> 0.15581259 | AI47: =(('Results Scenario B'!D29*Assumptions!$B$7*Assumptions!$C$7*Assumptions!$B$61*(1-Assumptions!$D$7)+'Results Scenario B'!E29*Assumptions!$B$8*Assumptions!$C$8*Assumptions!$B$61*(1-Assumptions!$D$8))*0.4)/('Results Scenario B'!C29*Assumptions!$B$6*Assumptions!$C$6*Assumptions!$B$61+'Results Scenario B'!D29*Assumptions!$B$7*Assumptions!$C$7*Assumptions!$B$61+'Results Scenario B'!E29*Assumptions!$B$8*Assumptions!$C$8*Assumptions!$B$61+'Results Scenario B'!F29*Assumptions!$B$9*Assumptions!$C$9*Assumptions!$B$61+'Results Scenario B'!G29*Assumptions!$B$10*Assumptions!$C$10*Assumptions!$B$61+'Results Scenario B'!H29*Assumptions!$B$11*Assumptions!$C$11*Assumptions!$B$61) -> 0.15483974 | AJ47: =(('Results Scenario B'!D30*Assumptions!$B$7*Assumptions!$C$7*Assumptions!$B$61*(1-Assumptions!$D$7)+'Results Scenario B'!E30*Assumptions!$B$8*Assumptions!$C$8*Assumptions!$B$61*(1-Assumptions!$D$8))*0.4)/('Results Scenario B'!C30*Assumptions!$B$6*Assumptions!$C$6*Assumptions!$B$61+'Results Scenario B'!D30*Assumptions!$B$7*Assumptions!$C$7*Assumptions!$B$61+'Results Scenario B'!E30*Assumptions!$B$8*Assumptions!$C$8*Assumptions!$B$61+'Results Scenario B'!F30*Assumptions!$B$9*Assumptions!$C$9*Assumptions!$B$61+'Results Scenario B'!G30*Assumptions!$B$10*Assumptions!$C$10*Assumptions!$B$61+'Results Scenario B'!H30*Assumptions!$B$11*Assumptions!$C$11*Assumptions!$B$61) -> 0.15355555 | AK47: =(('Results Scenario B'!D31*Assumptions!$B$7*Assumptions!$C$7*Assumptions!$B$61*(1-Assumptions!$D$7)+'Results Scenario B'!E31*Assumptions!$B$8*Assumptions!$C$8*Assumptions!$B$61*(1-Assumptions!$D$8))*0.4)/('Results Scenario B'!C31*Assumptions!$B$6*Assumptions!$C$6*Assumptions!$B$61+'Results Scenario B'!D31*Assumptions!$B$7*Assumptions!$C$7*Assumptions!$B$61+'Results Scenario B'!E31*Assumptions!$B$8*Assumptions!$C$8*Assumptions!$B$61+'Results Scenario B'!F31*Assumptions!$B$9*Assumptions!$C$9*Assumptions!$B$61+'Results Scenario B'!G31*Assumptions!$B$10*Assumptions!$C$10*Assumptions!$B$61+'Results Scenario B'!H31*Assumptions!$B$11*Assumptions!$C$11*Assumptions!$B$61) -> 0.15200742 | AL47: =(('Results Scenario B'!D32*Assumptions!$B$7*Assumptions!$C$7*Assumptions!$B$61*(1-Assumptions!$D$7)+'Results Scenario B'!E32*Assumptions!$B$8*Assumptions!$C$8*Assumptions!$B$61*(1-Assumptions!$D$8))*0.4)/('Results Scenario B'!C32*Assumptions!$B$6*Assumptions!$C$6*Assumptions!$B$61+'Results Scenario B'!D32*Assumptions!$B$7*Assumptions!$C$7*Assumptions!$B$61+'Results Scenario B'!E32*Assumptions!$B$8*Assumptions!$C$8*Assumptions!$B$61+'Results Scenario B'!F32*Assumptions!$B$9*Assumptions!$C$9*Assumptions!$B$61+'Results Scenario B'!G32*Assumptions!$B$10*Assumptions!$C$10*Assumptions!$B$61+'Results Scenario B'!H32*Assumptions!$B$11*Assumptions!$C$11*Assumptions!$B$61) -> 0.15025779 | AM47: =(('Results Scenario B'!D33*Assumptions!$B$7*Assumptions!$C$7*Assumptions!$B$61*(1-Assumptions!$D$7)+'Results Scenario B'!E33*Assumptions!$B$8*Assumptions!$C$8*Assumptions!$B$61*(1-Assumptions!$D$8))*0.4)/('Results Scenario B'!C33*Assumptions!$B$6*Assumptions!$C$6*Assumptions!$B$61+'Results Scenario B'!D33*Assumptions!$B$7*Assumptions!$C$7*Assumptions!$B$61+'Results Scenario B'!E33*Assumptions!$B$8*Assumptions!$C$8*Assumptions!$B$61+'Results Scenario B'!F33*Assumptions!$B$9*Assumptions!$C$9*Assumptions!$B$61+'Results Scenario B'!G33*Assumptions!$B$10*Assumptions!$C$10*Assumptions!$B$61+'Results Scenario B'!H33*Assumptions!$B$11*Assumptions!$C$11*Assumptions!$B$61) -> 0.14837749 | AN47: =(('Results Scenario B'!D34*Assumptions!$B$7*Assumptions!$C$7*Assumptions!$B$61*(1-Assumptions!$D$7)+'Results Scenario B'!E34*Assumptions!$B$8*Assumptions!$C$8*Assumptions!$B$61*(1-Assumptions!$D$8))*0.4)/('Results Scenario B'!C34*Assumptions!$B$6*Assumptions!$C$6*Assumptions!$B$61+'Results Scenario B'!D34*Assumptions!$B$7*Assumptions!$C$7*Assumptions!$B$61+'Results Scenario B'!E34*Assumptions!$B$8*Assumptions!$C$8*Assumptions!$B$61+'Results Scenario B'!F34*Assumptions!$B$9*Assumptions!$C$9*Assumptions!$B$61+'Results Scenario B'!G34*Assumptions!$B$10*Assumptions!$C$10*Assumptions!$B$61+'Results Scenario B'!H34*Assumptions!$B$11*Assumptions!$C$11*Assumptions!$B$61) -> 0.14643831 | AO47: =(('Results Scenario B'!D35*Assumptions!$B$7*Assumptions!$C$7*Assumptions!$B$61*(1-Assumptions!$D$7)+'Results Scenario B'!E35*Assumptions!$B$8*Assumptions!$C$8*Assumptions!$B$61*(1-Assumptions!$D$8))*0.4)/('Results Scenario B'!C35*Assumptions!$B$6*Assumptions!$C$6*Assumptions!$B$61+'Results Scenario B'!D35*Assumptions!$B$7*Assumptions!$C$7*Assumptions!$B$61+'Results Scenario B'!E35*Assumptions!$B$8*Assumptions!$C$8*Assumptions!$B$61+'Results Scenario B'!F35*Assumptions!$B$9*Assumptions!$C$9*Assumptions!$B$61+'Results Scenario B'!G35*Assumptions!$B$10*Assumptions!$C$10*Assumptions!$B$61+'Results Scenario B'!H35*Assumptions!$B$11*Assumptions!$C$11*Assumptions!$B$61) -> 0.14450644 | AP47: =(('Results Scenario B'!D36*Assumptions!$B$7*Assumptions!$C$7*Assumptions!$B$61*(1-Assumptions!$D$7)+'Results Scenario B'!E36*Assumptions!$B$8*Assumptions!$C$8*Assumptions!$B$61*(1-Assumptions!$D$8))*0.4)/('Results Scenario B'!C36*Assumptions!$B$6*Assumptions!$C$6*Assumptions!$B$61+'Results Scenario B'!D36*Assumptions!$B$7*Assumptions!$C$7*Assumptions!$B$61+'Results Scenario B'!E36*Assumptions!$B$8*Assumptions!$C$8*Assumptions!$B$61+'Results Scenario B'!F36*Assumptions!$B$9*Assumptions!$C$9*Assumptions!$B$61+'Results Scenario B'!G36*Assumptions!$B$10*Assumptions!$C$10*Assumptions!$B$61+'Results Scenario B'!H36*Assumptions!$B$11*Assumptions!$C$11*Assumptions!$B$61) -> 0.14263767 | AQ47: =(('Results Scenario B'!D37*Assumptions!$B$7*Assumptions!$C$7*Assumptions!$B$61*(1-Assumptions!$D$7)+'Results Scenario B'!E37*Assumptions!$B$8*Assumptions!$C$8*Assumptions!$B$61*(1-Assumptions!$D$8))*0.4)/('Results Scenario B'!C37*Assumptions!$B$6*Assumptions!$C$6*Assumptions!$B$61+'Results Scenario B'!D37*Assumptions!$B$7*Assumptions!$C$7*Assumptions!$B$61+'Results Scenario B'!E37*Assumptions!$B$8*Assumptions!$C$8*Assumptions!$B$61+'Results Scenario B'!F37*Assumptions!$B$9*Assumptions!$C$9*Assumptions!$B$61+'Results Scenario B'!G37*Assumptions!$B$10*Assumptions!$C$10*Assumptions!$B$61+'Results Scenario B'!H37*Assumptions!$B$11*Assumptions!$C$11*Assumptions!$B$61) -> 0.14087481 | AR47: =(('Results Scenario B'!D38*Assumptions!$B$7*Assumptions!$C$7*Assumptions!$B$61*(1-Assumptions!$D$7)+'Results Scenario B'!E38*Assumptions!$B$8*Assumptions!$C$8*Assumptions!$B$61*(1-Assumptions!$D$8))*0.4)/('Results Scenario B'!C38*Assumptions!$B$6*Assumptions!$C$6*Assumptions!$B$61+'Results Scenario B'!D38*Assumptions!$B$7*Assumptions!$C$7*Assumptions!$B$61+'Results Scenario B'!E38*Assumptions!$B$8*Assumptions!$C$8*Assumptions!$B$61+'Results Scenario B'!F38*Assumptions!$B$9*Assumptions!$C$9*Assumptions!$B$61+'Results Scenario B'!G38*Assumptions!$B$10*Assumptions!$C$10*Assumptions!$B$61+'Results Scenario B'!H38*Assumptions!$B$11*Assumptions!$C$11*Assumptions!$B$61) -> 0.13924718 | AS47: =(('Results Scenario B'!D39*Assumptions!$B$7*Assumptions!$C$7*Assumptions!$B$61*(1-Assumptions!$D$7)+'Results Scenario B'!E39*Assumptions!$B$8*Assumptions!$C$8*Assumptions!$B$61*(1-Assumptions!$D$8))*0.4)/('Results Scenario B'!C39*Assumptions!$B$6*Assumptions!$C$6*Assumptions!$B$61+'Results Scenario B'!D39*Assumptions!$B$7*Assumptions!$C$7*Assumptions!$B$61+'Results Scenario B'!E39*Assumptions!$B$8*Assumptions!$C$8*Assumptions!$B$61+'Results Scenario B'!F39*Assumptions!$B$9*Assumptions!$C$9*Assumptions!$B$61+'Results Scenario B'!G39*Assumptions!$B$10*Assumptions!$C$10*Assumptions!$B$61+'Results Scenario B'!H39*Assumptions!$B$11*Assumptions!$C$11*Assumptions!$B$61) -> 0.13777167
I48: Depot weight | J48: =('Results Scenario B'!F4*Assumptions!$B$9*Assumptions!$C$9*Assumptions!$B$61+'Results Scenario B'!G4*Assumptions!$B$10*Assumptions!$C$10*Assumptions!$B$61+'Results Scenario B'!H4*Assumptions!$B$11*Assumptions!$C$11*Assumptions!$B$61)/('Results Scenario B'!C4*Assumptions!$B$6*Assumptions!$C$6*Assumptions!$B$61+'Results Scenario B'!D4*Assumptions!$B$7*Assumptions!$C$7*Assumptions!$B$61+'Results Scenario B'!E4*Assumptions!$B$8*Assumptions!$C$8*Assumptions!$B$61+'Results Scenario B'!F4*Assumptions!$B$9*Assumptions!$C$9*Assumptions!$B$61+'Results Scenario B'!G4*Assumptions!$B$10*Assumptions!$C$10*Assumptions!$B$61+'Results Scenario B'!H4*Assumptions!$B$11*Assumptions!$C$11*Assumptions!$B$61) -> 0.49306156 | K48: =('Results Scenario B'!F5*Assumptions!$B$9*Assumptions!$C$9*Assumptions!$B$61+'Results Scenario B'!G5*Assumptions!$B$10*Assumptions!$C$10*Assumptions!$B$61+'Results Scenario B'!H5*Assumptions!$B$11*Assumptions!$C$11*Assumptions!$B$61)/('Results Scenario B'!C5*Assumptions!$B$6*Assumptions!$C$6*Assumptions!$B$61+'Results Scenario B'!D5*Assumptions!$B$7*Assumptions!$C$7*Assumptions!$B$61+'Results Scenario B'!E5*Assumptions!$B$8*Assumptions!$C$8*Assumptions!$B$61+'Results Scenario B'!F5*Assumptions!$B$9*Assumptions!$C$9*Assumptions!$B$61+'Results Scenario B'!G5*Assumptions!$B$10*Assumptions!$C$10*Assumptions!$B$61+'Results Scenario B'!H5*Assumptions!$B$11*Assumptions!$C$11*Assumptions!$B$61) -> 0.48097101 | L48: =('Results Scenario B'!F6*Assumptions!$B$9*Assumptions!$C$9*Assumptions!$B$61+'Results Scenario B'!G6*Assumptions!$B$10*Assumptions!$C$10*Assumptions!$B$61+'Results Scenario B'!H6*Assumptions!$B$11*Assumptions!$C$11*Assumptions!$B$61)/('Results Scenario B'!C6*Assumptions!$B$6*Assumptions!$C$6*Assumptions!$B$61+'Results Scenario B'!D6*Assumptions!$B$7*Assumptions!$C$7*Assumptions!$B$61+'Results Scenario B'!E6*Assumptions!$B$8*Assumptions!$C$8*Assumptions!$B$61+'Results Scenario B'!F6*Assumptions!$B$9*Assumptions!$C$9*Assumptions!$B$61+'Results Scenario B'!G6*Assumptions!$B$10*Assumptions!$C$10*Assumptions!$B$61+'Results Scenario B'!H6*Assumptions!$B$11*Assumptions!$C$11*Assumptions!$B$61) -> 0.46887316 | M48: =('Results Scenario B'!F7*Assumptions!$B$9*Assumptions!$C$9*Assumptions!$B$61+'Results Scenario B'!G7*Assumptions!$B$10*Assumptions!$C$10*Assumptions!$B$61+'Results Scenario B'!H7*Assumptions!$B$11*Assumptions!$C$11*Assumptions!$B$61)/('Results Scenario B'!C7*Assumptions!$B$6*Assumptions!$C$6*Assumptions!$B$61+'Results Scenario B'!D7*Assumptions!$B$7*Assumptions!$C$7*Assumptions!$B$61+'Results Scenario B'!E7*Assumptions!$B$8*Assumptions!$C$8*Assumptions!$B$61+'Results Scenario B'!F7*Assumptions!$B$9*Assumptions!$C$9*Assumptions!$B$61+'Results Scenario B'!G7*Assumptions!$B$10*Assumptions!$C$10*Assumptions!$B$61+'Results Scenario B'!H7*Assumptions!$B$11*Assumptions!$C$11*Assumptions!$B$61) -> 0.45678928 | N48: =('Results Scenario B'!F8*Assumptions!$B$9*Assumptions!$C$9*Assumptions!$B$61+'Results Scenario B'!G8*Assumptions!$B$10*Assumptions!$C$10*Assumptions!$B$61+'Results Scenario B'!H8*Assumptions!$B$11*Assumptions!$C$11*Assumptions!$B$61)/('Results Scenario B'!C8*Assumptions!$B$6*Assumptions!$C$6*Assumptions!$B$61+'Results Scenario B'!D8*Assumptions!$B$7*Assumptions!$C$7*Assumptions!$B$61+'Results Scenario B'!E8*Assumptions!$B$8*Assumptions!$C$8*Assumptions!$B$61+'Results Scenario B'!F8*Assumptions!$B$9*Assumptions!$C$9*Assumptions!$B$61+'Results Scenario B'!G8*Assumptions!$B$10*Assumptions!$C$10*Assumptions!$B$61+'Results Scenario B'!H8*Assumptions!$B$11*Assumptions!$C$11*Assumptions!$B$61) -> 0.44474296 | O48: =('Results Scenario B'!F9*Assumptions!$B$9*Assumptions!$C$9*Assumptions!$B$61+'Results Scenario B'!G9*Assumptions!$B$10*Assumptions!$C$10*Assumptions!$B$61+'Results Scenario B'!H9*Assumptions!$B$11*Assumptions!$C$11*Assumptions!$B$61)/('Results Scenario B'!C9*Assumptions!$B$6*Assumptions!$C$6*Assumptions!$B$61+'Results Scenario B'!D9*Assumptions!$B$7*Assumptions!$C$7*Assumptions!$B$61+'Results Scenario B'!E9*Assumptions!$B$8*Assumptions!$C$8*Assumptions!$B$61+'Results Scenario B'!F9*Assumptions!$B$9*Assumptions!$C$9*Assumptions!$B$61+'Results Scenario B'!G9*Assumptions!$B$10*Assumptions!$C$10*Assumptions!$B$61+'Results Scenario B'!H9*Assumptions!$B$11*Assumptions!$C$11*Assumptions!$B$61) -> 0.43276067 | P48: =('Results Scenario B'!F10*Assumptions!$B$9*Assumptions!$C$9*Assumptions!$B$61+'Results Scenario B'!G10*Assumptions!$B$10*Assumptions!$C$10*Assumptions!$B$61+'Results Scenario B'!H10*Assumptions!$B$11*Assumptions!$C$11*Assumptions!$B$61)/('Results Scenario B'!C10*Assumptions!$B$6*Assumptions!$C$6*Assumptions!$B$61+'Results Scenario B'!D10*Assumptions!$B$7*Assumptions!$C$7*Assumptions!$B$61+'Results Scenario B'!E10*Assumptions!$B$8*Assumptions!$C$8*Assumptions!$B$61+'Results Scenario B'!F10*Assumptions!$B$9*Assumptions!$C$9*Assumptions!$B$61+'Results Scenario B'!G10*Assumptions!$B$10*Assumptions!$C$10*Assumptions!$B$61+'Results Scenario B'!H10*Assumptions!$B$11*Assumptions!$C$11*Assumptions!$B$61) -> 0.42087255 | Q48: =('Results Scenario B'!F11*Assumptions!$B$9*Assumptions!$C$9*Assumptions!$B$61+'Results Scenario B'!G11*Assumptions!$B$10*Assumptions!$C$10*Assumptions!$B$61+'Results Scenario B'!H11*Assumptions!$B$11*Assumptions!$C$11*Assumptions!$B$61)/('Results Scenario B'!C11*Assumptions!$B$6*Assumptions!$C$6*Assumptions!$B$61+'Results Scenario B'!D11*Assumptions!$B$7*Assumptions!$C$7*Assumptions!$B$61+'Results Scenario B'!E11*Assumptions!$B$8*Assumptions!$C$8*Assumptions!$B$61+'Results Scenario B'!F11*Assumptions!$B$9*Assumptions!$C$9*Assumptions!$B$61+'Results Scenario B'!G11*Assumptions!$B$10*Assumptions!$C$10*Assumptions!$B$61+'Results Scenario B'!H11*Assumptions!$B$11*Assumptions!$C$11*Assumptions!$B$61) -> 0.40911334 | R48: =('Results Scenario B'!F12*Assumptions!$B$9*Assumptions!$C$9*Assumptions!$B$61+'Results Scenario B'!G12*Assumptions!$B$10*Assumptions!$C$10*Assumptions!$B$61+'Results Scenario B'!H12*Assumptions!$B$11*Assumptions!$C$11*Assumptions!$B$61)/('Results Scenario B'!C12*Assumptions!$B$6*Assumptions!$C$6*Assumptions!$B$61+'Results Scenario B'!D12*Assumptions!$B$7*Assumptions!$C$7*Assumptions!$B$61+'Results Scenario B'!E12*Assumptions!$B$8*Assumptions!$C$8*Assumptions!$B$61+'Results Scenario B'!F12*Assumptions!$B$9*Assumptions!$C$9*Assumptions!$B$61+'Results Scenario B'!G12*Assumptions!$B$10*Assumptions!$C$10*Assumptions!$B$61+'Results Scenario B'!H12*Assumptions!$B$11*Assumptions!$C$11*Assumptions!$B$61) -> 0.39752357 | S48: =('Results Scenario B'!F13*Assumptions!$B$9*Assumptions!$C$9*Assumptions!$B$61+'Results Scenario B'!G13*Assumptions!$B$10*Assumptions!$C$10*Assumptions!$B$61+'Results Scenario B'!H13*Assumptions!$B$11*Assumptions!$C$11*Assumptions!$B$61)/('Results Scenario B'!C13*Assumptions!$B$6*Assumptions!$C$6*Assumptions!$B$61+'Results Scenario B'!D13*Assumptions!$B$7*Assumptions!$C$7*Assumptions!$B$61+'Results Scenario B'!E13*Assumptions!$B$8*Assumptions!$C$8*Assumptions!$B$61+'Results Scenario B'!F13*Assumptions!$B$9*Assumptions!$C$9*Assumptions!$B$61+'Results Scenario B'!G13*Assumptions!$B$10*Assumptions!$C$10*Assumptions!$B$61+'Results Scenario B'!H13*Assumptions!$B$11*Assumptions!$C$11*Assumptions!$B$61) -> 0.38615096 | T48: =('Results Scenario B'!F14*Assumptions!$B$9*Assumptions!$C$9*Assumptions!$B$61+'Results Scenario B'!G14*Assumptions!$B$10*Assumptions!$C$10*Assumptions!$B$61+'Results Scenario B'!H14*Assumptions!$B$11*Assumptions!$C$11*Assumptions!$B$61)/('Results Scenario B'!C14*Assumptions!$B$6*Assumptions!$C$6*Assumptions!$B$61+'Results Scenario B'!D14*Assumptions!$B$7*Assumptions!$C$7*Assumptions!$B$61+'Results Scenario B'!E14*Assumptions!$B$8*Assumptions!$C$8*Assumptions!$B$61+'Results Scenario B'!F14*Assumptions!$B$9*Assumptions!$C$9*Assumptions!$B$61+'Results Scenario B'!G14*Assumptions!$B$10*Assumptions!$C$10*Assumptions!$B$61+'Results Scenario B'!H14*Assumptions!$B$11*Assumptions!$C$11*Assumptions!$B$61) -> 0.3750521 | U48: =('Results Scenario B'!F15*Assumptions!$B$9*Assumptions!$C$9*Assumptions!$B$61+'Results Scenario B'!G15*Assumptions!$B$10*Assumptions!$C$10*Assumptions!$B$61+'Results Scenario B'!H15*Assumptions!$B$11*Assumptions!$C$11*Assumptions!$B$61)/('Results Scenario B'!C15*Assumptions!$B$6*Assumptions!$C$6*Assumptions!$B$61+'Results Scenario B'!D15*Assumptions!$B$7*Assumptions!$C$7*Assumptions!$B$61+'Results Scenario B'!E15*Assumptions!$B$8*Assumptions!$C$8*Assumptions!$B$61+'Results Scenario B'!F15*Assumptions!$B$9*Assumptions!$C$9*Assumptions!$B$61+'Results Scenario B'!G15*Assumptions!$B$10*Assumptions!$C$10*Assumptions!$B$61+'Results Scenario B'!H15*Assumptions!$B$11*Assumptions!$C$11*Assumptions!$B$61) -> 0.36429434 | V48: =('Results Scenario B'!F16*Assumptions!$B$9*Assumptions!$C$9*Assumptions!$B$61+'Results Scenario B'!G16*Assumptions!$B$10*Assumptions!$C$10*Assumptions!$B$61+'Results Scenario B'!H16*Assumptions!$B$11*Assumptions!$C$11*Assumptions!$B$61)/('Results Scenario B'!C16*Assumptions!$B$6*Assumptions!$C$6*Assumptions!$B$61+'Results Scenario B'!D16*Assumptions!$B$7*Assumptions!$C$7*Assumptions!$B$61+'Results Scenario B'!E16*Assumptions!$B$8*Assumptions!$C$8*Assumptions!$B$61+'Results Scenario B'!F16*Assumptions!$B$9*Assumptions!$C$9*Assumptions!$B$61+'Results Scenario B'!G16*Assumptions!$B$10*Assumptions!$C$10*Assumptions!$B$61+'Results Scenario B'!H16*Assumptions!$B$11*Assumptions!$C$11*Assumptions!$B$61) -> 0.35395774 | W48: =('Results Scenario B'!F17*Assumptions!$B$9*Assumptions!$C$9*Assumptions!$B$61+'Results Scenario B'!G17*Assumptions!$B$10*Assumptions!$C$10*Assumptions!$B$61+'Results Scenario B'!H17*Assumptions!$B$11*Assumptions!$C$11*Assumptions!$B$61)/('Results Scenario B'!C17*Assumptions!$B$6*Assumptions!$C$6*Assumptions!$B$61+'Results Scenario B'!D17*Assumptions!$B$7*Assumptions!$C$7*Assumptions!$B$61+'Results Scenario B'!E17*Assumptions!$B$8*Assumptions!$C$8*Assumptions!$B$61+'Results Scenario B'!F17*Assumptions!$B$9*Assumptions!$C$9*Assumptions!$B$61+'Results Scenario B'!G17*Assumptions!$B$10*Assumptions!$C$10*Assumptions!$B$61+'Results Scenario B'!H17*Assumptions!$B$11*Assumptions!$C$11*Assumptions!$B$61) -> 0.34413705 | X48: =('Results Scenario B'!F18*Assumptions!$B$9*Assumptions!$C$9*Assumptions!$B$61+'Results Scenario B'!G18*Assumptions!$B$10*Assumptions!$C$10*Assumptions!$B$61+'Results Scenario B'!H18*Assumptions!$B$11*Assumptions!$C$11*Assumptions!$B$61)/('Results Scenario B'!C18*Assumptions!$B$6*Assumptions!$C$6*Assumptions!$B$61+'Results Scenario B'!D18*Assumptions!$B$7*Assumptions!$C$7*Assumptions!$B$61+'Results Scenario B'!E18*Assumptions!$B$8*Assumptions!$C$8*Assumptions!$B$61+'Results Scenario B'!F18*Assumptions!$B$9*Assumptions!$C$9*Assumptions!$B$61+'Results Scenario B'!G18*Assumptions!$B$10*Assumptions!$C$10*Assumptions!$B$61+'Results Scenario B'!H18*Assumptions!$B$11*Assumptions!$C$11*Assumptions!$B$61) -> 0.3349432 | Y48: =('Results Scenario B'!F19*Assumptions!$B$9*Assumptions!$C$9*Assumptions!$B$61+'Results Scenario B'!G19*Assumptions!$B$10*Assumptions!$C$10*Assumptions!$B$61+'Results Scenario B'!H19*Assumptions!$B$11*Assumptions!$C$11*Assumptions!$B$61)/('Results Scenario B'!C19*Assumptions!$B$6*Assumptions!$C$6*Assumptions!$B$61+'Results Scenario B'!D19*Assumptions!$B$7*Assumptions!$C$7*Assumptions!$B$61+'Results Scenario B'!E19*Assumptions!$B$8*Assumptions!$C$8*Assumptions!$B$61+'Results Scenario B'!F19*Assumptions!$B$9*Assumptions!$C$9*Assumptions!$B$61+'Results Scenario B'!G19*Assumptions!$B$10*Assumptions!$C$10*Assumptions!$B$61+'Results Scenario B'!H19*Assumptions!$B$11*Assumptions!$C$11*Assumptions!$B$61) -> 0.32650401 | Z48: =('Results Scenario B'!F20*Assumptions!$B$9*Assumptions!$C$9*Assumptions!$B$61+'Results Scenario B'!G20*Assumptions!$B$10*Assumptions!$C$10*Assumptions!$B$61+'Results Scenario B'!H20*Assumptions!$B$11*Assumptions!$C$11*Assumptions!$B$61)/('Results Scenario B'!C20*Assumptions!$B$6*Assumptions!$C$6*Assumptions!$B$61+'Results Scenario B'!D20*Assumptions!$B$7*Assumptions!$C$7*Assumptions!$B$61+'Results Scenario B'!E20*Assumptions!$B$8*Assumptions!$C$8*Assumptions!$B$61+'Results Scenario B'!F20*Assumptions!$B$9*Assumptions!$C$9*Assumptions!$B$61+'Results Scenario B'!G20*Assumptions!$B$10*Assumptions!$C$10*Assumptions!$B$61+'Results Scenario B'!H20*Assumptions!$B$11*Assumptions!$C$11*Assumptions!$B$61) -> 0.3189634 | AA48: =('Results Scenario B'!F21*Assumptions!$B$9*Assumptions!$C$9*Assumptions!$B$61+'Results Scenario B'!G21*Assumptions!$B$10*Assumptions!$C$10*Assumptions!$B$61+'Results Scenario B'!H21*Assumptions!$B$11*Assumptions!$C$11*Assumptions!$B$61)/('Results Scenario B'!C21*Assumptions!$B$6*Assumptions!$C$6*Assumptions!$B$61+'Results Scenario B'!D21*Assumptions!$B$7*Assumptions!$C$7*Assumptions!$B$61+'Results Scenario B'!E21*Assumptions!$B$8*Assumptions!$C$8*Assumptions!$B$61+'Results Scenario B'!F21*Assumptions!$B$9*Assumptions!$C$9*Assumptions!$B$61+'Results Scenario B'!G21*Assumptions!$B$10*Assumptions!$C$10*Assumptions!$B$61+'Results Scenario B'!H21*Assumptions!$B$11*Assumptions!$C$11*Assumptions!$B$61) -> 0.31247847 | AB48: =('Results Scenario B'!F22*Assumptions!$B$9*Assumptions!$C$9*Assumptions!$B$61+'Results Scenario B'!G22*Assumptions!$B$10*Assumptions!$C$10*Assumptions!$B$61+'Results Scenario B'!H22*Assumptions!$B$11*Assumptions!$C$11*Assumptions!$B$61)/('Results Scenario B'!C22*Assumptions!$B$6*Assumptions!$C$6*Assumptions!$B$61+'Results Scenario B'!D22*Assumptions!$B$7*Assumptions!$C$7*Assumptions!$B$61+'Results Scenario B'!E22*Assumptions!$B$8*Assumptions!$C$8*Assumptions!$B$61+'Results Scenario B'!F22*Assumptions!$B$9*Assumptions!$C$9*Assumptions!$B$61+'Results Scenario B'!G22*Assumptions!$B$10*Assumptions!$C$10*Assumptions!$B$61+'Results Scenario B'!H22*Assumptions!$B$11*Assumptions!$C$11*Assumptions!$B$61) -> 0.30721364 | AC48: =('Results Scenario B'!F23*Assumptions!$B$9*Assumptions!$C$9*Assumptions!$B$61+'Results Scenario B'!G23*Assumptions!$B$10*Assumptions!$C$10*Assumptions!$B$61+'Results Scenario B'!H23*Assumptions!$B$11*Assumptions!$C$11*Assumptions!$B$61)/('Results Scenario B'!C23*Assumptions!$B$6*Assumptions!$C$6*Assumptions!$B$61+'Results Scenario B'!D23*Assumptions!$B$7*Assumptions!$C$7*Assumptions!$B$61+'Results Scenario B'!E23*Assumptions!$B$8*Assumptions!$C$8*Assumptions!$B$61+'Results Scenario B'!F23*Assumptions!$B$9*Assumptions!$C$9*Assumptions!$B$61+'Results Scenario B'!G23*Assumptions!$B$10*Assumptions!$C$10*Assumptions!$B$61+'Results Scenario B'!H23*Assumptions!$B$11*Assumptions!$C$11*Assumptions!$B$61) -> 0.30333142 | AD48: =('Results Scenario B'!F24*Assumptions!$B$9*Assumptions!$C$9*Assumptions!$B$61+'Results Scenario B'!G24*Assumptions!$B$10*Assumptions!$C$10*Assumptions!$B$61+'Results Scenario B'!H24*Assumptions!$B$11*Assumptions!$C$11*Assumptions!$B$61)/('Results Scenario B'!C24*Assumptions!$B$6*Assumptions!$C$6*Assumptions!$B$61+'Results Scenario B'!D24*Assumptions!$B$7*Assumptions!$C$7*Assumptions!$B$61+'Results Scenario B'!E24*Assumptions!$B$8*Assumptions!$C$8*Assumptions!$B$61+'Results Scenario B'!F24*Assumptions!$B$9*Assumptions!$C$9*Assumptions!$B$61+'Results Scenario B'!G24*Assumptions!$B$10*Assumptions!$C$10*Assumptions!$B$61+'Results Scenario B'!H24*Assumptions!$B$11*Assumptions!$C$11*Assumptions!$B$61) -> 0.3009799 | AE48: =('Results Scenario B'!F25*Assumptions!$B$9*Assumptions!$C$9*Assumptions!$B$61+'Results Scenario B'!G25*Assumptions!$B$10*Assumptions!$C$10*Assumptions!$B$61+'Results Scenario B'!H25*Assumptions!$B$11*Assumptions!$C$11*Assumptions!$B$61)/('Results Scenario B'!C25*Assumptions!$B$6*Assumptions!$C$6*Assumptions!$B$61+'Results Scenario B'!D25*Assumptions!$B$7*Assumptions!$C$7*Assumptions!$B$61+'Results Scenario B'!E25*Assumptions!$B$8*Assumptions!$C$8*Assumptions!$B$61+'Results Scenario B'!F25*Assumptions!$B$9*Assumptions!$C$9*Assumptions!$B$61+'Results Scenario B'!G25*Assumptions!$B$10*Assumptions!$C$10*Assumptions!$B$61+'Results Scenario B'!H25*Assumptions!$B$11*Assumptions!$C$11*Assumptions!$B$61) -> 0.30027758 | AF48: =('Results Scenario B'!F26*Assumptions!$B$9*Assumptions!$C$9*Assumptions!$B$61+'Results Scenario B'!G26*Assumptions!$B$10*Assumptions!$C$10*Assumptions!$B$61+'Results Scenario B'!H26*Assumptions!$B$11*Assumptions!$C$11*Assumptions!$B$61)/('Results Scenario B'!C26*Assumptions!$B$6*Assumptions!$C$6*Assumptions!$B$61+'Results Scenario B'!D26*Assumptions!$B$7*Assumptions!$C$7*Assumptions!$B$61+'Results Scenario B'!E26*Assumptions!$B$8*Assumptions!$C$8*Assumptions!$B$61+'Results Scenario B'!F26*Assumptions!$B$9*Assumptions!$C$9*Assumptions!$B$61+'Results Scenario B'!G26*Assumptions!$B$10*Assumptions!$C$10*Assumptions!$B$61+'Results Scenario B'!H26*Assumptions!$B$11*Assumptions!$C$11*Assumptions!$B$61) -> 0.30129701 | AG48: =('Results Scenario B'!F27*Assumptions!$B$9*Assumptions!$C$9*Assumptions!$B$61+'Results Scenario B'!G27*Assumptions!$B$10*Assumptions!$C$10*Assumptions!$B$61+'Results Scenario B'!H27*Assumptions!$B$11*Assumptions!$C$11*Assumptions!$B$61)/('Results Scenario B'!C27*Assumptions!$B$6*Assumptions!$C$6*Assumptions!$B$61+'Results Scenario B'!D27*Assumptions!$B$7*Assumptions!$C$7*Assumptions!$B$61+'Results Scenario B'!E27*Assumptions!$B$8*Assumptions!$C$8*Assumptions!$B$61+'Results Scenario B'!F27*Assumptions!$B$9*Assumptions!$C$9*Assumptions!$B$61+'Results Scenario B'!G27*Assumptions!$B$10*Assumptions!$C$10*Assumptions!$B$61+'Results Scenario B'!H27*Assumptions!$B$11*Assumptions!$C$11*Assumptions!$B$61) -> 0.30404947 | AH48: =('Results Scenario B'!F28*Assumptions!$B$9*Assumptions!$C$9*Assumptions!$B$61+'Results Scenario B'!G28*Assumptions!$B$10*Assumptions!$C$10*Assumptions!$B$61+'Results Scenario B'!H28*Assumptions!$B$11*Assumptions!$C$11*Assumptions!$B$61)/('Results Scenario B'!C28*Assumptions!$B$6*Assumptions!$C$6*Assumptions!$B$61+'Results Scenario B'!D28*Assumptions!$B$7*Assumptions!$C$7*Assumptions!$B$61+'Results Scenario B'!E28*Assumptions!$B$8*Assumptions!$C$8*Assumptions!$B$61+'Results Scenario B'!F28*Assumptions!$B$9*Assumptions!$C$9*Assumptions!$B$61+'Results Scenario B'!G28*Assumptions!$B$10*Assumptions!$C$10*Assumptions!$B$61+'Results Scenario B'!H28*Assumptions!$B$11*Assumptions!$C$11*Assumptions!$B$61) -> 0.3084733 | AI48: =('Results Scenario B'!F29*Assumptions!$B$9*Assumptions!$C$9*Assumptions!$B$61+'Results Scenario B'!G29*Assumptions!$B$10*Assumptions!$C$10*Assumptions!$B$61+'Results Scenario B'!H29*Assumptions!$B$11*Assumptions!$C$11*Assumptions!$B$61)/('Results Scenario B'!C29*Assumptions!$B$6*Assumptions!$C$6*Assumptions!$B$61+'Results Scenario B'!D29*Assumptions!$B$7*Assumptions!$C$7*Assumptions!$B$61+'Results Scenario B'!E29*Assumptions!$B$8*Assumptions!$C$8*Assumptions!$B$61+'Results Scenario B'!F29*Assumptions!$B$9*Assumptions!$C$9*Assumptions!$B$61+'Results Scenario B'!G29*Assumptions!$B$10*Assumptions!$C$10*Assumptions!$B$61+'Results Scenario B'!H29*Assumptions!$B$11*Assumptions!$C$11*Assumptions!$B$61) -> 0.31442864 | AJ48: =('Results Scenario B'!F30*Assumptions!$B$9*Assumptions!$C$9*Assumptions!$B$61+'Results Scenario B'!G30*Assumptions!$B$10*Assumptions!$C$10*Assumptions!$B$61+'Results Scenario B'!H30*Assumptions!$B$11*Assumptions!$C$11*Assumptions!$B$61)/('Results Scenario B'!C30*Assumptions!$B$6*Assumptions!$C$6*Assumptions!$B$61+'Results Scenario B'!D30*Assumptions!$B$7*Assumptions!$C$7*Assumptions!$B$61+'Results Scenario B'!E30*Assumptions!$B$8*Assumptions!$C$8*Assumptions!$B$61+'Results Scenario B'!F30*Assumptions!$B$9*Assumptions!$C$9*Assumptions!$B$61+'Results Scenario B'!G30*Assumptions!$B$10*Assumptions!$C$10*Assumptions!$B$61+'Results Scenario B'!H30*Assumptions!$B$11*Assumptions!$C$11*Assumptions!$B$61) -> 0.32170098 | AK48: =('Results Scenario B'!F31*Assumptions!$B$9*Assumptions!$C$9*Assumptions!$B$61+'Results Scenario B'!G31*Assumptions!$B$10*Assumptions!$C$10*Assumptions!$B$61+'Results Scenario B'!H31*Assumptions!$B$11*Assumptions!$C$11*Assumptions!$B$61)/('Results Scenario B'!C31*Assumptions!$B$6*Assumptions!$C$6*Assumptions!$B$61+'Results Scenario B'!D31*Assumptions!$B$7*Assumptions!$C$7*Assumptions!$B$61+'Results Scenario B'!E31*Assumptions!$B$8*Assumptions!$C$8*Assumptions!$B$61+'Results Scenario B'!F31*Assumptions!$B$9*Assumptions!$C$9*Assumptions!$B$61+'Results Scenario B'!G31*Assumptions!$B$10*Assumptions!$C$10*Assumptions!$B$61+'Results Scenario B'!H31*Assumptions!$B$11*Assumptions!$C$11*Assumptions!$B$61) -> 0.33001416 | AL48: =('Results Scenario B'!F32*Assumptions!$B$9*Assumptions!$C$9*Assumptions!$B$61+'Results Scenario B'!G32*Assumptions!$B$10*Assumptions!$C$10*Assumptions!$B$61+'Results Scenario B'!H32*Assumptions!$B$11*Assumptions!$C$11*Assumptions!$B$61)/('Results Scenario B'!C32*Assumptions!$B$6*Assumptions!$C$6*Assumptions!$B$61+'Results Scenario B'!D32*Assumptions!$B$7*Assumptions!$C$7*Assumptions!$B$61+'Results Scenario B'!E32*Assumptions!$B$8*Assumptions!$C$8*Assumptions!$B$61+'Results Scenario B'!F32*Assumptions!$B$9*Assumptions!$C$9*Assumptions!$B$61+'Results Scenario B'!G32*Assumptions!$B$10*Assumptions!$C$10*Assumptions!$B$61+'Results Scenario B'!H32*Assumptions!$B$11*Assumptions!$C$11*Assumptions!$B$61) -> 0.33905198 | AM48: =('Results Scenario B'!F33*Assumptions!$B$9*Assumptions!$C$9*Assumptions!$B$61+'Results Scenario B'!G33*Assumptions!$B$10*Assumptions!$C$10*Assumptions!$B$61+'Results Scenario B'!H33*Assumptions!$B$11*Assumptions!$C$11*Assumptions!$B$61)/('Results Scenario B'!C33*Assumptions!$B$6*Assumptions!$C$6*Assumptions!$B$61+'Results Scenario B'!D33*Assumptions!$B$7*Assumptions!$C$7*Assumptions!$B$61+'Results Scenario B'!E33*Assumptions!$B$8*Assumptions!$C$8*Assumptions!$B$61+'Results Scenario B'!F33*Assumptions!$B$9*Assumptions!$C$9*Assumptions!$B$61+'Results Scenario B'!G33*Assumptions!$B$10*Assumptions!$C$10*Assumptions!$B$61+'Results Scenario B'!H33*Assumptions!$B$11*Assumptions!$C$11*Assumptions!$B$61) -> 0.34848473 | AN48: =('Results Scenario B'!F34*Assumptions!$B$9*Assumptions!$C$9*Assumptions!$B$61+'Results Scenario B'!G34*Assumptions!$B$10*Assumptions!$C$10*Assumptions!$B$61+'Results Scenario B'!H34*Assumptions!$B$11*Assumptions!$C$11*Assumptions!$B$61)/('Results Scenario B'!C34*Assumptions!$B$6*Assumptions!$C$6*Assumptions!$B$61+'Results Scenario B'!D34*Assumptions!$B$7*Assumptions!$C$7*Assumptions!$B$61+'Results Scenario B'!E34*Assumptions!$B$8*Assumptions!$C$8*Assumptions!$B$61+'Results Scenario B'!F34*Assumptions!$B$9*Assumptions!$C$9*Assumptions!$B$61+'Results Scenario B'!G34*Assumptions!$B$10*Assumptions!$C$10*Assumptions!$B$61+'Results Scenario B'!H34*Assumptions!$B$11*Assumptions!$C$11*Assumptions!$B$61) -> 0.35799636 | AO48: =('Results Scenario B'!F35*Assumptions!$B$9*Assumptions!$C$9*Assumptions!$B$61+'Results Scenario B'!G35*Assumptions!$B$10*Assumptions!$C$10*Assumptions!$B$61+'Results Scenario B'!H35*Assumptions!$B$11*Assumptions!$C$11*Assumptions!$B$61)/('Results Scenario B'!C35*Assumptions!$B$6*Assumptions!$C$6*Assumptions!$B$61+'Results Scenario B'!D35*Assumptions!$B$7*Assumptions!$C$7*Assumptions!$B$61+'Results Scenario B'!E35*Assumptions!$B$8*Assumptions!$C$8*Assumptions!$B$61+'Results Scenario B'!F35*Assumptions!$B$9*Assumptions!$C$9*Assumptions!$B$61+'Results Scenario B'!G35*Assumptions!$B$10*Assumptions!$C$10*Assumptions!$B$61+'Results Scenario B'!H35*Assumptions!$B$11*Assumptions!$C$11*Assumptions!$B$61) -> 0.3673075 | AP48: =('Results Scenario B'!F36*Assumptions!$B$9*Assumptions!$C$9*Assumptions!$B$61+'Results Scenario B'!G36*Assumptions!$B$10*Assumptions!$C$10*Assumptions!$B$61+'Results Scenario B'!H36*Assumptions!$B$11*Assumptions!$C$11*Assumptions!$B$61)/('Results Scenario B'!C36*Assumptions!$B$6*Assumptions!$C$6*Assumptions!$B$61+'Results Scenario B'!D36*Assumptions!$B$7*Assumptions!$C$7*Assumptions!$B$61+'Results Scenario B'!E36*Assumptions!$B$8*Assumptions!$C$8*Assumptions!$B$61+'Results Scenario B'!F36*Assumptions!$B$9*Assumptions!$C$9*Assumptions!$B$61+'Results Scenario B'!G36*Assumptions!$B$10*Assumptions!$C$10*Assumptions!$B$61+'Results Scenario B'!H36*Assumptions!$B$11*Assumptions!$C$11*Assumptions!$B$61) -> 0.37619117 | AQ48: =('Results Scenario B'!F37*Assumptions!$B$9*Assumptions!$C$9*Assumptions!$B$61+'Results Scenario B'!G37*Assumptions!$B$10*Assumptions!$C$10*Assumptions!$B$61+'Results Scenario B'!H37*Assumptions!$B$11*Assumptions!$C$11*Assumptions!$B$61)/('Results Scenario B'!C37*Assumptions!$B$6*Assumptions!$C$6*Assumptions!$B$61+'Results Scenario B'!D37*Assumptions!$B$7*Assumptions!$C$7*Assumptions!$B$61+'Results Scenario B'!E37*Assumptions!$B$8*Assumptions!$C$8*Assumptions!$B$61+'Results Scenario B'!F37*Assumptions!$B$9*Assumptions!$C$9*Assumptions!$B$61+'Results Scenario B'!G37*Assumptions!$B$10*Assumptions!$C$10*Assumptions!$B$61+'Results Scenario B'!H37*Assumptions!$B$11*Assumptions!$C$11*Assumptions!$B$61) -> 0.38448011 | AR48: =('Results Scenario B'!F38*Assumptions!$B$9*Assumptions!$C$9*Assumptions!$B$61+'Results Scenario B'!G38*Assumptions!$B$10*Assumptions!$C$10*Assumptions!$B$61+'Results Scenario B'!H38*Assumptions!$B$11*Assumptions!$C$11*Assumptions!$B$61)/('Results Scenario B'!C38*Assumptions!$B$6*Assumptions!$C$6*Assumptions!$B$61+'Results Scenario B'!D38*Assumptions!$B$7*Assumptions!$C$7*Assumptions!$B$61+'Results Scenario B'!E38*Assumptions!$B$8*Assumptions!$C$8*Assumptions!$B$61+'Results Scenario B'!F38*Assumptions!$B$9*Assumptions!$C$9*Assumptions!$B$61+'Results Scenario B'!G38*Assumptions!$B$10*Assumptions!$C$10*Assumptions!$B$61+'Results Scenario B'!H38*Assumptions!$B$11*Assumptions!$C$11*Assumptions!$B$61) -> 0.39206636 | AS48: =('Results Scenario B'!F39*Assumptions!$B$9*Assumptions!$C$9*Assumptions!$B$61+'Results Scenario B'!G39*Assumptions!$B$10*Assumptions!$C$10*Assumptions!$B$61+'Results Scenario B'!H39*Assumptions!$B$11*Assumptions!$C$11*Assumptions!$B$61)/('Results Scenario B'!C39*Assumptions!$B$6*Assumptions!$C$6*Assumptions!$B$61+'Results Scenario B'!D39*Assumptions!$B$7*Assumptions!$C$7*Assumptions!$B$61+'Results Scenario B'!E39*Assumptions!$B$8*Assumptions!$C$8*Assumptions!$B$61+'Results Scenario B'!F39*Assumptions!$B$9*Assumptions!$C$9*Assumptions!$B$61+'Results Scenario B'!G39*Assumptions!$B$10*Assumptions!$C$10*Assumptions!$B$61+'Results Scenario B'!H39*Assumptions!$B$11*Assumptions!$C$11*Assumptions!$B$61) -> 0.39889507
I49: Battery swap weight | J49: ='Results Scenario B'!C4*Assumptions!$B$6*Assumptions!$C$6*Assumptions!$B$61*(1-Assumptions!$D$6)*Assumptions!$B$89/Assumptions!$B$6/('Results Scenario B'!C4*Assumptions!$B$6*Assumptions!$C$6*Assumptions!$B$61+'Results Scenario B'!D4*Assumptions!$B$7*Assumptions!$C$7*Assumptions!$B$61+'Results Scenario B'!E4*Assumptions!$B$8*Assumptions!$C$8*Assumptions!$B$61+'Results Scenario B'!F4*Assumptions!$B$9*Assumptions!$C$9*Assumptions!$B$61+'Results Scenario B'!G4*Assumptions!$B$10*Assumptions!$C$10*Assumptions!$B$61+'Results Scenario B'!H4*Assumptions!$B$11*Assumptions!$C$11*Assumptions!$B$61) -> 0.02335693 | K49: ='Results Scenario B'!C5*Assumptions!$B$6*Assumptions!$C$6*Assumptions!$B$61*(1-Assumptions!$D$6)*Assumptions!$B$89/Assumptions!$B$6/('Results Scenario B'!C5*Assumptions!$B$6*Assumptions!$C$6*Assumptions!$B$61+'Results Scenario B'!D5*Assumptions!$B$7*Assumptions!$C$7*Assumptions!$B$61+'Results Scenario B'!E5*Assumptions!$B$8*Assumptions!$C$8*Assumptions!$B$61+'Results Scenario B'!F5*Assumptions!$B$9*Assumptions!$C$9*Assumptions!$B$61+'Results Scenario B'!G5*Assumptions!$B$10*Assumptions!$C$10*Assumptions!$B$61+'Results Scenario B'!H5*Assumptions!$B$11*Assumptions!$C$11*Assumptions!$B$61) -> 0.024615537 | L49: ='Results Scenario B'!C6*Assumptions!$B$6*Assumptions!$C$6*Assumptions!$B$61*(1-Assumptions!$D$6)*Assumptions!$B$89/Assumptions!$B$6/('Results Scenario B'!C6*Assumptions!$B$6*Assumptions!$C$6*Assumptions!$B$61+'Results Scenario B'!D6*Assumptions!$B$7*Assumptions!$C$7*Assumptions!$B$61+'Results Scenario B'!E6*Assumptions!$B$8*Assumptions!$C$8*Assumptions!$B$61+'Results Scenario B'!F6*Assumptions!$B$9*Assumptions!$C$9*Assumptions!$B$61+'Results Scenario B'!G6*Assumptions!$B$10*Assumptions!$C$10*Assumptions!$B$61+'Results Scenario B'!H6*Assumptions!$B$11*Assumptions!$C$11*Assumptions!$B$61) -> 0.025921983 | M49: ='Results Scenario B'!C7*Assumptions!$B$6*Assumptions!$C$6*Assumptions!$B$61*(1-Assumptions!$D$6)*Assumptions!$B$89/Assumptions!$B$6/('Results Scenario B'!C7*Assumptions!$B$6*Assumptions!$C$6*Assumptions!$B$61+'Results Scenario B'!D7*Assumptions!$B$7*Assumptions!$C$7*Assumptions!$B$61+'Results Scenario B'!E7*Assumptions!$B$8*Assumptions!$C$8*Assumptions!$B$61+'Results Scenario B'!F7*Assumptions!$B$9*Assumptions!$C$9*Assumptions!$B$61+'Results Scenario B'!G7*Assumptions!$B$10*Assumptions!$C$10*Assumptions!$B$61+'Results Scenario B'!H7*Assumptions!$B$11*Assumptions!$C$11*Assumptions!$B$61) -> 0.027275659 | N49: ='Results Scenario B'!C8*Assumptions!$B$6*Assumptions!$C$6*Assumptions!$B$61*(1-Assumptions!$D$6)*Assumptions!$B$89/Assumptions!$B$6/('Results Scenario B'!C8*Assumptions!$B$6*Assumptions!$C$6*Assumptions!$B$61+'Results Scenario B'!D8*Assumptions!$B$7*Assumptions!$C$7*Assumptions!$B$61+'Results Scenario B'!E8*Assumptions!$B$8*Assumptions!$C$8*Assumptions!$B$61+'Results Scenario B'!F8*Assumptions!$B$9*Assumptions!$C$9*Assumptions!$B$61+'Results Scenario B'!G8*Assumptions!$B$10*Assumptions!$C$10*Assumptions!$B$61+'Results Scenario B'!H8*Assumptions!$B$11*Assumptions!$C$11*Assumptions!$B$61) -> 0.028675283 | O49: ='Results Scenario B'!C9*Assumptions!$B$6*Assumptions!$C$6*Assumptions!$B$61*(1-Assumptions!$D$6)*Assumptions!$B$89/Assumptions!$B$6/('Results Scenario B'!C9*Assumptions!$B$6*Assumptions!$C$6*Assumptions!$B$61+'Results Scenario B'!D9*Assumptions!$B$7*Assumptions!$C$7*Assumptions!$B$61+'Results Scenario B'!E9*Assumptions!$B$8*Assumptions!$C$8*Assumptions!$B$61+'Results Scenario B'!F9*Assumptions!$B$9*Assumptions!$C$9*Assumptions!$B$61+'Results Scenario B'!G9*Assumptions!$B$10*Assumptions!$C$10*Assumptions!$B$61+'Results Scenario B'!H9*Assumptions!$B$11*Assumptions!$C$11*Assumptions!$B$61) -> 0.030118659 | P49: ='Results Scenario B'!C10*Assumptions!$B$6*Assumptions!$C$6*Assumptions!$B$61*(1-Assumptions!$D$6)*Assumptions!$B$89/Assumptions!$B$6/('Results Scenario B'!C10*Assumptions!$B$6*Assumptions!$C$6*Assumptions!$B$61+'Results Scenario B'!D10*Assumptions!$B$7*Assumptions!$C$7*Assumptions!$B$61+'Results Scenario B'!E10*Assumptions!$B$8*Assumptions!$C$8*Assumptions!$B$61+'Results Scenario B'!F10*Assumptions!$B$9*Assumptions!$C$9*Assumptions!$B$61+'Results Scenario B'!G10*Assumptions!$B$10*Assumptions!$C$10*Assumptions!$B$61+'Results Scenario B'!H10*Assumptions!$B$11*Assumptions!$C$11*Assumptions!$B$61) -> 0.031602333 | Q49: ='Results Scenario B'!C11*Assumptions!$B$6*Assumptions!$C$6*Assumptions!$B$61*(1-Assumptions!$D$6)*Assumptions!$B$89/Assumptions!$B$6/('Results Scenario B'!C11*Assumptions!$B$6*Assumptions!$C$6*Assumptions!$B$61+'Results Scenario B'!D11*Assumptions!$B$7*Assumptions!$C$7*Assumptions!$B$61+'Results Scenario B'!E11*Assumptions!$B$8*Assumptions!$C$8*Assumptions!$B$61+'Results Scenario B'!F11*Assumptions!$B$9*Assumptions!$C$9*Assumptions!$B$61+'Results Scenario B'!G11*Assumptions!$B$10*Assumptions!$C$10*Assumptions!$B$61+'Results Scenario B'!H11*Assumptions!$B$11*Assumptions!$C$11*Assumptions!$B$61) -> 0.033121152 | R49: ='Results Scenario B'!C12*Assumptions!$B$6*Assumptions!$C$6*Assumptions!$B$61*(1-Assumptions!$D$6)*Assumptions!$B$89/Assumptions!$B$6/('Results Scenario B'!C12*Assumptions!$B$6*Assumptions!$C$6*Assumptions!$B$61+'Results Scenario B'!D12*Assumptions!$B$7*Assumptions!$C$7*Assumptions!$B$61+'Results Scenario B'!E12*Assumptions!$B$8*Assumptions!$C$8*Assumptions!$B$61+'Results Scenario B'!F12*Assumptions!$B$9*Assumptions!$C$9*Assumptions!$B$61+'Results Scenario B'!G12*Assumptions!$B$10*Assumptions!$C$10*Assumptions!$B$61+'Results Scenario B'!H12*Assumptions!$B$11*Assumptions!$C$11*Assumptions!$B$61) -> 0.034667671 | S49: ='Results Scenario B'!C13*Assumptions!$B$6*Assumptions!$C$6*Assumptions!$B$61*(1-Assumptions!$D$6)*Assumptions!$B$89/Assumptions!$B$6/('Results Scenario B'!C13*Assumptions!$B$6*Assumptions!$C$6*Assumptions!$B$61+'Results Scenario B'!D13*Assumptions!$B$7*Assumptions!$C$7*Assumptions!$B$61+'Results Scenario B'!E13*Assumptions!$B$8*Assumptions!$C$8*Assumptions!$B$61+'Results Scenario B'!F13*Assumptions!$B$9*Assumptions!$C$9*Assumptions!$B$61+'Results Scenario B'!G13*Assumptions!$B$10*Assumptions!$C$10*Assumptions!$B$61+'Results Scenario B'!H13*Assumptions!$B$11*Assumptions!$C$11*Assumptions!$B$61) -> 0.036231408 | T49: ='Results Scenario B'!C14*Assumptions!$B$6*Assumptions!$C$6*Assumptions!$B$61*(1-Assumptions!$D$6)*Assumptions!$B$89/Assumptions!$B$6/('Results Scenario B'!C14*Assumptions!$B$6*Assumptions!$C$6*Assumptions!$B$61+'Results Scenario B'!D14*Assumptions!$B$7*Assumptions!$C$7*Assumptions!$B$61+'Results Scenario B'!E14*Assumptions!$B$8*Assumptions!$C$8*Assumptions!$B$61+'Results Scenario B'!F14*Assumptions!$B$9*Assumptions!$C$9*Assumptions!$B$61+'Results Scenario B'!G14*Assumptions!$B$10*Assumptions!$C$10*Assumptions!$B$61+'Results Scenario B'!H14*Assumptions!$B$11*Assumptions!$C$11*Assumptions!$B$61) -> 0.037797925 | U49: ='Results Scenario B'!C15*Assumptions!$B$6*Assumptions!$C$6*Assumptions!$B$61*(1-Assumptions!$D$6)*Assumptions!$B$89/Assumptions!$B$6/('Results Scenario B'!C15*Assumptions!$B$6*Assumptions!$C$6*Assumptions!$B$61+'Results Scenario B'!D15*Assumptions!$B$7*Assumptions!$C$7*Assumptions!$B$61+'Results Scenario B'!E15*Assumptions!$B$8*Assumptions!$C$8*Assumptions!$B$61+'Results Scenario B'!F15*Assumptions!$B$9*Assumptions!$C$9*Assumptions!$B$61+'Results Scenario B'!G15*Assumptions!$B$10*Assumptions!$C$10*Assumptions!$B$61+'Results Scenario B'!H15*Assumptions!$B$11*Assumptions!$C$11*Assumptions!$B$61) -> 0.039347756 | V49: ='Results Scenario B'!C16*Assumptions!$B$6*Assumptions!$C$6*Assumptions!$B$61*(1-Assumptions!$D$6)*Assumptions!$B$89/Assumptions!$B$6/('Results Scenario B'!C16*Assumptions!$B$6*Assumptions!$C$6*Assumptions!$B$61+'Results Scenario B'!D16*Assumptions!$B$7*Assumptions!$C$7*Assumptions!$B$61+'Results Scenario B'!E16*Assumptions!$B$8*Assumptions!$C$8*Assumptions!$B$61+'Results Scenario B'!F16*Assumptions!$B$9*Assumptions!$C$9*Assumptions!$B$61+'Results Scenario B'!G16*Assumptions!$B$10*Assumptions!$C$10*Assumptions!$B$61+'Results Scenario B'!H16*Assumptions!$B$11*Assumptions!$C$11*Assumptions!$B$61) -> 0.040855282 | W49: ='Results Scenario B'!C17*Assumptions!$B$6*Assumptions!$C$6*Assumptions!$B$61*(1-Assumptions!$D$6)*Assumptions!$B$89/Assumptions!$B$6/('Results Scenario B'!C17*Assumptions!$B$6*Assumptions!$C$6*Assumptions!$B$61+'Results Scenario B'!D17*Assumptions!$B$7*Assumptions!$C$7*Assumptions!$B$61+'Results Scenario B'!E17*Assumptions!$B$8*Assumptions!$C$8*Assumptions!$B$61+'Results Scenario B'!F17*Assumptions!$B$9*Assumptions!$C$9*Assumptions!$B$61+'Results Scenario B'!G17*Assumptions!$B$10*Assumptions!$C$10*Assumptions!$B$61+'Results Scenario B'!H17*Assumptions!$B$11*Assumptions!$C$11*Assumptions!$B$61) -> 0.042287718 | X49: ='Results Scenario B'!C18*Assumptions!$B$6*Assumptions!$C$6*Assumptions!$B$61*(1-Assumptions!$D$6)*Assumptions!$B$89/Assumptions!$B$6/('Results Scenario B'!C18*Assumptions!$B$6*Assumptions!$C$6*Assumptions!$B$61+'Results Scenario B'!D18*Assumptions!$B$7*Assumptions!$C$7*Assumptions!$B$61+'Results Scenario B'!E18*Assumptions!$B$8*Assumptions!$C$8*Assumptions!$B$61+'Results Scenario B'!F18*Assumptions!$B$9*Assumptions!$C$9*Assumptions!$B$61+'Results Scenario B'!G18*Assumptions!$B$10*Assumptions!$C$10*Assumptions!$B$61+'Results Scenario B'!H18*Assumptions!$B$11*Assumptions!$C$11*Assumptions!$B$61) -> 0.043604554 | Y49: ='Results Scenario B'!C19*Assumptions!$B$6*Assumptions!$C$6*Assumptions!$B$61*(1-Assumptions!$D$6)*Assumptions!$B$89/Assumptions!$B$6/('Results Scenario B'!C19*Assumptions!$B$6*Assumptions!$C$6*Assumptions!$B$61+'Results Scenario B'!D19*Assumptions!$B$7*Assumptions!$C$7*Assumptions!$B$61+'Results Scenario B'!E19*Assumptions!$B$8*Assumptions!$C$8*Assumptions!$B$61+'Results Scenario B'!F19*Assumptions!$B$9*Assumptions!$C$9*Assumptions!$B$61+'Results Scenario B'!G19*Assumptions!$B$10*Assumptions!$C$10*Assumptions!$B$61+'Results Scenario B'!H19*Assumptions!$B$11*Assumptions!$C$11*Assumptions!$B$61) -> 0.044757945 | Z49: ='Results Scenario B'!C20*Assumptions!$B$6*Assumptions!$C$6*Assumptions!$B$61*(1-Assumptions!$D$6)*Assumptions!$B$89/Assumptions!$B$6/('Results Scenario B'!C20*Assumptions!$B$6*Assumptions!$C$6*Assumptions!$B$61+'Results Scenario B'!D20*Assumptions!$B$7*Assumptions!$C$7*Assumptions!$B$61+'Results Scenario B'!E20*Assumptions!$B$8*Assumptions!$C$8*Assumptions!$B$61+'Results Scenario B'!F20*Assumptions!$B$9*Assumptions!$C$9*Assumptions!$B$61+'Results Scenario B'!G20*Assumptions!$B$10*Assumptions!$C$10*Assumptions!$B$61+'Results Scenario B'!H20*Assumptions!$B$11*Assumptions!$C$11*Assumptions!$B$61) -> 0.045694683 | AA49: ='Results Scenario B'!C21*Assumptions!$B$6*Assumptions!$C$6*Assumptions!$B$61*(1-Assumptions!$D$6)*Assumptions!$B$89/Assumptions!$B$6/('Results Scenario B'!C21*Assumptions!$B$6*Assumptions!$C$6*Assumptions!$B$61+'Results Scenario B'!D21*Assumptions!$B$7*Assumptions!$C$7*Assumptions!$B$61+'Results Scenario B'!E21*Assumptions!$B$8*Assumptions!$C$8*Assumptions!$B$61+'Results Scenario B'!F21*Assumptions!$B$9*Assumptions!$C$9*Assumptions!$B$61+'Results Scenario B'!G21*Assumptions!$B$10*Assumptions!$C$10*Assumptions!$B$61+'Results Scenario B'!H21*Assumptions!$B$11*Assumptions!$C$11*Assumptions!$B$61) -> 0.046360339 | AB49: ='Results Scenario B'!C22*Assumptions!$B$6*Assumptions!$C$6*Assumptions!$B$61*(1-Assumptions!$D$6)*Assumptions!$B$89/Assumptions!$B$6/('Results Scenario B'!C22*Assumptions!$B$6*Assumptions!$C$6*Assumptions!$B$61+'Results Scenario B'!D22*Assumptions!$B$7*Assumptions!$C$7*Assumptions!$B$61+'Results Scenario B'!E22*Assumptions!$B$8*Assumptions!$C$8*Assumptions!$B$61+'Results Scenario B'!F22*Assumptions!$B$9*Assumptions!$C$9*Assumptions!$B$61+'Results Scenario B'!G22*Assumptions!$B$10*Assumptions!$C$10*Assumptions!$B$61+'Results Scenario B'!H22*Assumptions!$B$11*Assumptions!$C$11*Assumptions!$B$61) -> 0.04670581 | AC49: ='Results Scenario B'!C23*Assumptions!$B$6*Assumptions!$C$6*Assumptions!$B$61*(1-Assumptions!$D$6)*Assumptions!$B$89/Assumptions!$B$6/('Results Scenario B'!C23*Assumptions!$B$6*Assumptions!$C$6*Assumptions!$B$61+'Results Scenario B'!D23*Assumptions!$B$7*Assumptions!$C$7*Assumptions!$B$61+'Results Scenario B'!E23*Assumptions!$B$8*Assumptions!$C$8*Assumptions!$B$61+'Results Scenario B'!F23*Assumptions!$B$9*Assumptions!$C$9*Assumptions!$B$61+'Results Scenario B'!G23*Assumptions!$B$10*Assumptions!$C$10*Assumptions!$B$61+'Results Scenario B'!H23*Assumptions!$B$11*Assumptions!$C$11*Assumptions!$B$61) -> 0.046695671 | AD49: ='Results Scenario B'!C24*Assumptions!$B$6*Assumptions!$C$6*Assumptions!$B$61*(1-Assumptions!$D$6)*Assumptions!$B$89/Assumptions!$B$6/('Results Scenario B'!C24*Assumptions!$B$6*Assumptions!$C$6*Assumptions!$B$61+'Results Scenario B'!D24*Assumptions!$B$7*Assumptions!$C$7*Assumptions!$B$61+'Results Scenario B'!E24*Assumptions!$B$8*Assumptions!$C$8*Assumptions!$B$61+'Results Scenario B'!F24*Assumptions!$B$9*Assumptions!$C$9*Assumptions!$B$61+'Results Scenario B'!G24*Assumptions!$B$10*Assumptions!$C$10*Assumptions!$B$61+'Results Scenario B'!H24*Assumptions!$B$11*Assumptions!$C$11*Assumptions!$B$61) -> 0.046316608 | AE49: ='Results Scenario B'!C25*Assumptions!$B$6*Assumptions!$C$6*Assumptions!$B$61*(1-Assumptions!$D$6)*Assumptions!$B$89/Assumptions!$B$6/('Results Scenario B'!C25*Assumptions!$B$6*Assumptions!$C$6*Assumptions!$B$61+'Results Scenario B'!D25*Assumptions!$B$7*Assumptions!$C$7*Assumptions!$B$61+'Results Scenario B'!E25*Assumptions!$B$8*Assumptions!$C$8*Assumptions!$B$61+'Results Scenario B'!F25*Assumptions!$B$9*Assumptions!$C$9*Assumptions!$B$61+'Results Scenario B'!G25*Assumptions!$B$10*Assumptions!$C$10*Assumptions!$B$61+'Results Scenario B'!H25*Assumptions!$B$11*Assumptions!$C$11*Assumptions!$B$61) -> 0.045583313 | AF49: ='Results Scenario B'!C26*Assumptions!$B$6*Assumptions!$C$6*Assumptions!$B$61*(1-Assumptions!$D$6)*Assumptions!$B$89/Assumptions!$B$6/('Results Scenario B'!C26*Assumptions!$B$6*Assumptions!$C$6*Assumptions!$B$61+'Results Scenario B'!D26*Assumptions!$B$7*Assumptions!$C$7*Assumptions!$B$61+'Results Scenario B'!E26*Assumptions!$B$8*Assumptions!$C$8*Assumptions!$B$61+'Results Scenario B'!F26*Assumptions!$B$9*Assumptions!$C$9*Assumptions!$B$61+'Results Scenario B'!G26*Assumptions!$B$10*Assumptions!$C$10*Assumptions!$B$61+'Results Scenario B'!H26*Assumptions!$B$11*Assumptions!$C$11*Assumptions!$B$61) -> 0.044539279 | AG49: ='Results Scenario B'!C27*Assumptions!$B$6*Assumptions!$C$6*Assumptions!$B$61*(1-Assumptions!$D$6)*Assumptions!$B$89/Assumptions!$B$6/('Results Scenario B'!C27*Assumptions!$B$6*Assumptions!$C$6*Assumptions!$B$61+'Results Scenario B'!D27*Assumptions!$B$7*Assumptions!$C$7*Assumptions!$B$61+'Results Scenario B'!E27*Assumptions!$B$8*Assumptions!$C$8*Assumptions!$B$61+'Results Scenario B'!F27*Assumptions!$B$9*Assumptions!$C$9*Assumptions!$B$61+'Results Scenario B'!G27*Assumptions!$B$10*Assumptions!$C$10*Assumptions!$B$61+'Results Scenario B'!H27*Assumptions!$B$11*Assumptions!$C$11*Assumptions!$B$61) -> 0.043251465 | AH49: ='Results Scenario B'!C28*Assumptions!$B$6*Assumptions!$C$6*Assumptions!$B$61*(1-Assumptions!$D$6)*Assumptions!$B$89/Assumptions!$B$6/('Results Scenario B'!C28*Assumptions!$B$6*Assumptions!$C$6*Assumptions!$B$61+'Results Scenario B'!D28*Assumptions!$B$7*Assumptions!$C$7*Assumptions!$B$61+'Results Scenario B'!E28*Assumptions!$B$8*Assumptions!$C$8*Assumptions!$B$61+'Results Scenario B'!F28*Assumptions!$B$9*Assumptions!$C$9*Assumptions!$B$61+'Results Scenario B'!G28*Assumptions!$B$10*Assumptions!$C$10*Assumptions!$B$61+'Results Scenario B'!H28*Assumptions!$B$11*Assumptions!$C$11*Assumptions!$B$61) -> 0.041800094 | AI49: ='Results Scenario B'!C29*Assumptions!$B$6*Assumptions!$C$6*Assumptions!$B$61*(1-Assumptions!$D$6)*Assumptions!$B$89/Assumptions!$B$6/('Results Scenario B'!C29*Assumptions!$B$6*Assumptions!$C$6*Assumptions!$B$61+'Results Scenario B'!D29*Assumptions!$B$7*Assumptions!$C$7*Assumptions!$B$61+'Results Scenario B'!E29*Assumptions!$B$8*Assumptions!$C$8*Assumptions!$B$61+'Results Scenario B'!F29*Assumptions!$B$9*Assumptions!$C$9*Assumptions!$B$61+'Results Scenario B'!G29*Assumptions!$B$10*Assumptions!$C$10*Assumptions!$B$61+'Results Scenario B'!H29*Assumptions!$B$11*Assumptions!$C$11*Assumptions!$B$61) -> 0.040266774 | AJ49: ='Results Scenario B'!C30*Assumptions!$B$6*Assumptions!$C$6*Assumptions!$B$61*(1-Assumptions!$D$6)*Assumptions!$B$89/Assumptions!$B$6/('Results Scenario B'!C30*Assumptions!$B$6*Assumptions!$C$6*Assumptions!$B$61+'Results Scenario B'!D30*Assumptions!$B$7*Assumptions!$C$7*Assumptions!$B$61+'Results Scenario B'!E30*Assumptions!$B$8*Assumptions!$C$8*Assumptions!$B$61+'Results Scenario B'!F30*Assumptions!$B$9*Assumptions!$C$9*Assumptions!$B$61+'Results Scenario B'!G30*Assumptions!$B$10*Assumptions!$C$10*Assumptions!$B$61+'Results Scenario B'!H30*Assumptions!$B$11*Assumptions!$C$11*Assumptions!$B$61) -> 0.038724391 | AK49: ='Results Scenario B'!C31*Assumptions!$B$6*Assumptions!$C$6*Assumptions!$B$61*(1-Assumptions!$D$6)*Assumptions!$B$89/Assumptions!$B$6/('Results Scenario B'!C31*Assumptions!$B$6*Assumptions!$C$6*Assumptions!$B$61+'Results Scenario B'!D31*Assumptions!$B$7*Assumptions!$C$7*Assumptions!$B$61+'Results Scenario B'!E31*Assumptions!$B$8*Assumptions!$C$8*Assumptions!$B$61+'Results Scenario B'!F31*Assumptions!$B$9*Assumptions!$C$9*Assumptions!$B$61+'Results Scenario B'!G31*Assumptions!$B$10*Assumptions!$C$10*Assumptions!$B$61+'Results Scenario B'!H31*Assumptions!$B$11*Assumptions!$C$11*Assumptions!$B$61) -> 0.037230924 | AL49: ='Results Scenario B'!C32*Assumptions!$B$6*Assumptions!$C$6*Assumptions!$B$61*(1-Assumptions!$D$6)*Assumptions!$B$89/Assumptions!$B$6/('Results Scenario B'!C32*Assumptions!$B$6*Assumptions!$C$6*Assumptions!$B$61+'Results Scenario B'!D32*Assumptions!$B$7*Assumptions!$C$7*Assumptions!$B$61+'Results Scenario B'!E32*Assumptions!$B$8*Assumptions!$C$8*Assumptions!$B$61+'Results Scenario B'!F32*Assumptions!$B$9*Assumptions!$C$9*Assumptions!$B$61+'Results Scenario B'!G32*Assumptions!$B$10*Assumptions!$C$10*Assumptions!$B$61+'Results Scenario B'!H32*Assumptions!$B$11*Assumptions!$C$11*Assumptions!$B$61) -> 0.035827486 | AM49: ='Results Scenario B'!C33*Assumptions!$B$6*Assumptions!$C$6*Assumptions!$B$61*(1-Assumptions!$D$6)*Assumptions!$B$89/Assumptions!$B$6/('Results Scenario B'!C33*Assumptions!$B$6*Assumptions!$C$6*Assumptions!$B$61+'Results Scenario B'!D33*Assumptions!$B$7*Assumptions!$C$7*Assumptions!$B$61+'Results Scenario B'!E33*Assumptions!$B$8*Assumptions!$C$8*Assumptions!$B$61+'Results Scenario B'!F33*Assumptions!$B$9*Assumptions!$C$9*Assumptions!$B$61+'Results Scenario B'!G33*Assumptions!$B$10*Assumptions!$C$10*Assumptions!$B$61+'Results Scenario B'!H33*Assumptions!$B$11*Assumptions!$C$11*Assumptions!$B$61) -> 0.034539515 | AN49: ='Results Scenario B'!C34*Assumptions!$B$6*Assumptions!$C$6*Assumptions!$B$61*(1-Assumptions!$D$6)*Assumptions!$B$89/Assumptions!$B$6/('Results Scenario B'!C34*Assumptions!$B$6*Assumptions!$C$6*Assumptions!$B$61+'Results Scenario B'!D34*Assumptions!$B$7*Assumptions!$C$7*Assumptions!$B$61+'Results Scenario B'!E34*Assumptions!$B$8*Assumptions!$C$8*Assumptions!$B$61+'Results Scenario B'!F34*Assumptions!$B$9*Assumptions!$C$9*Assumptions!$B$61+'Results Scenario B'!G34*Assumptions!$B$10*Assumptions!$C$10*Assumptions!$B$61+'Results Scenario B'!H34*Assumptions!$B$11*Assumptions!$C$11*Assumptions!$B$61) -> 0.033379637 | AO49: ='Results Scenario B'!C35*Assumptions!$B$6*Assumptions!$C$6*Assumptions!$B$61*(1-Assumptions!$D$6)*Assumptions!$B$89/Assumptions!$B$6/('Results Scenario B'!C35*Assumptions!$B$6*Assumptions!$C$6*Assumptions!$B$61+'Results Scenario B'!D35*Assumptions!$B$7*Assumptions!$C$7*Assumptions!$B$61+'Results Scenario B'!E35*Assumptions!$B$8*Assumptions!$C$8*Assumptions!$B$61+'Results Scenario B'!F35*Assumptions!$B$9*Assumptions!$C$9*Assumptions!$B$61+'Results Scenario B'!G35*Assumptions!$B$10*Assumptions!$C$10*Assumptions!$B$61+'Results Scenario B'!H35*Assumptions!$B$11*Assumptions!$C$11*Assumptions!$B$61) -> 0.03235094 | AP49: ='Results Scenario B'!C36*Assumptions!$B$6*Assumptions!$C$6*Assumptions!$B$61*(1-Assumptions!$D$6)*Assumptions!$B$89/Assumptions!$B$6/('Results Scenario B'!C36*Assumptions!$B$6*Assumptions!$C$6*Assumptions!$B$61+'Results Scenario B'!D36*Assumptions!$B$7*Assumptions!$C$7*Assumptions!$B$61+'Results Scenario B'!E36*Assumptions!$B$8*Assumptions!$C$8*Assumptions!$B$61+'Results Scenario B'!F36*Assumptions!$B$9*Assumptions!$C$9*Assumptions!$B$61+'Results Scenario B'!G36*Assumptions!$B$10*Assumptions!$C$10*Assumptions!$B$61+'Results Scenario B'!H36*Assumptions!$B$11*Assumptions!$C$11*Assumptions!$B$61) -> 0.031449954 | AQ49: ='Results Scenario B'!C37*Assumptions!$B$6*Assumptions!$C$6*Assumptions!$B$61*(1-Assumptions!$D$6)*Assumptions!$B$89/Assumptions!$B$6/('Results Scenario B'!C37*Assumptions!$B$6*Assumptions!$C$6*Assumptions!$B$61+'Results Scenario B'!D37*Assumptions!$B$7*Assumptions!$C$7*Assumptions!$B$61+'Results Scenario B'!E37*Assumptions!$B$8*Assumptions!$C$8*Assumptions!$B$61+'Results Scenario B'!F37*Assumptions!$B$9*Assumptions!$C$9*Assumptions!$B$61+'Results Scenario B'!G37*Assumptions!$B$10*Assumptions!$C$10*Assumptions!$B$61+'Results Scenario B'!H37*Assumptions!$B$11*Assumptions!$C$11*Assumptions!$B$61) -> 0.030669034 | AR49: ='Results Scenario B'!C38*Assumptions!$B$6*Assumptions!$C$6*Assumptions!$B$61*(1-Assumptions!$D$6)*Assumptions!$B$89/Assumptions!$B$6/('Results Scenario B'!C38*Assumptions!$B$6*Assumptions!$C$6*Assumptions!$B$61+'Results Scenario B'!D38*Assumptions!$B$7*Assumptions!$C$7*Assumptions!$B$61+'Results Scenario B'!E38*Assumptions!$B$8*Assumptions!$C$8*Assumptions!$B$61+'Results Scenario B'!F38*Assumptions!$B$9*Assumptions!$C$9*Assumptions!$B$61+'Results Scenario B'!G38*Assumptions!$B$10*Assumptions!$C$10*Assumptions!$B$61+'Results Scenario B'!H38*Assumptions!$B$11*Assumptions!$C$11*Assumptions!$B$61) -> 0.029998145 | AS49: ='Results Scenario B'!C39*Assumptions!$B$6*Assumptions!$C$6*Assumptions!$B$61*(1-Assumptions!$D$6)*Assumptions!$B$89/Assumptions!$B$6/('Results Scenario B'!C39*Assumptions!$B$6*Assumptions!$C$6*Assumptions!$B$61+'Results Scenario B'!D39*Assumptions!$B$7*Assumptions!$C$7*Assumptions!$B$61+'Results Scenario B'!E39*Assumptions!$B$8*Assumptions!$C$8*Assumptions!$B$61+'Results Scenario B'!F39*Assumptions!$B$9*Assumptions!$C$9*Assumptions!$B$61+'Results Scenario B'!G39*Assumptions!$B$10*Assumptions!$C$10*Assumptions!$B$61+'Results Scenario B'!H39*Assumptions!$B$11*Assumptions!$C$11*Assumptions!$B$61) -> 0.029426126
I50: Hour 0 aggregate share | J50: =$B5*J$45+$C5*J$46+$D5*J$47+$E5*J$48+$F5*J$49 -> 0.074672417 | K50: =$B5*K$45+$C5*K$46+$D5*K$47+$E5*K$48+$F5*K$49 -> 0.073850407 | L50: =$B5*L$45+$C5*L$46+$D5*L$47+$E5*L$48+$F5*L$49 -> 0.073028347 | M50: =$B5*M$45+$C5*M$46+$D5*M$47+$E5*M$48+$F5*M$49 -> 0.072207689 | N50: =$B5*N$45+$C5*N$46+$D5*N$47+$E5*N$48+$F5*N$49 -> 0.071390042 | O50: =$B5*O$45+$C5*O$46+$D5*O$47+$E5*O$48+$F5*O$49 -> 0.070577217 | P50: =$B5*P$45+$C5*P$46+$D5*P$47+$E5*P$48+$F5*P$49 -> 0.069771276 | Q50: =$B5*Q$45+$C5*Q$46+$D5*Q$47+$E5*Q$48+$F5*Q$49 -> 0.068974595 | ... AS50: =$B5*AS$45+$C5*AS$46+$D5*AS$47+$E5*AS$48+$F5*AS$49 -> 0.068516558
I51: Hour 1 aggregate share | J51: =$B6*J$45+$C6*J$46+$D6*J$47+$E6*J$48+$F6*J$49 -> 0.074672417 | K51: =$B6*K$45+$C6*K$46+$D6*K$47+$E6*K$48+$F6*K$49 -> 0.073850407 | L51: =$B6*L$45+$C6*L$46+$D6*L$47+$E6*L$48+$F6*L$49 -> 0.073028347 | M51: =$B6*M$45+$C6*M$46+$D6*M$47+$E6*M$48+$F6*M$49 -> 0.072207689 | N51: =$B6*N$45+$C6*N$46+$D6*N$47+$E6*N$48+$F6*N$49 -> 0.071390042 | O51: =$B6*O$45+$C6*O$46+$D6*O$47+$E6*O$48+$F6*O$49 -> 0.070577217 | P51: =$B6*P$45+$C6*P$46+$D6*P$47+$E6*P$48+$F6*P$49 -> 0.069771276 | Q51: =$B6*Q$45+$C6*Q$46+$D6*Q$47+$E6*Q$48+$F6*Q$49 -> 0.068974595 | ... AS51: =$B6*AS$45+$C6*AS$46+$D6*AS$47+$E6*AS$48+$F6*AS$49 -> 0.068516558
I52: Hour 2 aggregate share | J52: =$B7*J$45+$C7*J$46+$D7*J$47+$E7*J$48+$F7*J$49 -> 0.074672417 | K52: =$B7*K$45+$C7*K$46+$D7*K$47+$E7*K$48+$F7*K$49 -> 0.073850407 | L52: =$B7*L$45+$C7*L$46+$D7*L$47+$E7*L$48+$F7*L$49 -> 0.073028347 | M52: =$B7*M$45+$C7*M$46+$D7*M$47+$E7*M$48+$F7*M$49 -> 0.072207689 | N52: =$B7*N$45+$C7*N$46+$D7*N$47+$E7*N$48+$F7*N$49 -> 0.071390042 | O52: =$B7*O$45+$C7*O$46+$D7*O$47+$E7*O$48+$F7*O$49 -> 0.070577217 | P52: =$B7*P$45+$C7*P$46+$D7*P$47+$E7*P$48+$F7*P$49 -> 0.069771276 | Q52: =$B7*Q$45+$C7*Q$46+$D7*Q$47+$E7*Q$48+$F7*Q$49 -> 0.068974595 | ... AS52: =$B7*AS$45+$C7*AS$46+$D7*AS$47+$E7*AS$48+$F7*AS$49 -> 0.068516558
I53: Hour 3 aggregate share | J53: =$B8*J$45+$C8*J$46+$D8*J$47+$E8*J$48+$F8*J$49 -> 0.074672417 | K53: =$B8*K$45+$C8*K$46+$D8*K$47+$E8*K$48+$F8*K$49 -> 0.073850407 | L53: =$B8*L$45+$C8*L$46+$D8*L$47+$E8*L$48+$F8*L$49 -> 0.073028347 | M53: =$B8*M$45+$C8*M$46+$D8*M$47+$E8*M$48+$F8*M$49 -> 0.072207689 | N53: =$B8*N$45+$C8*N$46+$D8*N$47+$E8*N$48+$F8*N$49 -> 0.071390042 | O53: =$B8*O$45+$C8*O$46+$D8*O$47+$E8*O$48+$F8*O$49 -> 0.070577217 | P53: =$B8*P$45+$C8*P$46+$D8*P$47+$E8*P$48+$F8*P$49 -> 0.069771276 | Q53: =$B8*Q$45+$C8*Q$46+$D8*Q$47+$E8*Q$48+$F8*Q$49 -> 0.068974595 | ... AS53: =$B8*AS$45+$C8*AS$46+$D8*AS$47+$E8*AS$48+$F8*AS$49 -> 0.068516558
I54: Hour 4 aggregate share | J54: =$B9*J$45+$C9*J$46+$D9*J$47+$E9*J$48+$F9*J$49 -> 0.074672417 | K54: =$B9*K$45+$C9*K$46+$D9*K$47+$E9*K$48+$F9*K$49 -> 0.073850407 | L54: =$B9*L$45+$C9*L$46+$D9*L$47+$E9*L$48+$F9*L$49 -> 0.073028347 | M54: =$B9*M$45+$C9*M$46+$D9*M$47+$E9*M$48+$F9*M$49 -> 0.072207689 | N54: =$B9*N$45+$C9*N$46+$D9*N$47+$E9*N$48+$F9*N$49 -> 0.071390042 | O54: =$B9*O$45+$C9*O$46+$D9*O$47+$E9*O$48+$F9*O$49 -> 0.070577217 | P54: =$B9*P$45+$C9*P$46+$D9*P$47+$E9*P$48+$F9*P$49 -> 0.069771276 | Q54: =$B9*Q$45+$C9*Q$46+$D9*Q$47+$E9*Q$48+$F9*Q$49 -> 0.068974595 | ... AS54: =$B9*AS$45+$C9*AS$46+$D9*AS$47+$E9*AS$48+$F9*AS$49 -> 0.068516558
I55: Hour 5 aggregate share | J55: =$B10*J$45+$C10*J$46+$D10*J$47+$E10*J$48+$F10*J$49 -> 0.06923308 | K55: =$B10*K$45+$C10*K$46+$D10*K$47+$E10*K$48+$F10*K$49 -> 0.06852262 | L55: =$B10*L$45+$C10*L$46+$D10*L$47+$E10*L$48+$F10*L$49 -> 0.067812498 | M55: =$B10*M$45+$C10*M$46+$D10*M$47+$E10*M$48+$F10*M$49 -> 0.067103982 | N55: =$B10*N$45+$C10*N$46+$D10*N$47+$E10*N$48+$F10*N$49 -> 0.066398473 | O55: =$B10*O$45+$C10*O$46+$D10*O$47+$E10*O$48+$F10*O$49 -> 0.065697541 | P55: =$B10*P$45+$C10*P$46+$D10*P$47+$E10*P$48+$F10*P$49 -> 0.065002964 | Q55: =$B10*Q$45+$C10*Q$46+$D10*Q$47+$E10*Q$48+$F10*Q$49 -> 0.064316785 | ... AS55: =$B10*AS$45+$C10*AS$46+$D10*AS$47+$E10*AS$48+$F10*AS$49 -> 0.063879872
I56: Hour 6 aggregate share | J56: =$B11*J$45+$C11*J$46+$D11*J$47+$E11*J$48+$F11*J$49 -> 0.034865495 | K56: =$B11*K$45+$C11*K$46+$D11*K$47+$E11*K$48+$F11*K$49 -> 0.034769942 | L56: =$B11*L$45+$C11*L$46+$D11*L$47+$E11*L$48+$F11*L$49 -> 0.034675803 | M56: =$B11*M$45+$C11*M$46+$D11*M$47+$E11*M$48+$F11*M$49 -> 0.034583291 | N56: =$B11*N$45+$C11*N$46+$D11*N$47+$E11*N$48+$F11*N$49 -> 0.034492629 | O56: =$B11*O$45+$C11*O$46+$D11*O$47+$E11*O$48+$F11*O$49 -> 0.034404044 | P56: =$B11*P$45+$C11*P$46+$D11*P$47+$E11*P$48+$F11*P$49 -> 0.034317771 | Q56: =$B11*Q$45+$C11*Q$46+$D11*Q$47+$E11*Q$48+$F11*Q$49 -> 0.034234047 | ... AS56: =$B11*AS$45+$C11*AS$46+$D11*AS$47+$E11*AS$48+$F11*AS$49 -> 0.034105705
I57: Hour 7 aggregate share | J57: =$B12*J$45+$C12*J$46+$D12*J$47+$E12*J$48+$F12*J$49 -> 0.013685162 | K57: =$B12*K$45+$C12*K$46+$D12*K$47+$E12*K$48+$F12*K$49 -> 0.014025517 | L57: =$B12*L$45+$C12*L$46+$D12*L$47+$E12*L$48+$F12*L$49 -> 0.01436726 | M57: =$B12*M$45+$C12*M$46+$D12*M$47+$E12*M$48+$F12*M$49 -> 0.014709836 | N57: =$B12*N$45+$C12*N$46+$D12*N$47+$E12*N$48+$F12*N$49 -> 0.015052611 | O57: =$B12*O$45+$C12*O$46+$D12*O$47+$E12*O$48+$F12*O$49 -> 0.015394852 | P57: =$B12*P$45+$C12*P$46+$D12*P$47+$E12*P$48+$F12*P$49 -> 0.0157357 | Q57: =$B12*Q$45+$C12*Q$46+$D12*Q$47+$E12*Q$48+$F12*Q$49 -> 0.016074129 | ... AS57: =$B12*AS$45+$C12*AS$46+$D12*AS$47+$E12*AS$48+$F12*AS$49 -> 0.016167991
